Workbook

Sheet Dashboard
B1: CeraLux · Dashboard de rentabilidad
B2: Spray reparación de arañazos 120ml · contra reembolso · Ads: Meta (HeatioShop)
B3: Desde | C3: =DATE(YEAR(TODAY()),MONTH(TODAY()),1) -> 46296 | E3: Hasta | F3: =TODAY() -> 46318 | H3: Días | I3: =MAX(1,$F$3-$C$3+1) -> 23 | J3: Tasa entrega esperada | L3: =TASA_BE -> 0.6311281
B5: RESUMEN DEL PERIODO
B6: BENEFICIO NETO PROYECTADO | D6: LIQUIDACIÓN ALMACÉN | F6: BENEFICIO COBRADO (REAL) | H6: PEDIDOS | J6: FACTURACIÓN BRUTA | L6: GASTO ADS
B7: =F25 -> 528.87646 | D7: =SUMIFS(Diario!$W$6:$W$370,Diario!$A$6:$A$370,">="&$C$3,Diario!$A$6:$A$370,"<="&$F$3) -> 1828.0714 | F7: =SUMIFS(Diario!$X$6:$X$370,Diario!$A$6:$A$370,">="&$C$3,Diario!$A$6:$A$370,"<="&$F$3)+F24 -> 26.641437 | H7: =SUMIFS(Diario!$P$6:$P$370,Diario!$A$6:$A$370,">="&$C$3,Diario!$A$6:$A$370,"<="&$F$3) -> 159 | J7: =SUMIFS(Diario!$R$6:$R$370,Diario!$A$6:$A$370,">="&$C$3,Diario!$A$6:$A$370,"<="&$F$3) -> 5678.41 | L7: =SUMIFS(Diario!$N$6:$N$370,Diario!$A$6:$A$370,">="&$C$3,Diario!$A$6:$A$370,"<="&$F$3) -> 1393.68
B9: CPA (COSTE POR PEDIDO) | D9: CPA BREAK-EVEN | F9: ROAS | H9: ROAS BREAK-EVEN | J9: TICKET MEDIO | L9: % PACK 2 O PACK 3
B10: =IF(H7>0,L7/H7,"") -> 8.765283 | D10: =CPA_BE -> 11.851932 | F10: =IF(L7>0,J7/L7,"") -> 4.0744001 | H10: =ROAS_BE -> 3.0398196 | J10: =IF(H7>0,J7/H7,"") -> 35.71327 | L10: =IF(H7>0,(SUMIFS(Diario!$C$6:$C$370,Diario!$A$6:$A$370,">="&$C$3,Diario!$A$6:$A$370,"<="&$F$3)+SUMIFS(Diario!$D$6:$D$370,Diario!$A$6:$A$370,">="&$C$3,Diario!$A$6:$A$370,"<="&$F$3))/H7,"") -> 0.44025157
B12: ENTREGADOS | D12: PENDIENTES | F12: EN INCIDENCIA | H12: DEVUELTOS | J12: TASA DE ENTREGA | L12: SEMÁFORO CAMPAÑA
B13: =SUMIFS(Diario!$E$6:$E$370,Diario!$A$6:$A$370,">="&$C$3,Diario!$A$6:$A$370,"<="&$F$3)+SUMIFS(Diario!$F$6:$F$370,Diario!$A$6:$A$370,">="&$C$3,Diario!$A$6:$A$370,"<="&$F$3)+SUMIFS(Diario!$G$6:$G$370,Diario!$A$6:$A$370,">="&$C$3,Diario!$A$6:$A$370,"<="&$F$3) -> 74 | D13: =SUMIFS(Diario!$Q$6:$Q$370,Diario!$A$6:$A$370,">="&$C$3,Diario!$A$6:$A$370,"<="&$F$3) -> 51 | F13: =SUMIFS(Diario!$K$6:$K$370,Diario!$A$6:$A$370,">="&$C$3,Diario!$A$6:$A$370,"<="&$F$3) -> 29 | H13: =SUMIFS(Diario!$H$6:$H$370,Diario!$A$6:$A$370,">="&$C$3,Diario!$A$6:$A$370,"<="&$F$3)+SUMIFS(Diario!$I$6:$I$370,Diario!$A$6:$A$370,">="&$C$3,Diario!$A$6:$A$370,"<="&$F$3)+SUMIFS(Diario!$J$6:$J$370,Diario!$A$6:$A$370,">="&$C$3,Diario!$A$6:$A$370,"<="&$F$3) -> 34 | J13: =IF(B13+H13>0,B13/(B13+H13),"") -> 0.68518519 | L13: =IF(B10="","SIN DATOS",IF(B10<=D10*0.75,"ESCALAR",IF(B10<=D10,"VIGILAR","CORTAR"))) -> ESCALAR
B15: CUENTA DE RESULTADOS (proyectada) | H15: CAMINO A 10.000 €/MES
B16: Ventas esperadas (IVA incl.) | E16: % ventas | F16: =SUMIFS(Diario!$AH$6:$AH$370,Diario!$A$6:$A$370,">="&$C$3,Diario!$A$6:$A$370,"<="&$F$3) -> 3652.9904 | H16: Objetivo de beneficio neto mensual | L16: =OBJETIVO_MES -> 10000
B17: − Coste de producto | E17: =IF($F$16>0,F17/$F$16,"") -> -0.11308773 | F17: =-SUMIFS(Diario!$AI$6:$AI$370,Diario!$A$6:$A$370,">="&$C$3,Diario!$A$6:$A$370,"<="&$F$3) -> -413.10837 | H17: Beneficio neto por día (periodo) | L17: =F25/I3 -> 22.994629
B18: − Envíos | E18: =IF($F$16>0,F18/$F$16,"") -> -0.19804685 | F18: =-SUMIFS(Diario!$AJ$6:$AJ$370,Diario!$A$6:$A$370,">="&$C$3,Diario!$A$6:$A$370,"<="&$F$3) -> -723.46325 | H18: Ritmo a 30 días | L18: =L17*30 -> 689.83886
B19: − Devoluciones | E19: =IF($F$16>0,F19/$F$16,"") -> -0.12121912 | F19: =-SUMIFS(Diario!$AK$6:$AK$370,Diario!$A$6:$A$370,">="&$C$3,Diario!$A$6:$A$370,"<="&$F$3) -> -442.81227 | H19: % del objetivo | L19: =IF(L16>0,L18/L16,"") -> 0.068983886
B20: − Comisión almacén (0,95 €/pedido) | E20: =IF($F$16>0,F20/$F$16,"") -> -0.041349685 | F20: =-SUMIFS(Diario!$AO$6:$AO$370,Diario!$A$6:$A$370,">="&$C$3,Diario!$A$6:$A$370,"<="&$F$3) -> -151.05 | H20: Beneficio esperado por pedido (antes de Ads) | L20: =BEN_PEDIDO -> 11.851932
B21: − IVA a liquidar (neto) | E21: =IF($F$16>0,F21/$F$16,"") -> 0 | F21: =-SUMIFS(Diario!$AL$6:$AL$370,Diario!$A$6:$A$370,">="&$C$3,Diario!$A$6:$A$370,"<="&$F$3) -> 0 | H21: CPA actual | L21: =B10 -> 8.765283
B22: − Publicidad Meta | E22: =IF($F$16>0,F22/$F$16,"") -> -0.38151757 | F22: =-SUMIFS(Diario!$AM$6:$AM$370,Diario!$A$6:$A$370,">="&$C$3,Diario!$A$6:$A$370,"<="&$F$3) -> -1393.68 | H22: Margen por pedido después de Ads | L22: =IF(ISNUMBER(L21),L20-L21*(1+RECARGO_ADS),"") -> 3.0866491
B23: Beneficio de campaña | E23: =IF($F$16>0,F23/$F$16,"") -> 0.14477905 | F23: =SUM(F16:F22) -> 528.87646 | H23: Pedidos/día necesarios para el objetivo | L23: =IF(NOT(ISNUMBER(L22)),"",IF(L22<=0,"Baja el CPA",ROUNDUP((L16-F24/I3*30)/30/L22,0))) -> 108
B24: − Otros gastos | E24: =IF($F$16>0,F24/$F$16,"") -> 0 | F24: =-SUMIFS(Gastos!$D$5:$D$304,Gastos!$A$5:$A$304,">="&$C$3,Gastos!$A$5:$A$304,"<="&$F$3) -> 0 | H24: Inversión diaria en Ads a ese CPA | L24: =IF(ISNUMBER(L23),L23*L21,"") -> 946.65057
B25: BENEFICIO NETO | E25: =IF($F$16>0,F25/$F$16,"") -> 0.14477905 | F25: =F23+F24 -> 528.87646
B26: Margen neto sobre ventas | F26: =IF(F16>0,F25/F16,"") -> 0.14477905
B27: ÚLTIMOS 14 DÍAS (hasta la fecha 'Hasta')
B28: Fecha | C28: Pedidos | D28: Gasto Ads | E28: CPA | F28: Beneficio proyectado | G28: Tasa entrega
B29: =$F$3-13 -> 46305 | C29: =SUMIFS(Diario!$P$6:$P$370,Diario!$A$6:$A$370,$B29) -> 9 | D29: =SUMIFS(Diario!$N$6:$N$370,Diario!$A$6:$A$370,$B29) -> 64.81 | E29: =IF(C29>0,D29/C29,"") -> 7.2011111 | F29: =SUMIFS(Diario!$Y$6:$Y$370,Diario!$A$6:$A$370,$B29) -> -5.198066 | G29: =IF((SUMIFS(Diario!$E$6:$E$370,Diario!$A$6:$A$370,$B29)+SUMIFS(Diario!$F$6:$F$370,Diario!$A$6:$A$370,$B29)+SUMIFS(Diario!$G$6:$G$370,Diario!$A$6:$A$370,$B29)+SUMIFS(Diario!$H$6:$H$370,Diario!$A$6:$A$370,$B29)+SUMIFS(Diario!$I$6:$I$370,Diario!$A$6:$A$370,$B29)+SUMIFS(Diario!$J$6:$J$370,Diario!$A$6:$A$370,$B29))>0,(SUMIFS(Diario!$E$6:$E$370,Diario!$A$6:$A$370,$B29)+SUMIFS(Diario!$F$6:$F$370,Diario!$A$6:$A$370,$B29)+SUMIFS(Diario!$G$6:$G$370,Diario!$A$6:$A$370,$B29))/(SUMIFS(Diario!$E$6:$E$370,Diario!$A$6:$A$370,$B29)+SUMIFS(Diario!$F$6:$F$370,Diario!$A$6:$A$370,$B29)+SUMIFS(Diario!$G$6:$G$370,Diario!$A$6:$A$370,$B29)+SUMIFS(Diario!$H$6:$H$370,Diario!$A$6:$A$370,$B29)+SUMIFS(Diario!$I$6:$I$370,Diario!$A$6:$A$370,$B29)+SUMIFS(Diario!$J$6:$J$370,Diario!$A$6:$A$370,$B29)),"") -> 0.5
B30: =$F$3-12 -> 46306 | C30: =SUMIFS(Diario!$P$6:$P$370,Diario!$A$6:$A$370,$B30) -> 6 | D30: =SUMIFS(Diario!$N$6:$N$370,Diario!$A$6:$A$370,$B30) -> 89.51 | E30: =IF(C30>0,D30/C30,"") -> 14.918333 | F30: =SUMIFS(Diario!$Y$6:$Y$370,Diario!$A$6:$A$370,$B30) -> -112.2279 | G30: =IF((SUMIFS(Diario!$E$6:$E$370,Diario!$A$6:$A$370,$B30)+SUMIFS(Diario!$F$6:$F$370,Diario!$A$6:$A$370,$B30)+SUMIFS(Diario!$G$6:$G$370,Diario!$A$6:$A$370,$B30)+SUMIFS(Diario!$H$6:$H$370,Diario!$A$6:$A$370,$B30)+SUMIFS(Diario!$I$6:$I$370,Diario!$A$6:$A$370,$B30)+SUMIFS(Diario!$J$6:$J$370,Diario!$A$6:$A$370,$B30))>0,(SUMIFS(Diario!$E$6:$E$370,Diario!$A$6:$A$370,$B30)+SUMIFS(Diario!$F$6:$F$370,Diario!$A$6:$A$370,$B30)+SUMIFS(Diario!$G$6:$G$370,Diario!$A$6:$A$370,$B30))/(SUMIFS(Diario!$E$6:$E$370,Diario!$A$6:$A$370,$B30)+SUMIFS(Diario!$F$6:$F$370,Diario!$A$6:$A$370,$B30)+SUMIFS(Diario!$G$6:$G$370,Diario!$A$6:$A$370,$B30)+SUMIFS(Diario!$H$6:$H$370,Diario!$A$6:$A$370,$B30)+SUMIFS(Diario!$I$6:$I$370,Diario!$A$6:$A$370,$B30)+SUMIFS(Diario!$J$6:$J$370,Diario!$A$6:$A$370,$B30)),"") -> 0.16666667
B31: =$F$3-11 -> 46307 | C31: =SUMIFS(Diario!$P$6:$P$370,Diario!$A$6:$A$370,$B31) -> 14 | D31: =SUMIFS(Diario!$N$6:$N$370,Diario!$A$6:$A$370,$B31) -> 78.33 | E31: =IF(C31>0,D31/C31,"") -> 5.595 | F31: =SUMIFS(Diario!$Y$6:$Y$370,Diario!$A$6:$A$370,$B31) -> 49.015501 | G31: =IF((SUMIFS(Diario!$E$6:$E$370,Diario!$A$6:$A$370,$B31)+SUMIFS(Diario!$F$6:$F$370,Diario!$A$6:$A$370,$B31)+SUMIFS(Diario!$G$6:$G$370,Diario!$A$6:$A$370,$B31)+SUMIFS(Diario!$H$6:$H$370,Diario!$A$6:$A$370,$B31)+SUMIFS(Diario!$I$6:$I$370,Diario!$A$6:$A$370,$B31)+SUMIFS(Diario!$J$6:$J$370,Diario!$A$6:$A$370,$B31))>0,(SUMIFS(Diario!$E$6:$E$370,Diario!$A$6:$A$370,$B31)+SUMIFS(Diario!$F$6:$F$370,Diario!$A$6:$A$370,$B31)+SUMIFS(Diario!$G$6:$G$370,Diario!$A$6:$A$370,$B31))/(SUMIFS(Diario!$E$6:$E$370,Diario!$A$6:$A$370,$B31)+SUMIFS(Diario!$F$6:$F$370,Diario!$A$6:$A$370,$B31)+SUMIFS(Diario!$G$6:$G$370,Diario!$A$6:$A$370,$B31)+SUMIFS(Diario!$H$6:$H$370,Diario!$A$6:$A$370,$B31)+SUMIFS(Diario!$I$6:$I$370,Diario!$A$6:$A$370,$B31)+SUMIFS(Diario!$J$6:$J$370,Diario!$A$6:$A$370,$B31)),"") -> 0.63636364
B32: =$F$3-10 -> 46308 | C32: =SUMIFS(Diario!$P$6:$P$370,Diario!$A$6:$A$370,$B32) -> 9 | D32: =SUMIFS(Diario!$N$6:$N$370,Diario!$A$6:$A$370,$B32) -> 68.05 | E32: =IF(C32>0,D32/C32,"") -> 7.5611111 | F32: =SUMIFS(Diario!$Y$6:$Y$370,Diario!$A$6:$A$370,$B32) -> 27.170735 | G32: =IF((SUMIFS(Diario!$E$6:$E$370,Diario!$A$6:$A$370,$B32)+SUMIFS(Diario!$F$6:$F$370,Diario!$A$6:$A$370,$B32)+SUMIFS(Diario!$G$6:$G$370,Diario!$A$6:$A$370,$B32)+SUMIFS(Diario!$H$6:$H$370,Diario!$A$6:$A$370,$B32)+SUMIFS(Diario!$I$6:$I$370,Diario!$A$6:$A$370,$B32)+SUMIFS(Diario!$J$6:$J$370,Diario!$A$6:$A$370,$B32))>0,(SUMIFS(Diario!$E$6:$E$370,Diario!$A$6:$A$370,$B32)+SUMIFS(Diario!$F$6:$F$370,Diario!$A$6:$A$370,$B32)+SUMIFS(Diario!$G$6:$G$370,Diario!$A$6:$A$370,$B32))/(SUMIFS(Diario!$E$6:$E$370,Diario!$A$6:$A$370,$B32)+SUMIFS(Diario!$F$6:$F$370,Diario!$A$6:$A$370,$B32)+SUMIFS(Diario!$G$6:$G$370,Diario!$A$6:$A$370,$B32)+SUMIFS(Diario!$H$6:$H$370,Diario!$A$6:$A$370,$B32)+SUMIFS(Diario!$I$6:$I$370,Diario!$A$6:$A$370,$B32)+SUMIFS(Diario!$J$6:$J$370,Diario!$A$6:$A$370,$B32)),"") -> 0.83333333
B33: =$F$3-9 -> 46309 | C33: =SUMIFS(Diario!$P$6:$P$370,Diario!$A$6:$A$370,$B33) -> 9 | D33: =SUMIFS(Diario!$N$6:$N$370,Diario!$A$6:$A$370,$B33) -> 73.35 | E33: =IF(C33>0,D33/C33,"") -> 8.15 | F33: =SUMIFS(Diario!$Y$6:$Y$370,Diario!$A$6:$A$370,$B33) -> 57.225835 | G33: =IF((SUMIFS(Diario!$E$6:$E$370,Diario!$A$6:$A$370,$B33)+SUMIFS(Diario!$F$6:$F$370,Diario!$A$6:$A$370,$B33)+SUMIFS(Diario!$G$6:$G$370,Diario!$A$6:$A$370,$B33)+SUMIFS(Diario!$H$6:$H$370,Diario!$A$6:$A$370,$B33)+SUMIFS(Diario!$I$6:$I$370,Diario!$A$6:$A$370,$B33)+SUMIFS(Diario!$J$6:$J$370,Diario!$A$6:$A$370,$B33))>0,(SUMIFS(Diario!$E$6:$E$370,Diario!$A$6:$A$370,$B33)+SUMIFS(Diario!$F$6:$F$370,Diario!$A$6:$A$370,$B33)+SUMIFS(Diario!$G$6:$G$370,Diario!$A$6:$A$370,$B33))/(SUMIFS(Diario!$E$6:$E$370,Diario!$A$6:$A$370,$B33)+SUMIFS(Diario!$F$6:$F$370,Diario!$A$6:$A$370,$B33)+SUMIFS(Diario!$G$6:$G$370,Diario!$A$6:$A$370,$B33)+SUMIFS(Diario!$H$6:$H$370,Diario!$A$6:$A$370,$B33)+SUMIFS(Diario!$I$6:$I$370,Diario!$A$6:$A$370,$B33)+SUMIFS(Diario!$J$6:$J$370,Diario!$A$6:$A$370,$B33)),"") -> 1
B34: =$F$3-8 -> 46310 | C34: =SUMIFS(Diario!$P$6:$P$370,Diario!$A$6:$A$370,$B34) -> 5 | D34: =SUMIFS(Diario!$N$6:$N$370,Diario!$A$6:$A$370,$B34) -> 60.8 | E34: =IF(C34>0,D34/C34,"") -> 12.16 | F34: =SUMIFS(Diario!$Y$6:$Y$370,Diario!$A$6:$A$370,$B34) -> 37.464167 | G34: =IF((SUMIFS(Diario!$E$6:$E$370,Diario!$A$6:$A$370,$B34)+SUMIFS(Diario!$F$6:$F$370,Diario!$A$6:$A$370,$B34)+SUMIFS(Diario!$G$6:$G$370,Diario!$A$6:$A$370,$B34)+SUMIFS(Diario!$H$6:$H$370,Diario!$A$6:$A$370,$B34)+SUMIFS(Diario!$I$6:$I$370,Diario!$A$6:$A$370,$B34)+SUMIFS(Diario!$J$6:$J$370,Diario!$A$6:$A$370,$B34))>0,(SUMIFS(Diario!$E$6:$E$370,Diario!$A$6:$A$370,$B34)+SUMIFS(Diario!$F$6:$F$370,Diario!$A$6:$A$370,$B34)+SUMIFS(Diario!$G$6:$G$370,Diario!$A$6:$A$370,$B34))/(SUMIFS(Diario!$E$6:$E$370,Diario!$A$6:$A$370,$B34)+SUMIFS(Diario!$F$6:$F$370,Diario!$A$6:$A$370,$B34)+SUMIFS(Diario!$G$6:$G$370,Diario!$A$6:$A$370,$B34)+SUMIFS(Diario!$H$6:$H$370,Diario!$A$6:$A$370,$B34)+SUMIFS(Diario!$I$6:$I$370,Diario!$A$6:$A$370,$B34)+SUMIFS(Diario!$J$6:$J$370,Diario!$A$6:$A$370,$B34)),"") -> 1
B35: =$F$3-7 -> 46311 | C35: =SUMIFS(Diario!$P$6:$P$370,Diario!$A$6:$A$370,$B35) -> 12 | D35: =SUMIFS(Diario!$N$6:$N$370,Diario!$A$6:$A$370,$B35) -> 100.4 | E35: =IF(C35>0,D35/C35,"") -> 8.3666667 | F35: =SUMIFS(Diario!$Y$6:$Y$370,Diario!$A$6:$A$370,$B35) -> 65.510936 | G35: =IF((SUMIFS(Diario!$E$6:$E$370,Diario!$A$6:$A$370,$B35)+SUMIFS(Diario!$F$6:$F$370,Diario!$A$6:$A$370,$B35)+SUMIFS(Diario!$G$6:$G$370,Diario!$A$6:$A$370,$B35)+SUMIFS(Diario!$H$6:$H$370,Diario!$A$6:$A$370,$B35)+SUMIFS(Diario!$I$6:$I$370,Diario!$A$6:$A$370,$B35)+SUMIFS(Diario!$J$6:$J$370,Diario!$A$6:$A$370,$B35))>0,(SUMIFS(Diario!$E$6:$E$370,Diario!$A$6:$A$370,$B35)+SUMIFS(Diario!$F$6:$F$370,Diario!$A$6:$A$370,$B35)+SUMIFS(Diario!$G$6:$G$370,Diario!$A$6:$A$370,$B35))/(SUMIFS(Diario!$E$6:$E$370,Diario!$A$6:$A$370,$B35)+SUMIFS(Diario!$F$6:$F$370,Diario!$A$6:$A$370,$B35)+SUMIFS(Diario!$G$6:$G$370,Diario!$A$6:$A$370,$B35)+SUMIFS(Diario!$H$6:$H$370,Diario!$A$6:$A$370,$B35)+SUMIFS(Diario!$I$6:$I$370,Diario!$A$6:$A$370,$B35)+SUMIFS(Diario!$J$6:$J$370,Diario!$A$6:$A$370,$B35)),"") -> 1
B36: =$F$3-6 -> 46312 | C36: =SUMIFS(Diario!$P$6:$P$370,Diario!$A$6:$A$370,$B36) -> 9 | D36: =SUMIFS(Diario!$N$6:$N$370,Diario!$A$6:$A$370,$B36) -> 81.87 | E36: =IF(C36>0,D36/C36,"") -> 9.0966667 | F36: =SUMIFS(Diario!$Y$6:$Y$370,Diario!$A$6:$A$370,$B36) -> 64.483447 | G36: =IF((SUMIFS(Diario!$E$6:$E$370,Diario!$A$6:$A$370,$B36)+SUMIFS(Diario!$F$6:$F$370,Diario!$A$6:$A$370,$B36)+SUMIFS(Diario!$G$6:$G$370,Diario!$A$6:$A$370,$B36)+SUMIFS(Diario!$H$6:$H$370,Diario!$A$6:$A$370,$B36)+SUMIFS(Diario!$I$6:$I$370,Diario!$A$6:$A$370,$B36)+SUMIFS(Diario!$J$6:$J$370,Diario!$A$6:$A$370,$B36))>0,(SUMIFS(Diario!$E$6:$E$370,Diario!$A$6:$A$370,$B36)+SUMIFS(Diario!$F$6:$F$370,Diario!$A$6:$A$370,$B36)+SUMIFS(Diario!$G$6:$G$370,Diario!$A$6:$A$370,$B36))/(SUMIFS(Diario!$E$6:$E$370,Diario!$A$6:$A$370,$B36)+SUMIFS(Diario!$F$6:$F$370,Diario!$A$6:$A$370,$B36)+SUMIFS(Diario!$G$6:$G$370,Diario!$A$6:$A$370,$B36)+SUMIFS(Diario!$H$6:$H$370,Diario!$A$6:$A$370,$B36)+SUMIFS(Diario!$I$6:$I$370,Diario!$A$6:$A$370,$B36)+SUMIFS(Diario!$J$6:$J$370,Diario!$A$6:$A$370,$B36)),"") -> 1
B37: =$F$3-5 -> 46313 | C37: =SUMIFS(Diario!$P$6:$P$370,Diario!$A$6:$A$370,$B37) -> 12 | D37: =SUMIFS(Diario!$N$6:$N$370,Diario!$A$6:$A$370,$B37) -> 149.88 | E37: =IF(C37>0,D37/C37,"") -> 12.49 | F37: =SUMIFS(Diario!$Y$6:$Y$370,Diario!$A$6:$A$370,$B37) -> 108.75311 | G37: =IF((SUMIFS(Diario!$E$6:$E$370,Diario!$A$6:$A$370,$B37)+SUMIFS(Diario!$F$6:$F$370,Diario!$A$6:$A$370,$B37)+SUMIFS(Diario!$G$6:$G$370,Diario!$A$6:$A$370,$B37)+SUMIFS(Diario!$H$6:$H$370,Diario!$A$6:$A$370,$B37)+SUMIFS(Diario!$I$6:$I$370,Diario!$A$6:$A$370,$B37)+SUMIFS(Diario!$J$6:$J$370,Diario!$A$6:$A$370,$B37))>0,(SUMIFS(Diario!$E$6:$E$370,Diario!$A$6:$A$370,$B37)+SUMIFS(Diario!$F$6:$F$370,Diario!$A$6:$A$370,$B37)+SUMIFS(Diario!$G$6:$G$370,Diario!$A$6:$A$370,$B37))/(SUMIFS(Diario!$E$6:$E$370,Diario!$A$6:$A$370,$B37)+SUMIFS(Diario!$F$6:$F$370,Diario!$A$6:$A$370,$B37)+SUMIFS(Diario!$G$6:$G$370,Diario!$A$6:$A$370,$B37)+SUMIFS(Diario!$H$6:$H$370,Diario!$A$6:$A$370,$B37)+SUMIFS(Diario!$I$6:$I$370,Diario!$A$6:$A$370,$B37)+SUMIFS(Diario!$J$6:$J$370,Diario!$A$6:$A$370,$B37)),"") -> 1
B38: =$F$3-4 -> 46314 | C38: =SUMIFS(Diario!$P$6:$P$370,Diario!$A$6:$A$370,$B38) -> 8 | D38: =SUMIFS(Diario!$N$6:$N$370,Diario!$A$6:$A$370,$B38) -> 85.31 | E38: =IF(C38>0,D38/C38,"") -> 10.66375 | F38: =SUMIFS(Diario!$Y$6:$Y$370,Diario!$A$6:$A$370,$B38) -> 93.113128 | G38: =IF((SUMIFS(Diario!$E$6:$E$370,Diario!$A$6:$A$370,$B38)+SUMIFS(Diario!$F$6:$F$370,Diario!$A$6:$A$370,$B38)+SUMIFS(Diario!$G$6:$G$370,Diario!$A$6:$A$370,$B38)+SUMIFS(Diario!$H$6:$H$370,Diario!$A$6:$A$370,$B38)+SUMIFS(Diario!$I$6:$I$370,Diario!$A$6:$A$370,$B38)+SUMIFS(Diario!$J$6:$J$370,Diario!$A$6:$A$370,$B38))>0,(SUMIFS(Diario!$E$6:$E$370,Diario!$A$6:$A$370,$B38)+SUMIFS(Diario!$F$6:$F$370,Diario!$A$6:$A$370,$B38)+SUMIFS(Diario!$G$6:$G$370,Diario!$A$6:$A$370,$B38))/(SUMIFS(Diario!$E$6:$E$370,Diario!$A$6:$A$370,$B38)+SUMIFS(Diario!$F$6:$F$370,Diario!$A$6:$A$370,$B38)+SUMIFS(Diario!$G$6:$G$370,Diario!$A$6:$A$370,$B38)+SUMIFS(Diario!$H$6:$H$370,Diario!$A$6:$A$370,$B38)+SUMIFS(Diario!$I$6:$I$370,Diario!$A$6:$A$370,$B38)+SUMIFS(Diario!$J$6:$J$370,Diario!$A$6:$A$370,$B38)),"") -> 1
B39: =$F$3-3 -> 46315 | C39: =SUMIFS(Diario!$P$6:$P$370,Diario!$A$6:$A$370,$B39) -> 6 | D39: =SUMIFS(Diario!$N$6:$N$370,Diario!$A$6:$A$370,$B39) -> 71.96 | E39: =IF(C39>0,D39/C39,"") -> 11.993333 | F39: =SUMIFS(Diario!$Y$6:$Y$370,Diario!$A$6:$A$370,$B39) -> 46.153396 | G39: =IF((SUMIFS(Diario!$E$6:$E$370,Diario!$A$6:$A$370,$B39)+SUMIFS(Diario!$F$6:$F$370,Diario!$A$6:$A$370,$B39)+SUMIFS(Diario!$G$6:$G$370,Diario!$A$6:$A$370,$B39)+SUMIFS(Diario!$H$6:$H$370,Diario!$A$6:$A$370,$B39)+SUMIFS(Diario!$I$6:$I$370,Diario!$A$6:$A$370,$B39)+SUMIFS(Diario!$J$6:$J$370,Diario!$A$6:$A$370,$B39))>0,(SUMIFS(Diario!$E$6:$E$370,Diario!$A$6:$A$370,$B39)+SUMIFS(Diario!$F$6:$F$370,Diario!$A$6:$A$370,$B39)+SUMIFS(Diario!$G$6:$G$370,Diario!$A$6:$A$370,$B39))/(SUMIFS(Diario!$E$6:$E$370,Diario!$A$6:$A$370,$B39)+SUMIFS(Diario!$F$6:$F$370,Diario!$A$6:$A$370,$B39)+SUMIFS(Diario!$G$6:$G$370,Diario!$A$6:$A$370,$B39)+SUMIFS(Diario!$H$6:$H$370,Diario!$A$6:$A$370,$B39)+SUMIFS(Diario!$I$6:$I$370,Diario!$A$6:$A$370,$B39)+SUMIFS(Diario!$J$6:$J$370,Diario!$A$6:$A$370,$B39)),"") -> 1
B40: =$F$3-2 -> 46316 | C40: =SUMIFS(Diario!$P$6:$P$370,Diario!$A$6:$A$370,$B40) -> 5 | D40: =SUMIFS(Diario!$N$6:$N$370,Diario!$A$6:$A$370,$B40) -> 79.53 | E40: =IF(C40>0,D40/C40,"") -> 15.906 | F40: =SUMIFS(Diario!$Y$6:$Y$370,Diario!$A$6:$A$370,$B40) -> 18.085867 | G40: =IF((SUMIFS(Diario!$E$6:$E$370,Diario!$A$6:$A$370,$B40)+SUMIFS(Diario!$F$6:$F$370,Diario!$A$6:$A$370,$B40)+SUMIFS(Diario!$G$6:$G$370,Diario!$A$6:$A$370,$B40)+SUMIFS(Diario!$H$6:$H$370,Diario!$A$6:$A$370,$B40)+SUMIFS(Diario!$I$6:$I$370,Diario!$A$6:$A$370,$B40)+SUMIFS(Diario!$J$6:$J$370,Diario!$A$6:$A$370,$B40))>0,(SUMIFS(Diario!$E$6:$E$370,Diario!$A$6:$A$370,$B40)+SUMIFS(Diario!$F$6:$F$370,Diario!$A$6:$A$370,$B40)+SUMIFS(Diario!$G$6:$G$370,Diario!$A$6:$A$370,$B40))/(SUMIFS(Diario!$E$6:$E$370,Diario!$A$6:$A$370,$B40)+SUMIFS(Diario!$F$6:$F$370,Diario!$A$6:$A$370,$B40)+SUMIFS(Diario!$G$6:$G$370,Diario!$A$6:$A$370,$B40)+SUMIFS(Diario!$H$6:$H$370,Diario!$A$6:$A$370,$B40)+SUMIFS(Diario!$I$6:$I$370,Diario!$A$6:$A$370,$B40)+SUMIFS(Diario!$J$6:$J$370,Diario!$A$6:$A$370,$B40)),"") -> 1
B41: =$F$3-1 -> 46317 | C41: =SUMIFS(Diario!$P$6:$P$370,Diario!$A$6:$A$370,$B41) -> 6 | D41: =SUMIFS(Diario!$N$6:$N$370,Diario!$A$6:$A$370,$B41) -> 83.29 | E41: =IF(C41>0,D41/C41,"") -> 13.881667 | F41: =SUMIFS(Diario!$Y$6:$Y$370,Diario!$A$6:$A$370,$B41) -> 5.6528793 | G41: =IF((SUMIFS(Diario!$E$6:$E$370,Diario!$A$6:$A$370,$B41)+SUMIFS(Diario!$F$6:$F$370,Diario!$A$6:$A$370,$B41)+SUMIFS(Diario!$G$6:$G$370,Diario!$A$6:$A$370,$B41)+SUMIFS(Diario!$H$6:$H$370,Diario!$A$6:$A$370,$B41)+SUMIFS(Diario!$I$6:$I$370,Diario!$A$6:$A$370,$B41)+SUMIFS(Diario!$J$6:$J$370,Diario!$A$6:$A$370,$B41))>0,(SUMIFS(Diario!$E$6:$E$370,Diario!$A$6:$A$370,$B41)+SUMIFS(Diario!$F$6:$F$370,Diario!$A$6:$A$370,$B41)+SUMIFS(Diario!$G$6:$G$370,Diario!$A$6:$A$370,$B41))/(SUMIFS(Diario!$E$6:$E$370,Diario!$A$6:$A$370,$B41)+SUMIFS(Diario!$F$6:$F$370,Diario!$A$6:$A$370,$B41)+SUMIFS(Diario!$G$6:$G$370,Diario!$A$6:$A$370,$B41)+SUMIFS(Diario!$H$6:$H$370,Diario!$A$6:$A$370,$B41)+SUMIFS(Diario!$I$6:$I$370,Diario!$A$6:$A$370,$B41)+SUMIFS(Diario!$J$6:$J$370,Diario!$A$6:$A$370,$B41)),"") -> 1
B42: =$F$3-0 -> 46318 | C42: =SUMIFS(Diario!$P$6:$P$370,Diario!$A$6:$A$370,$B42) -> 4 | D42: =SUMIFS(Diario!$N$6:$N$370,Diario!$A$6:$A$370,$B42) -> 29.29 | E42: =IF(C42>0,D42/C42,"") -> 7.3225 | F42: =SUMIFS(Diario!$Y$6:$Y$370,Diario!$A$6:$A$370,$B42) -> 16.635852 | G42: =IF((SUMIFS(Diario!$E$6:$E$370,Diario!$A$6:$A$370,$B42)+SUMIFS(Diario!$F$6:$F$370,Diario!$A$6:$A$370,$B42)+SUMIFS(Diario!$G$6:$G$370,Diario!$A$6:$A$370,$B42)+SUMIFS(Diario!$H$6:$H$370,Diario!$A$6:$A$370,$B42)+SUMIFS(Diario!$I$6:$I$370,Diario!$A$6:$A$370,$B42)+SUMIFS(Diario!$J$6:$J$370,Diario!$A$6:$A$370,$B42))>0,(SUMIFS(Diario!$E$6:$E$370,Diario!$A$6:$A$370,$B42)+SUMIFS(Diario!$F$6:$F$370,Diario!$A$6:$A$370,$B42)+SUMIFS(Diario!$G$6:$G$370,Diario!$A$6:$A$370,$B42))/(SUMIFS(Diario!$E$6:$E$370,Diario!$A$6:$A$370,$B42)+SUMIFS(Diario!$F$6:$F$370,Diario!$A$6:$A$370,$B42)+SUMIFS(Diario!$G$6:$G$370,Diario!$A$6:$A$370,$B42)+SUMIFS(Diario!$H$6:$H$370,Diario!$A$6:$A$370,$B42)+SUMIFS(Diario!$I$6:$I$370,Diario!$A$6:$A$370,$B42)+SUMIFS(Diario!$J$6:$J$370,Diario!$A$6:$A$370,$B42)),"")
B45: RESUMEN MENSUAL
B46: Mes | C46: Pedidos | D46: Gasto Ads | E46: CPA | F46: Facturación bruta | G46: Entregados | H46: Devueltos | I46: Tasa entrega | J46: Beneficio campaña | K46: Otros gastos | L46: Beneficio neto | M46: % objetivo | O46: Objetivo
B47: =DATE(YEAR(FECHA_INICIO),MONTH(FECHA_INICIO)+0,1) -> 46296 | C47: =SUMIFS(Diario!$P$6:$P$370,Diario!$A$6:$A$370,">="&$B47,Diario!$A$6:$A$370,"<="&EOMONTH($B47,0)) -> 159 | D47: =SUMIFS(Diario!$N$6:$N$370,Diario!$A$6:$A$370,">="&$B47,Diario!$A$6:$A$370,"<="&EOMONTH($B47,0)) -> 1393.68 | E47: =IF(C47>0,D47/C47,"") -> 8.765283 | F47: =SUMIFS(Diario!$R$6:$R$370,Diario!$A$6:$A$370,">="&$B47,Diario!$A$6:$A$370,"<="&EOMONTH($B47,0)) -> 5678.41 | G47: =SUMIFS(Diario!$E$6:$E$370,Diario!$A$6:$A$370,">="&$B47,Diario!$A$6:$A$370,"<="&EOMONTH($B47,0))+SUMIFS(Diario!$F$6:$F$370,Diario!$A$6:$A$370,">="&$B47,Diario!$A$6:$A$370,"<="&EOMONTH($B47,0))+SUMIFS(Diario!$G$6:$G$370,Diario!$A$6:$A$370,">="&$B47,Diario!$A$6:$A$370,"<="&EOMONTH($B47,0)) -> 74 | H47: =SUMIFS(Diario!$H$6:$H$370,Diario!$A$6:$A$370,">="&$B47,Diario!$A$6:$A$370,"<="&EOMONTH($B47,0))+SUMIFS(Diario!$I$6:$I$370,Diario!$A$6:$A$370,">="&$B47,Diario!$A$6:$A$370,"<="&EOMONTH($B47,0))+SUMIFS(Diario!$J$6:$J$370,Diario!$A$6:$A$370,">="&$B47,Diario!$A$6:$A$370,"<="&EOMONTH($B47,0)) -> 34 | I47: =IF(G47+H47>0,G47/(G47+H47),"") -> 0.68518519 | J47: =SUMIFS(Diario!$Y$6:$Y$370,Diario!$A$6:$A$370,">="&$B47,Diario!$A$6:$A$370,"<="&EOMONTH($B47,0)) -> 528.87646 | K47: =-SUMIFS(Gastos!$D$5:$D$304,Gastos!$A$5:$A$304,">="&$B47,Gastos!$A$5:$A$304,"<="&EOMONTH($B47,0)) -> 0 | L47: =J47+K47 -> 528.87646 | M47: =IF(OBJETIVO_MES>0,L47/OBJETIVO_MES,"") -> 0.052887646 | O47: =OBJETIVO_MES -> 10000
B48: =DATE(YEAR(FECHA_INICIO),MONTH(FECHA_INICIO)+1,1) -> 46327 | C48: =SUMIFS(Diario!$P$6:$P$370,Diario!$A$6:$A$370,">="&$B48,Diario!$A$6:$A$370,"<="&EOMONTH($B48,0)) -> 0 | D48: =SUMIFS(Diario!$N$6:$N$370,Diario!$A$6:$A$370,">="&$B48,Diario!$A$6:$A$370,"<="&EOMONTH($B48,0)) -> 0 | E48: =IF(C48>0,D48/C48,"") | F48: =SUMIFS(Diario!$R$6:$R$370,Diario!$A$6:$A$370,">="&$B48,Diario!$A$6:$A$370,"<="&EOMONTH($B48,0)) -> 0 | G48: =SUMIFS(Diario!$E$6:$E$370,Diario!$A$6:$A$370,">="&$B48,Diario!$A$6:$A$370,"<="&EOMONTH($B48,0))+SUMIFS(Diario!$F$6:$F$370,Diario!$A$6:$A$370,">="&$B48,Diario!$A$6:$A$370,"<="&EOMONTH($B48,0))+SUMIFS(Diario!$G$6:$G$370,Diario!$A$6:$A$370,">="&$B48,Diario!$A$6:$A$370,"<="&EOMONTH($B48,0)) -> 0 | H48: =SUMIFS(Diario!$H$6:$H$370,Diario!$A$6:$A$370,">="&$B48,Diario!$A$6:$A$370,"<="&EOMONTH($B48,0))+SUMIFS(Diario!$I$6:$I$370,Diario!$A$6:$A$370,">="&$B48,Diario!$A$6:$A$370,"<="&EOMONTH($B48,0))+SUMIFS(Diario!$J$6:$J$370,Diario!$A$6:$A$370,">="&$B48,Diario!$A$6:$A$370,"<="&EOMONTH($B48,0)) -> 0 | I48: =IF(G48+H48>0,G48/(G48+H48),"") | J48: =SUMIFS(Diario!$Y$6:$Y$370,Diario!$A$6:$A$370,">="&$B48,Diario!$A$6:$A$370,"<="&EOMONTH($B48,0)) -> 0 | K48: =-SUMIFS(Gastos!$D$5:$D$304,Gastos!$A$5:$A$304,">="&$B48,Gastos!$A$5:$A$304,"<="&EOMONTH($B48,0)) -> 0 | L48: =J48+K48 -> 0 | M48: =IF(OBJETIVO_MES>0,L48/OBJETIVO_MES,"") -> 0 | O48: =OBJETIVO_MES -> 10000
B49: =DATE(YEAR(FECHA_INICIO),MONTH(FECHA_INICIO)+2,1) -> 46357 | C49: =SUMIFS(Diario!$P$6:$P$370,Diario!$A$6:$A$370,">="&$B49,Diario!$A$6:$A$370,"<="&EOMONTH($B49,0)) -> 0 | D49: =SUMIFS(Diario!$N$6:$N$370,Diario!$A$6:$A$370,">="&$B49,Diario!$A$6:$A$370,"<="&EOMONTH($B49,0)) -> 0 | E49: =IF(C49>0,D49/C49,"") | F49: =SUMIFS(Diario!$R$6:$R$370,Diario!$A$6:$A$370,">="&$B49,Diario!$A$6:$A$370,"<="&EOMONTH($B49,0)) -> 0 | G49: =SUMIFS(Diario!$E$6:$E$370,Diario!$A$6:$A$370,">="&$B49,Diario!$A$6:$A$370,"<="&EOMONTH($B49,0))+SUMIFS(Diario!$F$6:$F$370,Diario!$A$6:$A$370,">="&$B49,Diario!$A$6:$A$370,"<="&EOMONTH($B49,0))+SUMIFS(Diario!$G$6:$G$370,Diario!$A$6:$A$370,">="&$B49,Diario!$A$6:$A$370,"<="&EOMONTH($B49,0)) -> 0 | H49: =SUMIFS(Diario!$H$6:$H$370,Diario!$A$6:$A$370,">="&$B49,Diario!$A$6:$A$370,"<="&EOMONTH($B49,0))+SUMIFS(Diario!$I$6:$I$370,Diario!$A$6:$A$370,">="&$B49,Diario!$A$6:$A$370,"<="&EOMONTH($B49,0))+SUMIFS(Diario!$J$6:$J$370,Diario!$A$6:$A$370,">="&$B49,Diario!$A$6:$A$370,"<="&EOMONTH($B49,0)) -> 0 | I49: =IF(G49+H49>0,G49/(G49+H49),"") | J49: =SUMIFS(Diario!$Y$6:$Y$370,Diario!$A$6:$A$370,">="&$B49,Diario!$A$6:$A$370,"<="&EOMONTH($B49,0)) -> 0 | K49: =-SUMIFS(Gastos!$D$5:$D$304,Gastos!$A$5:$A$304,">="&$B49,Gastos!$A$5:$A$304,"<="&EOMONTH($B49,0)) -> 0 | L49: =J49+K49 -> 0 | M49: =IF(OBJETIVO_MES>0,L49/OBJETIVO_MES,"") -> 0 | O49: =OBJETIVO_MES -> 10000
B50: =DATE(YEAR(FECHA_INICIO),MONTH(FECHA_INICIO)+3,1) -> 46388 | C50: =SUMIFS(Diario!$P$6:$P$370,Diario!$A$6:$A$370,">="&$B50,Diario!$A$6:$A$370,"<="&EOMONTH($B50,0)) -> 0 | D50: =SUMIFS(Diario!$N$6:$N$370,Diario!$A$6:$A$370,">="&$B50,Diario!$A$6:$A$370,"<="&EOMONTH($B50,0)) -> 0 | E50: =IF(C50>0,D50/C50,"") | F50: =SUMIFS(Diario!$R$6:$R$370,Diario!$A$6:$A$370,">="&$B50,Diario!$A$6:$A$370,"<="&EOMONTH($B50,0)) -> 0 | G50: =SUMIFS(Diario!$E$6:$E$370,Diario!$A$6:$A$370,">="&$B50,Diario!$A$6:$A$370,"<="&EOMONTH($B50,0))+SUMIFS(Diario!$F$6:$F$370,Diario!$A$6:$A$370,">="&$B50,Diario!$A$6:$A$370,"<="&EOMONTH($B50,0))+SUMIFS(Diario!$G$6:$G$370,Diario!$A$6:$A$370,">="&$B50,Diario!$A$6:$A$370,"<="&EOMONTH($B50,0)) -> 0 | H50: =SUMIFS(Diario!$H$6:$H$370,Diario!$A$6:$A$370,">="&$B50,Diario!$A$6:$A$370,"<="&EOMONTH($B50,0))+SUMIFS(Diario!$I$6:$I$370,Diario!$A$6:$A$370,">="&$B50,Diario!$A$6:$A$370,"<="&EOMONTH($B50,0))+SUMIFS(Diario!$J$6:$J$370,Diario!$A$6:$A$370,">="&$B50,Diario!$A$6:$A$370,"<="&EOMONTH($B50,0)) -> 0 | I50: =IF(G50+H50>0,G50/(G50+H50),"") | J50: =SUMIFS(Diario!$Y$6:$Y$370,Diario!$A$6:$A$370,">="&$B50,Diario!$A$6:$A$370,"<="&EOMONTH($B50,0)) -> 0 | K50: =-SUMIFS(Gastos!$D$5:$D$304,Gastos!$A$5:$A$304,">="&$B50,Gastos!$A$5:$A$304,"<="&EOMONTH($B50,0)) -> 0 | L50: =J50+K50 -> 0 | M50: =IF(OBJETIVO_MES>0,L50/OBJETIVO_MES,"") -> 0 | O50: =OBJETIVO_MES -> 10000
B51: =DATE(YEAR(FECHA_INICIO),MONTH(FECHA_INICIO)+4,1) -> 46419 | C51: =SUMIFS(Diario!$P$6:$P$370,Diario!$A$6:$A$370,">="&$B51,Diario!$A$6:$A$370,"<="&EOMONTH($B51,0)) -> 0 | D51: =SUMIFS(Diario!$N$6:$N$370,Diario!$A$6:$A$370,">="&$B51,Diario!$A$6:$A$370,"<="&EOMONTH($B51,0)) -> 0 | E51: =IF(C51>0,D51/C51,"") | F51: =SUMIFS(Diario!$R$6:$R$370,Diario!$A$6:$A$370,">="&$B51,Diario!$A$6:$A$370,"<="&EOMONTH($B51,0)) -> 0 | G51: =SUMIFS(Diario!$E$6:$E$370,Diario!$A$6:$A$370,">="&$B51,Diario!$A$6:$A$370,"<="&EOMONTH($B51,0))+SUMIFS(Diario!$F$6:$F$370,Diario!$A$6:$A$370,">="&$B51,Diario!$A$6:$A$370,"<="&EOMONTH($B51,0))+SUMIFS(Diario!$G$6:$G$370,Diario!$A$6:$A$370,">="&$B51,Diario!$A$6:$A$370,"<="&EOMONTH($B51,0)) -> 0 | H51: =SUMIFS(Diario!$H$6:$H$370,Diario!$A$6:$A$370,">="&$B51,Diario!$A$6:$A$370,"<="&EOMONTH($B51,0))+SUMIFS(Diario!$I$6:$I$370,Diario!$A$6:$A$370,">="&$B51,Diario!$A$6:$A$370,"<="&EOMONTH($B51,0))+SUMIFS(Diario!$J$6:$J$370,Diario!$A$6:$A$370,">="&$B51,Diario!$A$6:$A$370,"<="&EOMONTH($B51,0)) -> 0 | I51: =IF(G51+H51>0,G51/(G51+H51),"") | J51: =SUMIFS(Diario!$Y$6:$Y$370,Diario!$A$6:$A$370,">="&$B51,Diario!$A$6:$A$370,"<="&EOMONTH($B51,0)) -> 0 | K51: =-SUMIFS(Gastos!$D$5:$D$304,Gastos!$A$5:$A$304,">="&$B51,Gastos!$A$5:$A$304,"<="&EOMONTH($B51,0)) -> 0 | L51: =J51+K51 -> 0 | M51: =IF(OBJETIVO_MES>0,L51/OBJETIVO_MES,"") -> 0 | O51: =OBJETIVO_MES -> 10000
B52: =DATE(YEAR(FECHA_INICIO),MONTH(FECHA_INICIO)+5,1) -> 46447 | C52: =SUMIFS(Diario!$P$6:$P$370,Diario!$A$6:$A$370,">="&$B52,Diario!$A$6:$A$370,"<="&EOMONTH($B52,0)) -> 0 | D52: =SUMIFS(Diario!$N$6:$N$370,Diario!$A$6:$A$370,">="&$B52,Diario!$A$6:$A$370,"<="&EOMONTH($B52,0)) -> 0 | E52: =IF(C52>0,D52/C52,"") | F52: =SUMIFS(Diario!$R$6:$R$370,Diario!$A$6:$A$370,">="&$B52,Diario!$A$6:$A$370,"<="&EOMONTH($B52,0)) -> 0 | G52: =SUMIFS(Diario!$E$6:$E$370,Diario!$A$6:$A$370,">="&$B52,Diario!$A$6:$A$370,"<="&EOMONTH($B52,0))+SUMIFS(Diario!$F$6:$F$370,Diario!$A$6:$A$370,">="&$B52,Diario!$A$6:$A$370,"<="&EOMONTH($B52,0))+SUMIFS(Diario!$G$6:$G$370,Diario!$A$6:$A$370,">="&$B52,Diario!$A$6:$A$370,"<="&EOMONTH($B52,0)) -> 0 | H52: =SUMIFS(Diario!$H$6:$H$370,Diario!$A$6:$A$370,">="&$B52,Diario!$A$6:$A$370,"<="&EOMONTH($B52,0))+SUMIFS(Diario!$I$6:$I$370,Diario!$A$6:$A$370,">="&$B52,Diario!$A$6:$A$370,"<="&EOMONTH($B52,0))+SUMIFS(Diario!$J$6:$J$370,Diario!$A$6:$A$370,">="&$B52,Diario!$A$6:$A$370,"<="&EOMONTH($B52,0)) -> 0 | I52: =IF(G52+H52>0,G52/(G52+H52),"") | J52: =SUMIFS(Diario!$Y$6:$Y$370,Diario!$A$6:$A$370,">="&$B52,Diario!$A$6:$A$370,"<="&EOMONTH($B52,0)) -> 0 | K52: =-SUMIFS(Gastos!$D$5:$D$304,Gastos!$A$5:$A$304,">="&$B52,Gastos!$A$5:$A$304,"<="&EOMONTH($B52,0)) -> 0 | L52: =J52+K52 -> 0 | M52: =IF(OBJETIVO_MES>0,L52/OBJETIVO_MES,"") -> 0 | O52: =OBJETIVO_MES -> 10000
B53: =DATE(YEAR(FECHA_INICIO),MONTH(FECHA_INICIO)+6,1) -> 46478 | C53: =SUMIFS(Diario!$P$6:$P$370,Diario!$A$6:$A$370,">="&$B53,Diario!$A$6:$A$370,"<="&EOMONTH($B53,0)) -> 0 | D53: =SUMIFS(Diario!$N$6:$N$370,Diario!$A$6:$A$370,">="&$B53,Diario!$A$6:$A$370,"<="&EOMONTH($B53,0)) -> 0 | E53: =IF(C53>0,D53/C53,"") | F53: =SUMIFS(Diario!$R$6:$R$370,Diario!$A$6:$A$370,">="&$B53,Diario!$A$6:$A$370,"<="&EOMONTH($B53,0)) -> 0 | G53: =SUMIFS(Diario!$E$6:$E$370,Diario!$A$6:$A$370,">="&$B53,Diario!$A$6:$A$370,"<="&EOMONTH($B53,0))+SUMIFS(Diario!$F$6:$F$370,Diario!$A$6:$A$370,">="&$B53,Diario!$A$6:$A$370,"<="&EOMONTH($B53,0))+SUMIFS(Diario!$G$6:$G$370,Diario!$A$6:$A$370,">="&$B53,Diario!$A$6:$A$370,"<="&EOMONTH($B53,0)) -> 0 | H53: =SUMIFS(Diario!$H$6:$H$370,Diario!$A$6:$A$370,">="&$B53,Diario!$A$6:$A$370,"<="&EOMONTH($B53,0))+SUMIFS(Diario!$I$6:$I$370,Diario!$A$6:$A$370,">="&$B53,Diario!$A$6:$A$370,"<="&EOMONTH($B53,0))+SUMIFS(Diario!$J$6:$J$370,Diario!$A$6:$A$370,">="&$B53,Diario!$A$6:$A$370,"<="&EOMONTH($B53,0)) -> 0 | I53: =IF(G53+H53>0,G53/(G53+H53),"") | J53: =SUMIFS(Diario!$Y$6:$Y$370,Diario!$A$6:$A$370,">="&$B53,Diario!$A$6:$A$370,"<="&EOMONTH($B53,0)) -> 0 | K53: =-SUMIFS(Gastos!$D$5:$D$304,Gastos!$A$5:$A$304,">="&$B53,Gastos!$A$5:$A$304,"<="&EOMONTH($B53,0)) -> 0 | L53: =J53+K53 -> 0 | M53: =IF(OBJETIVO_MES>0,L53/OBJETIVO_MES,"") -> 0 | O53: =OBJETIVO_MES -> 10000
B54: =DATE(YEAR(FECHA_INICIO),MONTH(FECHA_INICIO)+7,1) -> 46508 | C54: =SUMIFS(Diario!$P$6:$P$370,Diario!$A$6:$A$370,">="&$B54,Diario!$A$6:$A$370,"<="&EOMONTH($B54,0)) -> 0 | D54: =SUMIFS(Diario!$N$6:$N$370,Diario!$A$6:$A$370,">="&$B54,Diario!$A$6:$A$370,"<="&EOMONTH($B54,0)) -> 0 | E54: =IF(C54>0,D54/C54,"") | F54: =SUMIFS(Diario!$R$6:$R$370,Diario!$A$6:$A$370,">="&$B54,Diario!$A$6:$A$370,"<="&EOMONTH($B54,0)) -> 0 | G54: =SUMIFS(Diario!$E$6:$E$370,Diario!$A$6:$A$370,">="&$B54,Diario!$A$6:$A$370,"<="&EOMONTH($B54,0))+SUMIFS(Diario!$F$6:$F$370,Diario!$A$6:$A$370,">="&$B54,Diario!$A$6:$A$370,"<="&EOMONTH($B54,0))+SUMIFS(Diario!$G$6:$G$370,Diario!$A$6:$A$370,">="&$B54,Diario!$A$6:$A$370,"<="&EOMONTH($B54,0)) -> 0 | H54: =SUMIFS(Diario!$H$6:$H$370,Diario!$A$6:$A$370,">="&$B54,Diario!$A$6:$A$370,"<="&EOMONTH($B54,0))+SUMIFS(Diario!$I$6:$I$370,Diario!$A$6:$A$370,">="&$B54,Diario!$A$6:$A$370,"<="&EOMONTH($B54,0))+SUMIFS(Diario!$J$6:$J$370,Diario!$A$6:$A$370,">="&$B54,Diario!$A$6:$A$370,"<="&EOMONTH($B54,0)) -> 0 | I54: =IF(G54+H54>0,G54/(G54+H54),"") | J54: =SUMIFS(Diario!$Y$6:$Y$370,Diario!$A$6:$A$370,">="&$B54,Diario!$A$6:$A$370,"<="&EOMONTH($B54,0)) -> 0 | K54: =-SUMIFS(Gastos!$D$5:$D$304,Gastos!$A$5:$A$304,">="&$B54,Gastos!$A$5:$A$304,"<="&EOMONTH($B54,0)) -> 0 | L54: =J54+K54 -> 0 | M54: =IF(OBJETIVO_MES>0,L54/OBJETIVO_MES,"") -> 0 | O54: =OBJETIVO_MES -> 10000
B55: =DATE(YEAR(FECHA_INICIO),MONTH(FECHA_INICIO)+8,1) -> 46539 | C55: =SUMIFS(Diario!$P$6:$P$370,Diario!$A$6:$A$370,">="&$B55,Diario!$A$6:$A$370,"<="&EOMONTH($B55,0)) -> 0 | D55: =SUMIFS(Diario!$N$6:$N$370,Diario!$A$6:$A$370,">="&$B55,Diario!$A$6:$A$370,"<="&EOMONTH($B55,0)) -> 0 | E55: =IF(C55>0,D55/C55,"") | F55: =SUMIFS(Diario!$R$6:$R$370,Diario!$A$6:$A$370,">="&$B55,Diario!$A$6:$A$370,"<="&EOMONTH($B55,0)) -> 0 | G55: =SUMIFS(Diario!$E$6:$E$370,Diario!$A$6:$A$370,">="&$B55,Diario!$A$6:$A$370,"<="&EOMONTH($B55,0))+SUMIFS(Diario!$F$6:$F$370,Diario!$A$6:$A$370,">="&$B55,Diario!$A$6:$A$370,"<="&EOMONTH($B55,0))+SUMIFS(Diario!$G$6:$G$370,Diario!$A$6:$A$370,">="&$B55,Diario!$A$6:$A$370,"<="&EOMONTH($B55,0)) -> 0 | H55: =SUMIFS(Diario!$H$6:$H$370,Diario!$A$6:$A$370,">="&$B55,Diario!$A$6:$A$370,"<="&EOMONTH($B55,0))+SUMIFS(Diario!$I$6:$I$370,Diario!$A$6:$A$370,">="&$B55,Diario!$A$6:$A$370,"<="&EOMONTH($B55,0))+SUMIFS(Diario!$J$6:$J$370,Diario!$A$6:$A$370,">="&$B55,Diario!$A$6:$A$370,"<="&EOMONTH($B55,0)) -> 0 | I55: =IF(G55+H55>0,G55/(G55+H55),"") | J55: =SUMIFS(Diario!$Y$6:$Y$370,Diario!$A$6:$A$370,">="&$B55,Diario!$A$6:$A$370,"<="&EOMONTH($B55,0)) -> 0 | K55: =-SUMIFS(Gastos!$D$5:$D$304,Gastos!$A$5:$A$304,">="&$B55,Gastos!$A$5:$A$304,"<="&EOMONTH($B55,0)) -> 0 | L55: =J55+K55 -> 0 | M55: =IF(OBJETIVO_MES>0,L55/OBJETIVO_MES,"") -> 0 | O55: =OBJETIVO_MES -> 10000
B56: =DATE(YEAR(FECHA_INICIO),MONTH(FECHA_INICIO)+9,1) -> 46569 | C56: =SUMIFS(Diario!$P$6:$P$370,Diario!$A$6:$A$370,">="&$B56,Diario!$A$6:$A$370,"<="&EOMONTH($B56,0)) -> 0 | D56: =SUMIFS(Diario!$N$6:$N$370,Diario!$A$6:$A$370,">="&$B56,Diario!$A$6:$A$370,"<="&EOMONTH($B56,0)) -> 0 | E56: =IF(C56>0,D56/C56,"") | F56: =SUMIFS(Diario!$R$6:$R$370,Diario!$A$6:$A$370,">="&$B56,Diario!$A$6:$A$370,"<="&EOMONTH($B56,0)) -> 0 | G56: =SUMIFS(Diario!$E$6:$E$370,Diario!$A$6:$A$370,">="&$B56,Diario!$A$6:$A$370,"<="&EOMONTH($B56,0))+SUMIFS(Diario!$F$6:$F$370,Diario!$A$6:$A$370,">="&$B56,Diario!$A$6:$A$370,"<="&EOMONTH($B56,0))+SUMIFS(Diario!$G$6:$G$370,Diario!$A$6:$A$370,">="&$B56,Diario!$A$6:$A$370,"<="&EOMONTH($B56,0)) -> 0 | H56: =SUMIFS(Diario!$H$6:$H$370,Diario!$A$6:$A$370,">="&$B56,Diario!$A$6:$A$370,"<="&EOMONTH($B56,0))+SUMIFS(Diario!$I$6:$I$370,Diario!$A$6:$A$370,">="&$B56,Diario!$A$6:$A$370,"<="&EOMONTH($B56,0))+SUMIFS(Diario!$J$6:$J$370,Diario!$A$6:$A$370,">="&$B56,Diario!$A$6:$A$370,"<="&EOMONTH($B56,0)) -> 0 | I56: =IF(G56+H56>0,G56/(G56+H56),"") | J56: =SUMIFS(Diario!$Y$6:$Y$370,Diario!$A$6:$A$370,">="&$B56,Diario!$A$6:$A$370,"<="&EOMONTH($B56,0)) -> 0 | K56: =-SUMIFS(Gastos!$D$5:$D$304,Gastos!$A$5:$A$304,">="&$B56,Gastos!$A$5:$A$304,"<="&EOMONTH($B56,0)) -> 0 | L56: =J56+K56 -> 0 | M56: =IF(OBJETIVO_MES>0,L56/OBJETIVO_MES,"") -> 0 | O56: =OBJETIVO_MES -> 10000
B57: =DATE(YEAR(FECHA_INICIO),MONTH(FECHA_INICIO)+10,1) -> 46600 | C57: =SUMIFS(Diario!$P$6:$P$370,Diario!$A$6:$A$370,">="&$B57,Diario!$A$6:$A$370,"<="&EOMONTH($B57,0)) -> 0 | D57: =SUMIFS(Diario!$N$6:$N$370,Diario!$A$6:$A$370,">="&$B57,Diario!$A$6:$A$370,"<="&EOMONTH($B57,0)) -> 0 | E57: =IF(C57>0,D57/C57,"") | F57: =SUMIFS(Diario!$R$6:$R$370,Diario!$A$6:$A$370,">="&$B57,Diario!$A$6:$A$370,"<="&EOMONTH($B57,0)) -> 0 | G57: =SUMIFS(Diario!$E$6:$E$370,Diario!$A$6:$A$370,">="&$B57,Diario!$A$6:$A$370,"<="&EOMONTH($B57,0))+SUMIFS(Diario!$F$6:$F$370,Diario!$A$6:$A$370,">="&$B57,Diario!$A$6:$A$370,"<="&EOMONTH($B57,0))+SUMIFS(Diario!$G$6:$G$370,Diario!$A$6:$A$370,">="&$B57,Diario!$A$6:$A$370,"<="&EOMONTH($B57,0)) -> 0 | H57: =SUMIFS(Diario!$H$6:$H$370,Diario!$A$6:$A$370,">="&$B57,Diario!$A$6:$A$370,"<="&EOMONTH($B57,0))+SUMIFS(Diario!$I$6:$I$370,Diario!$A$6:$A$370,">="&$B57,Diario!$A$6:$A$370,"<="&EOMONTH($B57,0))+SUMIFS(Diario!$J$6:$J$370,Diario!$A$6:$A$370,">="&$B57,Diario!$A$6:$A$370,"<="&EOMONTH($B57,0)) -> 0 | I57: =IF(G57+H57>0,G57/(G57+H57),"") | J57: =SUMIFS(Diario!$Y$6:$Y$370,Diario!$A$6:$A$370,">="&$B57,Diario!$A$6:$A$370,"<="&EOMONTH($B57,0)) -> 0 | K57: =-SUMIFS(Gastos!$D$5:$D$304,Gastos!$A$5:$A$304,">="&$B57,Gastos!$A$5:$A$304,"<="&EOMONTH($B57,0)) -> 0 | L57: =J57+K57 -> 0 | M57: =IF(OBJETIVO_MES>0,L57/OBJETIVO_MES,"") -> 0 | O57: =OBJETIVO_MES -> 10000
B58: =DATE(YEAR(FECHA_INICIO),MONTH(FECHA_INICIO)+11,1) -> 46631 | C58: =SUMIFS(Diario!$P$6:$P$370,Diario!$A$6:$A$370,">="&$B58,Diario!$A$6:$A$370,"<="&EOMONTH($B58,0)) -> 0 | D58: =SUMIFS(Diario!$N$6:$N$370,Diario!$A$6:$A$370,">="&$B58,Diario!$A$6:$A$370,"<="&EOMONTH($B58,0)) -> 0 | E58: =IF(C58>0,D58/C58,"") | F58: =SUMIFS(Diario!$R$6:$R$370,Diario!$A$6:$A$370,">="&$B58,Diario!$A$6:$A$370,"<="&EOMONTH($B58,0)) -> 0 | G58: =SUMIFS(Diario!$E$6:$E$370,Diario!$A$6:$A$370,">="&$B58,Diario!$A$6:$A$370,"<="&EOMONTH($B58,0))+SUMIFS(Diario!$F$6:$F$370,Diario!$A$6:$A$370,">="&$B58,Diario!$A$6:$A$370,"<="&EOMONTH($B58,0))+SUMIFS(Diario!$G$6:$G$370,Diario!$A$6:$A$370,">="&$B58,Diario!$A$6:$A$370,"<="&EOMONTH($B58,0)) -> 0 | H58: =SUMIFS(Diario!$H$6:$H$370,Diario!$A$6:$A$370,">="&$B58,Diario!$A$6:$A$370,"<="&EOMONTH($B58,0))+SUMIFS(Diario!$I$6:$I$370,Diario!$A$6:$A$370,">="&$B58,Diario!$A$6:$A$370,"<="&EOMONTH($B58,0))+SUMIFS(Diario!$J$6:$J$370,Diario!$A$6:$A$370,">="&$B58,Diario!$A$6:$A$370,"<="&EOMONTH($B58,0)) -> 0 | I58: =IF(G58+H58>0,G58/(G58+H58),"") | J58: =SUMIFS(Diario!$Y$6:$Y$370,Diario!$A$6:$A$370,">="&$B58,Diario!$A$6:$A$370,"<="&EOMONTH($B58,0)) -> 0 | K58: =-SUMIFS(Gastos!$D$5:$D$304,Gastos!$A$5:$A$304,">="&$B58,Gastos!$A$5:$A$304,"<="&EOMONTH($B58,0)) -> 0 | L58: =J58+K58 -> 0 | M58: =IF(OBJETIVO_MES>0,L58/OBJETIVO_MES,"") -> 0 | O58: =OBJETIVO_MES -> 10000
B59: TOTAL | C59: =SUM(C47:C58) -> 159 | D59: =SUM(D47:D58) -> 1393.68 | E59: =IF(C59>0,D59/C59,"") -> 8.765283 | F59: =SUM(F47:F58) -> 5678.41 | G59: =SUM(G47:G58) -> 74 | H59: =SUM(H47:H58) -> 34 | I59: =IF(G59+H59>0,G59/(G59+H59),"") -> 0.68518519 | J59: =SUM(J47:J58) -> 528.87646 | K59: =SUM(K47:K58) -> 0 | L59: =SUM(L47:L58) -> 528.87646

Sheet Diario
A1: Diario de pedidos
A2: Una fila por día de PEDIDO. Lo amarillo se rellena (lo hace Claude con el export del almacén). Pendientes = preparados + en ruta + incidencias; una incidencia no es venta perdida hasta que pasa a Devuelto.
A3: Ejemplo: el 05/10 entran 5 Pack 1, 4 Pack 2 y 1 Pack 3 → B=5, C=4, D=1. Luego se entregan 3 Pack 1 y 1 Pack 2 → E=3, F=1. 3 de los pendientes están en incidencia → K=3. | AA3: Cálculos auxiliares (no tocar) →
A4: TOTAL | B4: =SUM(B6:B370) -> 89 | C4: =SUM(C6:C370) -> 57 | D4: =SUM(D6:D370) -> 13 | E4: =SUM(E6:E370) -> 39 | F4: =SUM(F6:F370) -> 29 | G4: =SUM(G6:G370) -> 6 | H4: =SUM(H6:H370) -> 25 | I4: =SUM(I6:I370) -> 8 | ... N4: =SUM(N6:N370) -> 1393.68 | P4: =SUM(P6:P370) -> 159 | Q4: =SUM(Q6:Q370) -> 51 | R4: =SUM(R6:R370) -> 5678.41 | S4: =IF(P4>0,R4/P4,"") -> 35.71327 | T4: =IF(P4>0,N4/P4,"") -> 8.765283 | U4: =IF(N4>0,R4/N4,"") -> 4.0744001 | V4: =IF(E4+F4+G4+H4+I4+J4>0,(E4+F4+G4)/(E4+F4+G4+H4+I4+J4),"") -> 0.68518519 | W4: =SUM(W6:W370) -> 1828.0714 | X4: =SUM(X6:X370) -> 26.641437 | Y4: =SUM(Y6:Y370) -> 528.87646 | AA4: =SUM(AA6:AA370) -> 25 | AB4: =SUM(AB6:AB370) -> 20 | AC4: =SUM(AC6:AC370) -> 6 | AD4: =SUM(AD6:AD370) -> 51.683509 | AE4: =SUM(AE6:AE370) -> 39.188147 | AF4: =SUM(AF6:AF370) -> 9.4777115 | AG4: =SUM(AG6:AG370) -> 58.650632 | AH4: =SUM(AH6:AH370) -> 3652.9904 | ... AP4: =SUM(AP6:AP370) -> 29
A5: Fecha del pedido | B5: Pedidos Pack 1 | C5: Pedidos Pack 2 | D5: Pedidos Pack 3 | E5: Entregados Pack 1 | F5: Entregados Pack 2 | G5: Entregados Pack 3 | H5: Devueltos Pack 1 | I5: Devueltos Pack 2 | J5: Devueltos Pack 3 | K5: Incidencias (pendientes) | L5: Envío real entregados (€) | M5: Envío real pendientes (€) | N5: Gasto Ads Meta (€) | O5: Notas | P5: Pedidos totales | Q5: Pendientes | R5: Facturación bruta | S5: Ticket medio | T5: CPA | U5: ROAS | V5: Tasa de entrega | W5: Liquidación almacén (entregados) | X5: Beneficio cobrado (real) | Y5: Beneficio proyectado | AA5: Pendientes Pack 1 | AB5: Pendientes Pack 2 | AC5: Pendientes Pack 3 | AD5: Entregados proy. P1 | AE5: Entregados proy. P2 | AF5: Entregados proy. P3 | AG5: Devueltos proy. | AH5: Ventas proy. (IVA incl.) | AI5: Coste producto proy. | AJ5: Envíos proy. | AK5: Devoluciones proy. | AL5: IVA neto proy. | AM5: Ads total (con recargo) | AN5: Pedidos con envío real | AO5: Comisión almacén | AP5: Pendientes en incidencia | AQ5: Tasa de entrega de sus pendientes | AR5: Días laborables desde el pedido | AS5: Incidencias ya visibles | AT5: Tasa de sus pendientes sin incidencia
A6: 46300 | B6: 5 | C6: 4 | D6: 0 | E6: 3 | F6: 2 | H6: 1 | I6: 2 | K6: 1 | L6: 38.42 | M6: 8.06 | N6: 67.67 | O6: Arranca campaña CeraLux ES - Test 3 ángulos | P6: =B6+C6+D6 -> 9 | Q6: =AA6+AB6+AC6 -> 1 | R6: =B6*P1_PVP+C6*P2_PVP+D6*IF($A6<P3_DESDE,P3A_PVP,P3_PVP) -> 309.91 | S6: =IF(P6>0,R6/P6,"") -> 34.434444 | T6: =IF(P6>0,N6/P6,"") -> 7.5188889 | U6: =IF(N6>0,R6/N6,"") -> 4.5797251 | V6: =IF(E6+F6+G6+H6+I6+J6>0,(E6+F6+G6)/(E6+F6+G6+H6+I6+J6),"") -> 0.625 | W6: =E6*(P1_PVP-P1_CPROD)+F6*(P2_PVP-P2_CPROD)+G6*(IF($A6<P3_DESDE,P3A_PVP,P3_PVP)-IF($A6<P3_DESDE,P3A_CPROD,P3_CPROD))-IF(ISNUMBER(L6),L6,E6*P1_LOG+F6*P2_LOG+G6*P3_LOG) -> 114.6747 | X6: =W6-(E6*P1_IVAN+F6*P2_IVAN+G6*IF($A6<P3_DESDE,P3A_IVAN,P3_IVAN))-(H6+I6+J6)*(COSTE_DEV-IVA_DEV)-AM6-AO6 -> 15.8047 | Y6: =AH6-AI6-AJ6-AK6-AL6-AM6-AO6 -> 15.564167 | AA6: =MAX(0,B6-E6-H6) -> 1 | AB6: =MAX(0,C6-F6-I6) -> 0 | AC6: =MAX(0,D6-G6-J6) -> 0 | AD6: =E6+AA6*AQ6 -> 3.27 | AE6: =F6+AB6*AQ6 -> 2 | AF6: =G6+AC6*AQ6 -> 0 | AG6: =H6+I6+J6+(AA6+AB6+AC6)*(1-AQ6) -> 3.73 | AH6: =AD6*P1_PVP+AE6*P2_PVP+AF6*IF($A6<P3_DESDE,P3A_PVP,P3_PVP) -> 178.0473 | AI6: =AD6*P1_CPROD+AE6*P2_CPROD+AF6*IF($A6<P3_DESDE,P3A_CPROD,P3_CPROD) -> 17.505433 | AJ6: =IF(ISNUMBER(L6),L6,E6*P1_LOG+F6*P2_LOG+G6*P3_LOG)+IF(ISNUMBER(M6),M6,AA6*P1_LOG+AB6*P2_LOG+AC6*P3_LOG)*AQ6 -> 40.5962 | AK6: =AG6*COSTE_DEV -> 28.1615 | AL6: =AD6*P1_IVAN+AE6*P2_IVAN+AF6*IF($A6<P3_DESDE,P3A_IVAN,P3_IVAN)-AG6*IVA_DEV -> 0 | AM6: =N6*(1+RECARGO_ADS) -> 67.67 | AN6: =IF(ISNUMBER(L6),E6+F6+G6+AA6+AB6+AC6,0) -> 6 | AO6: =P6*COMISION -> 8.55 | AP6: =MIN(N(K6),Q6) -> 1 | AQ6: =IF(Q6>0,((Q6-AP6)*AT6+AP6*TASA_INC)/Q6,AT6) -> 0.27 | AR6: =IF($A6<FECHA_EXPORT,NETWORKDAYS($A6+1,FECHA_EXPORT,FESTIVOS),0) -> 13 | AS6: =IF(AR6>=5,1,INDEX(CDF_INC,1,AR6+1)) -> 1 | AT6: =TASA_USADA+(TASA_INC-TASA_USADA)*Q_INC*(1-AS6)/(1-Q_INC*AS6) -> 0.94117647
A7: 46301 | B7: 7 | C7: 1 | D7: 0 | E7: 2 | F7: 1 | H7: 5 | L7: 22.11 | M7: 0 | N7: 70.18 | P7: =B7+C7+D7 -> 8 | Q7: =AA7+AB7+AC7 -> 0 | R7: =B7*P1_PVP+C7*P2_PVP+D7*IF($A7<P3_DESDE,P3A_PVP,P3_PVP) -> 249.92 | S7: =IF(P7>0,R7/P7,"") -> 31.24 | T7: =IF(P7>0,N7/P7,"") -> 8.7725 | U7: =IF(N7>0,R7/N7,"") -> 3.5611285 | V7: =IF(E7+F7+G7+H7+I7+J7>0,(E7+F7+G7)/(E7+F7+G7+H7+I7+J7),"") -> 0.375 | W7: =E7*(P1_PVP-P1_CPROD)+F7*(P2_PVP-P2_CPROD)+G7*(IF($A7<P3_DESDE,P3A_PVP,P3_PVP)-IF($A7<P3_DESDE,P3A_CPROD,P3_CPROD))-IF(ISNUMBER(L7),L7,E7*P1_LOG+F7*P2_LOG+G7*P3_LOG) -> 68.2284 | X7: =W7-(E7*P1_IVAN+F7*P2_IVAN+G7*IF($A7<P3_DESDE,P3A_IVAN,P3_IVAN))-(H7+I7+J7)*(COSTE_DEV-IVA_DEV)-AM7-AO7 -> -47.3016 | Y7: =AH7-AI7-AJ7-AK7-AL7-AM7-AO7 -> -47.3016 | AA7: =MAX(0,B7-E7-H7) -> 0 | AB7: =MAX(0,C7-F7-I7) -> 0 | AC7: =MAX(0,D7-G7-J7) -> 0 | AD7: =E7+AA7*AQ7 -> 2 | AE7: =F7+AB7*AQ7 -> 1 | AF7: =G7+AC7*AQ7 -> 0 | AG7: =H7+I7+J7+(AA7+AB7+AC7)*(1-AQ7) -> 5 | AH7: =AD7*P1_PVP+AE7*P2_PVP+AF7*IF($A7<P3_DESDE,P3A_PVP,P3_PVP) -> 99.97 | AI7: =AD7*P1_CPROD+AE7*P2_CPROD+AF7*IF($A7<P3_DESDE,P3A_CPROD,P3_CPROD) -> 9.6316 | AJ7: =IF(ISNUMBER(L7),L7,E7*P1_LOG+F7*P2_LOG+G7*P3_LOG)+IF(ISNUMBER(M7),M7,AA7*P1_LOG+AB7*P2_LOG+AC7*P3_LOG)*AQ7 -> 22.11 | AK7: =AG7*COSTE_DEV -> 37.75 | AL7: =AD7*P1_IVAN+AE7*P2_IVAN+AF7*IF($A7<P3_DESDE,P3A_IVAN,P3_IVAN)-AG7*IVA_DEV -> 0 | AM7: =N7*(1+RECARGO_ADS) -> 70.18 | AN7: =IF(ISNUMBER(L7),E7+F7+G7+AA7+AB7+AC7,0) -> 3 | AO7: =P7*COMISION -> 7.6 | AP7: =MIN(N(K7),Q7) -> 0 | AQ7: =IF(Q7>0,((Q7-AP7)*AT7+AP7*TASA_INC)/Q7,AT7) -> 0.94117647 | AR7: =IF($A7<FECHA_EXPORT,NETWORKDAYS($A7+1,FECHA_EXPORT,FESTIVOS),0) -> 12 | AS7: =IF(AR7>=5,1,INDEX(CDF_INC,1,AR7+1)) -> 1 | AT7: =TASA_USADA+(TASA_INC-TASA_USADA)*Q_INC*(1-AS7)/(1-Q_INC*AS7) -> 0.94117647
A8: 46302 | B8: 6 | C8: 1 | D8: 0 | E8: 2 | F8: 1 | H8: 4 | L8: 22.65 | M8: 0 | N8: 47.78 | P8: =B8+C8+D8 -> 7 | Q8: =AA8+AB8+AC8 -> 0 | R8: =B8*P1_PVP+C8*P2_PVP+D8*IF($A8<P3_DESDE,P3A_PVP,P3_PVP) -> 219.93 | S8: =IF(P8>0,R8/P8,"") -> 31.418571 | T8: =IF(P8>0,N8/P8,"") -> 6.8257143 | U8: =IF(N8>0,R8/N8,"") -> 4.602972 | V8: =IF(E8+F8+G8+H8+I8+J8>0,(E8+F8+G8)/(E8+F8+G8+H8+I8+J8),"") -> 0.42857143 | W8: =E8*(P1_PVP-P1_CPROD)+F8*(P2_PVP-P2_CPROD)+G8*(IF($A8<P3_DESDE,P3A_PVP,P3_PVP)-IF($A8<P3_DESDE,P3A_CPROD,P3_CPROD))-IF(ISNUMBER(L8),L8,E8*P1_LOG+F8*P2_LOG+G8*P3_LOG) -> 67.6884 | X8: =W8-(E8*P1_IVAN+F8*P2_IVAN+G8*IF($A8<P3_DESDE,P3A_IVAN,P3_IVAN))-(H8+I8+J8)*(COSTE_DEV-IVA_DEV)-AM8-AO8 -> -16.9416 | Y8: =AH8-AI8-AJ8-AK8-AL8-AM8-AO8 -> -16.9416 | AA8: =MAX(0,B8-E8-H8) -> 0 | AB8: =MAX(0,C8-F8-I8) -> 0 | AC8: =MAX(0,D8-G8-J8) -> 0 | AD8: =E8+AA8*AQ8 -> 2 | AE8: =F8+AB8*AQ8 -> 1 | AF8: =G8+AC8*AQ8 -> 0 | AG8: =H8+I8+J8+(AA8+AB8+AC8)*(1-AQ8) -> 4 | AH8: =AD8*P1_PVP+AE8*P2_PVP+AF8*IF($A8<P3_DESDE,P3A_PVP,P3_PVP) -> 99.97 | AI8: =AD8*P1_CPROD+AE8*P2_CPROD+AF8*IF($A8<P3_DESDE,P3A_CPROD,P3_CPROD) -> 9.6316 | AJ8: =IF(ISNUMBER(L8),L8,E8*P1_LOG+F8*P2_LOG+G8*P3_LOG)+IF(ISNUMBER(M8),M8,AA8*P1_LOG+AB8*P2_LOG+AC8*P3_LOG)*AQ8 -> 22.65 | AK8: =AG8*COSTE_DEV -> 30.2 | AL8: =AD8*P1_IVAN+AE8*P2_IVAN+AF8*IF($A8<P3_DESDE,P3A_IVAN,P3_IVAN)-AG8*IVA_DEV -> 0 | AM8: =N8*(1+RECARGO_ADS) -> 47.78 | AN8: =IF(ISNUMBER(L8),E8+F8+G8+AA8+AB8+AC8,0) -> 3 | AO8: =P8*COMISION -> 6.65 | AP8: =MIN(N(K8),Q8) -> 0 | AQ8: =IF(Q8>0,((Q8-AP8)*AT8+AP8*TASA_INC)/Q8,AT8) -> 0.94117647 | AR8: =IF($A8<FECHA_EXPORT,NETWORKDAYS($A8+1,FECHA_EXPORT,FESTIVOS),0) -> 11 | AS8: =IF(AR8>=5,1,INDEX(CDF_INC,1,AR8+1)) -> 1 | AT8: =TASA_USADA+(TASA_INC-TASA_USADA)*Q_INC*(1-AS8)/(1-Q_INC*AS8) -> 0.94117647
A9: 46303 | B9: 9 | C9: 6 | D9: 1 | E9: 4 | F9: 2 | G9: 1 | H9: 4 | I9: 3 | K9: 2 | L9: 50.21 | M9: 16.12 | N9: 50.46 | O9: Primer rehusado: #1184 (pack 2, 39,99 €) rechazado en la puerta | P9: =B9+C9+D9 -> 16 | Q9: =AA9+AB9+AC9 -> 2 | R9: =B9*P1_PVP+C9*P2_PVP+D9*IF($A9<P3_DESDE,P3A_PVP,P3_PVP) -> 559.84 | S9: =IF(P9>0,R9/P9,"") -> 34.99 | T9: =IF(P9>0,N9/P9,"") -> 3.15375 | U9: =IF(N9>0,R9/N9,"") -> 11.094728 | V9: =IF(E9+F9+G9+H9+I9+J9>0,(E9+F9+G9)/(E9+F9+G9+H9+I9+J9),"") -> 0.5 | W9: =E9*(P1_PVP-P1_CPROD)+F9*(P2_PVP-P2_CPROD)+G9*(IF($A9<P3_DESDE,P3A_PVP,P3_PVP)-IF($A9<P3_DESDE,P3A_CPROD,P3_CPROD))-IF(ISNUMBER(L9),L9,E9*P1_LOG+F9*P2_LOG+G9*P3_LOG) -> 173.2331 | X9: =W9-(E9*P1_IVAN+F9*P2_IVAN+G9*IF($A9<P3_DESDE,P3A_IVAN,P3_IVAN))-(H9+I9+J9)*(COSTE_DEV-IVA_DEV)-AM9-AO9 -> 54.7231 | Y9: =AH9-AI9-AJ9-AK9-AL9-AM9-AO9 -> 56.291901 | AA9: =MAX(0,B9-E9-H9) -> 1 | AB9: =MAX(0,C9-F9-I9) -> 1 | AC9: =MAX(0,D9-G9-J9) -> 0 | AD9: =E9+AA9*AQ9 -> 4.27 | AE9: =F9+AB9*AQ9 -> 2.27 | AF9: =G9+AC9*AQ9 -> 1 | AG9: =H9+I9+J9+(AA9+AB9+AC9)*(1-AQ9) -> 8.46 | AH9: =AD9*P1_PVP+AE9*P2_PVP+AF9*IF($A9<P3_DESDE,P3A_PVP,P3_PVP) -> 268.8246 | AI9: =AD9*P1_CPROD+AE9*P2_CPROD+AF9*IF($A9<P3_DESDE,P3A_CPROD,P3_CPROD) -> 28.437299 | AJ9: =IF(ISNUMBER(L9),L9,E9*P1_LOG+F9*P2_LOG+G9*P3_LOG)+IF(ISNUMBER(M9),M9,AA9*P1_LOG+AB9*P2_LOG+AC9*P3_LOG)*AQ9 -> 54.5624 | AK9: =AG9*COSTE_DEV -> 63.873 | AL9: =AD9*P1_IVAN+AE9*P2_IVAN+AF9*IF($A9<P3_DESDE,P3A_IVAN,P3_IVAN)-AG9*IVA_DEV -> 0 | AM9: =N9*(1+RECARGO_ADS) -> 50.46 | AN9: =IF(ISNUMBER(L9),E9+F9+G9+AA9+AB9+AC9,0) -> 9 | AO9: =P9*COMISION -> 15.2 | AP9: =MIN(N(K9),Q9) -> 2 | AQ9: =IF(Q9>0,((Q9-AP9)*AT9+AP9*TASA_INC)/Q9,AT9) -> 0.27 | AR9: =IF($A9<FECHA_EXPORT,NETWORKDAYS($A9+1,FECHA_EXPORT,FESTIVOS),0) -> 10 | AS9: =IF(AR9>=5,1,INDEX(CDF_INC,1,AR9+1)) -> 1 | AT9: =TASA_USADA+(TASA_INC-TASA_USADA)*Q_INC*(1-AS9)/(1-Q_INC*AS9) -> 0.94117647
A10: 46304 | B10: 2 | C10: 3 | D10: 0 | E10: 1 | F10: 3 | H10: 1 | L10: 30.17 | M10: 0 | N10: 41.21 | P10: =B10+C10+D10 -> 5 | Q10: =AA10+AB10+AC10 -> 0 | R10: =B10*P1_PVP+C10*P2_PVP+D10*IF($A10<P3_DESDE,P3A_PVP,P3_PVP) -> 179.95 | S10: =IF(P10>0,R10/P10,"") -> 35.99 | T10: =IF(P10>0,N10/P10,"") -> 8.242 | U10: =IF(N10>0,R10/N10,"") -> 4.3666586 | V10: =IF(E10+F10+G10+H10+I10+J10>0,(E10+F10+G10)/(E10+F10+G10+H10+I10+J10),"") -> 0.8 | W10: =E10*(P1_PVP-P1_CPROD)+F10*(P2_PVP-P2_CPROD)+G10*(IF($A10<P3_DESDE,P3A_PVP,P3_PVP)-IF($A10<P3_DESDE,P3A_CPROD,P3_CPROD))-IF(ISNUMBER(L10),L10,E10*P1_LOG+F10*P2_LOG+G10*P3_LOG) -> 102.9347 | X10: =W10-(E10*P1_IVAN+F10*P2_IVAN+G10*IF($A10<P3_DESDE,P3A_IVAN,P3_IVAN))-(H10+I10+J10)*(COSTE_DEV-IVA_DEV)-AM10-AO10 -> 49.4247 | Y10: =AH10-AI10-AJ10-AK10-AL10-AM10-AO10 -> 49.4247 | AA10: =MAX(0,B10-E10-H10) -> 0 | AB10: =MAX(0,C10-F10-I10) -> 0 | AC10: =MAX(0,D10-G10-J10) -> 0 | AD10: =E10+AA10*AQ10 -> 1 | AE10: =F10+AB10*AQ10 -> 3 | AF10: =G10+AC10*AQ10 -> 0 | AG10: =H10+I10+J10+(AA10+AB10+AC10)*(1-AQ10) -> 1 | AH10: =AD10*P1_PVP+AE10*P2_PVP+AF10*IF($A10<P3_DESDE,P3A_PVP,P3_PVP) -> 149.96 | AI10: =AD10*P1_CPROD+AE10*P2_CPROD+AF10*IF($A10<P3_DESDE,P3A_CPROD,P3_CPROD) -> 16.8553 | AJ10: =IF(ISNUMBER(L10),L10,E10*P1_LOG+F10*P2_LOG+G10*P3_LOG)+IF(ISNUMBER(M10),M10,AA10*P1_LOG+AB10*P2_LOG+AC10*P3_LOG)*AQ10 -> 30.17 | AK10: =AG10*COSTE_DEV -> 7.55 | AL10: =AD10*P1_IVAN+AE10*P2_IVAN+AF10*IF($A10<P3_DESDE,P3A_IVAN,P3_IVAN)-AG10*IVA_DEV -> 0 | AM10: =N10*(1+RECARGO_ADS) -> 41.21 | AN10: =IF(ISNUMBER(L10),E10+F10+G10+AA10+AB10+AC10,0) -> 4 | AO10: =P10*COMISION -> 4.75 | AP10: =MIN(N(K10),Q10) -> 0 | AQ10: =IF(Q10>0,((Q10-AP10)*AT10+AP10*TASA_INC)/Q10,AT10) -> 0.94117647 | AR10: =IF($A10<FECHA_EXPORT,NETWORKDAYS($A10+1,FECHA_EXPORT,FESTIVOS),0) -> 9 | AS10: =IF(AR10>=5,1,INDEX(CDF_INC,1,AR10+1)) -> 1 | AT10: =TASA_USADA+(TASA_INC-TASA_USADA)*Q_INC*(1-AS10)/(1-Q_INC*AS10) -> 0.94117647
A11: 46305 | B11: 6 | C11: 2 | D11: 1 | E11: 3 | G11: 1 | H11: 3 | I11: 1 | K11: 1 | L11: 28.96 | M11: 8.06 | N11: 64.81 | P11: =B11+C11+D11 -> 9 | Q11: =AA11+AB11+AC11 -> 1 | R11: =B11*P1_PVP+C11*P2_PVP+D11*IF($A11<P3_DESDE,P3A_PVP,P3_PVP) -> 309.91 | S11: =IF(P11>0,R11/P11,"") -> 34.434444 | T11: =IF(P11>0,N11/P11,"") -> 7.2011111 | U11: =IF(N11>0,R11/N11,"") -> 4.7818238 | V11: =IF(E11+F11+G11+H11+I11+J11>0,(E11+F11+G11)/(E11+F11+G11+H11+I11+J11),"") -> 0.5 | W11: =E11*(P1_PVP-P1_CPROD)+F11*(P2_PVP-P2_CPROD)+G11*(IF($A11<P3_DESDE,P3A_PVP,P3_PVP)-IF($A11<P3_DESDE,P3A_CPROD,P3_CPROD))-IF(ISNUMBER(L11),L11,E11*P1_LOG+F11*P2_LOG+G11*P3_LOG) -> 96.5526 | X11: =W11-(E11*P1_IVAN+F11*P2_IVAN+G11*IF($A11<P3_DESDE,P3A_IVAN,P3_IVAN))-(H11+I11+J11)*(COSTE_DEV-IVA_DEV)-AM11-AO11 -> -7.0074 | Y11: =AH11-AI11-AJ11-AK11-AL11-AM11-AO11 -> -5.198066 | AA11: =MAX(0,B11-E11-H11) -> 0 | AB11: =MAX(0,C11-F11-I11) -> 1 | AC11: =MAX(0,D11-G11-J11) -> 0 | AD11: =E11+AA11*AQ11 -> 3 | AE11: =F11+AB11*AQ11 -> 0.27 | AF11: =G11+AC11*AQ11 -> 1 | AG11: =H11+I11+J11+(AA11+AB11+AC11)*(1-AQ11) -> 4.73 | AH11: =AD11*P1_PVP+AE11*P2_PVP+AF11*IF($A11<P3_DESDE,P3A_PVP,P3_PVP) -> 150.7573 | AI11: =AD11*P1_CPROD+AE11*P2_CPROD+AF11*IF($A11<P3_DESDE,P3A_CPROD,P3_CPROD) -> 15.747666 | AJ11: =IF(ISNUMBER(L11),L11,E11*P1_LOG+F11*P2_LOG+G11*P3_LOG)+IF(ISNUMBER(M11),M11,AA11*P1_LOG+AB11*P2_LOG+AC11*P3_LOG)*AQ11 -> 31.1362 | AK11: =AG11*COSTE_DEV -> 35.7115 | AL11: =AD11*P1_IVAN+AE11*P2_IVAN+AF11*IF($A11<P3_DESDE,P3A_IVAN,P3_IVAN)-AG11*IVA_DEV -> 0 | AM11: =N11*(1+RECARGO_ADS) -> 64.81 | AN11: =IF(ISNUMBER(L11),E11+F11+G11+AA11+AB11+AC11,0) -> 5 | AO11: =P11*COMISION -> 8.55 | AP11: =MIN(N(K11),Q11) -> 1 | AQ11: =IF(Q11>0,((Q11-AP11)*AT11+AP11*TASA_INC)/Q11,AT11) -> 0.27 | AR11: =IF($A11<FECHA_EXPORT,NETWORKDAYS($A11+1,FECHA_EXPORT,FESTIVOS),0) -> 9 | AS11: =IF(AR11>=5,1,INDEX(CDF_INC,1,AR11+1)) -> 1 | AT11: =TASA_USADA+(TASA_INC-TASA_USADA)*Q_INC*(1-AS11)/(1-Q_INC*AS11) -> 0.94117647
A12: 46306 | B12: 5 | C12: 1 | D12: 0 | E12: 1 | H12: 4 | I12: 1 | L12: 6.85 | M12: 0 | N12: 89.51 | P12: =B12+C12+D12 -> 6 | Q12: =AA12+AB12+AC12 -> 0 | R12: =B12*P1_PVP+C12*P2_PVP+D12*IF($A12<P3_DESDE,P3A_PVP,P3_PVP) -> 189.94 | S12: =IF(P12>0,R12/P12,"") -> 31.656667 | T12: =IF(P12>0,N12/P12,"") -> 14.918333 | U12: =IF(N12>0,R12/N12,"") -> 2.1219975 | V12: =IF(E12+F12+G12+H12+I12+J12>0,(E12+F12+G12)/(E12+F12+G12+H12+I12+J12),"") -> 0.16666667 | W12: =E12*(P1_PVP-P1_CPROD)+F12*(P2_PVP-P2_CPROD)+G12*(IF($A12<P3_DESDE,P3A_PVP,P3_PVP)-IF($A12<P3_DESDE,P3A_CPROD,P3_CPROD))-IF(ISNUMBER(L12),L12,E12*P1_LOG+F12*P2_LOG+G12*P3_LOG) -> 20.7321 | X12: =W12-(E12*P1_IVAN+F12*P2_IVAN+G12*IF($A12<P3_DESDE,P3A_IVAN,P3_IVAN))-(H12+I12+J12)*(COSTE_DEV-IVA_DEV)-AM12-AO12 -> -112.2279 | Y12: =AH12-AI12-AJ12-AK12-AL12-AM12-AO12 -> -112.2279 | AA12: =MAX(0,B12-E12-H12) -> 0 | AB12: =MAX(0,C12-F12-I12) -> 0 | AC12: =MAX(0,D12-G12-J12) -> 0 | AD12: =E12+AA12*AQ12 -> 1 | AE12: =F12+AB12*AQ12 -> 0 | AF12: =G12+AC12*AQ12 -> 0 | AG12: =H12+I12+J12+(AA12+AB12+AC12)*(1-AQ12) -> 5 | AH12: =AD12*P1_PVP+AE12*P2_PVP+AF12*IF($A12<P3_DESDE,P3A_PVP,P3_PVP) -> 29.99 | AI12: =AD12*P1_CPROD+AE12*P2_CPROD+AF12*IF($A12<P3_DESDE,P3A_CPROD,P3_CPROD) -> 2.4079 | AJ12: =IF(ISNUMBER(L12),L12,E12*P1_LOG+F12*P2_LOG+G12*P3_LOG)+IF(ISNUMBER(M12),M12,AA12*P1_LOG+AB12*P2_LOG+AC12*P3_LOG)*AQ12 -> 6.85 | AK12: =AG12*COSTE_DEV -> 37.75 | AL12: =AD12*P1_IVAN+AE12*P2_IVAN+AF12*IF($A12<P3_DESDE,P3A_IVAN,P3_IVAN)-AG12*IVA_DEV -> 0 | AM12: =N12*(1+RECARGO_ADS) -> 89.51 | AN12: =IF(ISNUMBER(L12),E12+F12+G12+AA12+AB12+AC12,0) -> 1 | AO12: =P12*COMISION -> 5.7 | AP12: =MIN(N(K12),Q12) -> 0 | AQ12: =IF(Q12>0,((Q12-AP12)*AT12+AP12*TASA_INC)/Q12,AT12) -> 0.94117647 | AR12: =IF($A12<FECHA_EXPORT,NETWORKDAYS($A12+1,FECHA_EXPORT,FESTIVOS),0) -> 9 | AS12: =IF(AR12>=5,1,INDEX(CDF_INC,1,AR12+1)) -> 1 | AT12: =TASA_USADA+(TASA_INC-TASA_USADA)*Q_INC*(1-AS12)/(1-Q_INC*AS12) -> 0.94117647
A13: 46307 | B13: 9 | C13: 3 | D13: 2 | E13: 4 | F13: 2 | G13: 1 | H13: 2 | I13: 1 | J13: 1 | K13: 3 | L13: 52.47 | M13: 21.98 | N13: 78.33 | P13: =B13+C13+D13 -> 14 | Q13: =AA13+AB13+AC13 -> 3 | R13: =B13*P1_PVP+C13*P2_PVP+D13*IF($A13<P3_DESDE,P3A_PVP,P3_PVP) -> 489.86 | S13: =IF(P13>0,R13/P13,"") -> 34.99 | T13: =IF(P13>0,N13/P13,"") -> 5.595 | U13: =IF(N13>0,R13/N13,"") -> 6.253798 | V13: =IF(E13+F13+G13+H13+I13+J13>0,(E13+F13+G13)/(E13+F13+G13+H13+I13+J13),"") -> 0.63636364 | W13: =E13*(P1_PVP-P1_CPROD)+F13*(P2_PVP-P2_CPROD)+G13*(IF($A13<P3_DESDE,P3A_PVP,P3_PVP)-IF($A13<P3_DESDE,P3A_CPROD,P3_CPROD))-IF(ISNUMBER(L13),L13,E13*P1_LOG+F13*P2_LOG+G13*P3_LOG) -> 170.9731 | X13: =W13-(E13*P1_IVAN+F13*P2_IVAN+G13*IF($A13<P3_DESDE,P3A_IVAN,P3_IVAN))-(H13+I13+J13)*(COSTE_DEV-IVA_DEV)-AM13-AO13 -> 49.1431 | Y13: =AH13-AI13-AJ13-AK13-AL13-AM13-AO13 -> 49.015501 | AA13: =MAX(0,B13-E13-H13) -> 3 | AB13: =MAX(0,C13-F13-I13) -> 0 | AC13: =MAX(0,D13-G13-J13) -> 0 | AD13: =E13+AA13*AQ13 -> 4.81 | AE13: =F13+AB13*AQ13 -> 2 | AF13: =G13+AC13*AQ13 -> 1 | AG13: =H13+I13+J13+(AA13+AB13+AC13)*(1-AQ13) -> 6.19 | AH13: =AD13*P1_PVP+AE13*P2_PVP+AF13*IF($A13<P3_DESDE,P3A_PVP,P3_PVP) -> 274.2219 | AI13: =AD13*P1_CPROD+AE13*P2_CPROD+AF13*IF($A13<P3_DESDE,P3A_CPROD,P3_CPROD) -> 28.437299 | AJ13: =IF(ISNUMBER(L13),L13,E13*P1_LOG+F13*P2_LOG+G13*P3_LOG)+IF(ISNUMBER(M13),M13,AA13*P1_LOG+AB13*P2_LOG+AC13*P3_LOG)*AQ13 -> 58.4046 | AK13: =AG13*COSTE_DEV -> 46.7345 | AL13: =AD13*P1_IVAN+AE13*P2_IVAN+AF13*IF($A13<P3_DESDE,P3A_IVAN,P3_IVAN)-AG13*IVA_DEV -> 0 | AM13: =N13*(1+RECARGO_ADS) -> 78.33 | AN13: =IF(ISNUMBER(L13),E13+F13+G13+AA13+AB13+AC13,0) -> 10 | AO13: =P13*COMISION -> 13.3 | AP13: =MIN(N(K13),Q13) -> 3 | AQ13: =IF(Q13>0,((Q13-AP13)*AT13+AP13*TASA_INC)/Q13,AT13) -> 0.27 | AR13: =IF($A13<FECHA_EXPORT,NETWORKDAYS($A13+1,FECHA_EXPORT,FESTIVOS),0) -> 9 | AS13: =IF(AR13>=5,1,INDEX(CDF_INC,1,AR13+1)) -> 1 | AT13: =TASA_USADA+(TASA_INC-TASA_USADA)*Q_INC*(1-AS13)/(1-Q_INC*AS13) -> 0.94117647
A14: 46308 | B14: 7 | C14: 1 | D14: 1 | E14: 4 | F14: 1 | H14: 1 | K14: 3 | L14: 37.56 | M14: 24.18 | N14: 68.05 | P14: =B14+C14+D14 -> 9 | Q14: =AA14+AB14+AC14 -> 3 | R14: =B14*P1_PVP+C14*P2_PVP+D14*IF($A14<P3_DESDE,P3A_PVP,P3_PVP) -> 299.91 | S14: =IF(P14>0,R14/P14,"") -> 33.323333 | T14: =IF(P14>0,N14/P14,"") -> 7.5611111 | U14: =IF(N14>0,R14/N14,"") -> 4.4072006 | V14: =IF(E14+F14+G14+H14+I14+J14>0,(E14+F14+G14)/(E14+F14+G14+H14+I14+J14),"") -> 0.83333333 | W14: =E14*(P1_PVP-P1_CPROD)+F14*(P2_PVP-P2_CPROD)+G14*(IF($A14<P3_DESDE,P3A_PVP,P3_PVP)-IF($A14<P3_DESDE,P3A_CPROD,P3_CPROD))-IF(ISNUMBER(L14),L14,E14*P1_LOG+F14*P2_LOG+G14*P3_LOG) -> 107.9426 | X14: =W14-(E14*P1_IVAN+F14*P2_IVAN+G14*IF($A14<P3_DESDE,P3A_IVAN,P3_IVAN))-(H14+I14+J14)*(COSTE_DEV-IVA_DEV)-AM14-AO14 -> 23.7926 | Y14: =AH14-AI14-AJ14-AK14-AL14-AM14-AO14 -> 27.170735 | AA14: =MAX(0,B14-E14-H14) -> 2 | AB14: =MAX(0,C14-F14-I14) -> 0 | AC14: =MAX(0,D14-G14-J14) -> 1 | AD14: =E14+AA14*AQ14 -> 4.54 | AE14: =F14+AB14*AQ14 -> 1 | AF14: =G14+AC14*AQ14 -> 0.27 | AG14: =H14+I14+J14+(AA14+AB14+AC14)*(1-AQ14) -> 3.19 | AH14: =AD14*P1_PVP+AE14*P2_PVP+AF14*IF($A14<P3_DESDE,P3A_PVP,P3_PVP) -> 189.6419 | AI14: =AD14*P1_CPROD+AE14*P2_CPROD+AF14*IF($A14<P3_DESDE,P3A_CPROD,P3_CPROD) -> 17.698065 | AJ14: =IF(ISNUMBER(L14),L14,E14*P1_LOG+F14*P2_LOG+G14*P3_LOG)+IF(ISNUMBER(M14),M14,AA14*P1_LOG+AB14*P2_LOG+AC14*P3_LOG)*AQ14 -> 44.0886 | AK14: =AG14*COSTE_DEV -> 24.0845 | AL14: =AD14*P1_IVAN+AE14*P2_IVAN+AF14*IF($A14<P3_DESDE,P3A_IVAN,P3_IVAN)-AG14*IVA_DEV -> 0 | AM14: =N14*(1+RECARGO_ADS) -> 68.05 | AN14: =IF(ISNUMBER(L14),E14+F14+G14+AA14+AB14+AC14,0) -> 8 | AO14: =P14*COMISION -> 8.55 | AP14: =MIN(N(K14),Q14) -> 3 | AQ14: =IF(Q14>0,((Q14-AP14)*AT14+AP14*TASA_INC)/Q14,AT14) -> 0.27 | AR14: =IF($A14<FECHA_EXPORT,NETWORKDAYS($A14+1,FECHA_EXPORT,FESTIVOS),0) -> 8 | AS14: =IF(AR14>=5,1,INDEX(CDF_INC,1,AR14+1)) -> 1 | AT14: =TASA_USADA+(TASA_INC-TASA_USADA)*Q_INC*(1-AS14)/(1-Q_INC*AS14) -> 0.94117647
A15: 46309 | B15: 5 | C15: 4 | D15: 0 | E15: 4 | F15: 2 | K15: 3 | L15: 45.11 | M15: 23.51 | N15: 73.35 | P15: =B15+C15+D15 -> 9 | Q15: =AA15+AB15+AC15 -> 3 | R15: =B15*P1_PVP+C15*P2_PVP+D15*IF($A15<P3_DESDE,P3A_PVP,P3_PVP) -> 309.91 | S15: =IF(P15>0,R15/P15,"") -> 34.434444 | T15: =IF(P15>0,N15/P15,"") -> 8.15 | U15: =IF(N15>0,R15/N15,"") -> 4.2250852 | V15: =IF(E15+F15+G15+H15+I15+J15>0,(E15+F15+G15)/(E15+F15+G15+H15+I15+J15),"") -> 1 | W15: =E15*(P1_PVP-P1_CPROD)+F15*(P2_PVP-P2_CPROD)+G15*(IF($A15<P3_DESDE,P3A_PVP,P3_PVP)-IF($A15<P3_DESDE,P3A_CPROD,P3_CPROD))-IF(ISNUMBER(L15),L15,E15*P1_LOG+F15*P2_LOG+G15*P3_LOG) -> 135.5668 | X15: =W15-(E15*P1_IVAN+F15*P2_IVAN+G15*IF($A15<P3_DESDE,P3A_IVAN,P3_IVAN))-(H15+I15+J15)*(COSTE_DEV-IVA_DEV)-AM15-AO15 -> 53.6668 | Y15: =AH15-AI15-AJ15-AK15-AL15-AM15-AO15 -> 57.225835 | AA15: =MAX(0,B15-E15-H15) -> 1 | AB15: =MAX(0,C15-F15-I15) -> 2 | AC15: =MAX(0,D15-G15-J15) -> 0 | AD15: =E15+AA15*AQ15 -> 4.27 | AE15: =F15+AB15*AQ15 -> 2.54 | AF15: =G15+AC15*AQ15 -> 0 | AG15: =H15+I15+J15+(AA15+AB15+AC15)*(1-AQ15) -> 2.19 | AH15: =AD15*P1_PVP+AE15*P2_PVP+AF15*IF($A15<P3_DESDE,P3A_PVP,P3_PVP) -> 229.6319 | AI15: =AD15*P1_CPROD+AE15*P2_CPROD+AF15*IF($A15<P3_DESDE,P3A_CPROD,P3_CPROD) -> 22.513865 | AJ15: =IF(ISNUMBER(L15),L15,E15*P1_LOG+F15*P2_LOG+G15*P3_LOG)+IF(ISNUMBER(M15),M15,AA15*P1_LOG+AB15*P2_LOG+AC15*P3_LOG)*AQ15 -> 51.4577 | AK15: =AG15*COSTE_DEV -> 16.5345 | AL15: =AD15*P1_IVAN+AE15*P2_IVAN+AF15*IF($A15<P3_DESDE,P3A_IVAN,P3_IVAN)-AG15*IVA_DEV -> 0 | AM15: =N15*(1+RECARGO_ADS) -> 73.35 | AN15: =IF(ISNUMBER(L15),E15+F15+G15+AA15+AB15+AC15,0) -> 9 | AO15: =P15*COMISION -> 8.55 | AP15: =MIN(N(K15),Q15) -> 3 | AQ15: =IF(Q15>0,((Q15-AP15)*AT15+AP15*TASA_INC)/Q15,AT15) -> 0.27 | AR15: =IF($A15<FECHA_EXPORT,NETWORKDAYS($A15+1,FECHA_EXPORT,FESTIVOS),0) -> 7 | AS15: =IF(AR15>=5,1,INDEX(CDF_INC,1,AR15+1)) -> 1 | AT15: =TASA_USADA+(TASA_INC-TASA_USADA)*Q_INC*(1-AS15)/(1-Q_INC*AS15) -> 0.94117647
A16: 46310 | B16: 2 | C16: 3 | D16: 0 | E16: 1 | F16: 3 | K16: 1 | L16: 29.85 | M16: 8.06 | N16: 60.8 | P16: =B16+C16+D16 -> 5 | Q16: =AA16+AB16+AC16 -> 1 | R16: =B16*P1_PVP+C16*P2_PVP+D16*IF($A16<P3_DESDE,P3A_PVP,P3_PVP) -> 179.95 | S16: =IF(P16>0,R16/P16,"") -> 35.99 | T16: =IF(P16>0,N16/P16,"") -> 12.16 | U16: =IF(N16>0,R16/N16,"") -> 2.9597039 | V16: =IF(E16+F16+G16+H16+I16+J16>0,(E16+F16+G16)/(E16+F16+G16+H16+I16+J16),"") -> 1 | W16: =E16*(P1_PVP-P1_CPROD)+F16*(P2_PVP-P2_CPROD)+G16*(IF($A16<P3_DESDE,P3A_PVP,P3_PVP)-IF($A16<P3_DESDE,P3A_CPROD,P3_CPROD))-IF(ISNUMBER(L16),L16,E16*P1_LOG+F16*P2_LOG+G16*P3_LOG) -> 103.2547 | X16: =W16-(E16*P1_IVAN+F16*P2_IVAN+G16*IF($A16<P3_DESDE,P3A_IVAN,P3_IVAN))-(H16+I16+J16)*(COSTE_DEV-IVA_DEV)-AM16-AO16 -> 37.7047 | Y16: =AH16-AI16-AJ16-AK16-AL16-AM16-AO16 -> 37.464167 | AA16: =MAX(0,B16-E16-H16) -> 1 | AB16: =MAX(0,C16-F16-I16) -> 0 | AC16: =MAX(0,D16-G16-J16) -> 0 | AD16: =E16+AA16*AQ16 -> 1.27 | AE16: =F16+AB16*AQ16 -> 3 | AF16: =G16+AC16*AQ16 -> 0 | AG16: =H16+I16+J16+(AA16+AB16+AC16)*(1-AQ16) -> 0.73 | AH16: =AD16*P1_PVP+AE16*P2_PVP+AF16*IF($A16<P3_DESDE,P3A_PVP,P3_PVP) -> 158.0573 | AI16: =AD16*P1_CPROD+AE16*P2_CPROD+AF16*IF($A16<P3_DESDE,P3A_CPROD,P3_CPROD) -> 17.505433 | AJ16: =IF(ISNUMBER(L16),L16,E16*P1_LOG+F16*P2_LOG+G16*P3_LOG)+IF(ISNUMBER(M16),M16,AA16*P1_LOG+AB16*P2_LOG+AC16*P3_LOG)*AQ16 -> 32.0262 | AK16: =AG16*COSTE_DEV -> 5.5115 | AL16: =AD16*P1_IVAN+AE16*P2_IVAN+AF16*IF($A16<P3_DESDE,P3A_IVAN,P3_IVAN)-AG16*IVA_DEV -> 0 | AM16: =N16*(1+RECARGO_ADS) -> 60.8 | AN16: =IF(ISNUMBER(L16),E16+F16+G16+AA16+AB16+AC16,0) -> 5 | AO16: =P16*COMISION -> 4.75 | AP16: =MIN(N(K16),Q16) -> 1 | AQ16: =IF(Q16>0,((Q16-AP16)*AT16+AP16*TASA_INC)/Q16,AT16) -> 0.27 | AR16: =IF($A16<FECHA_EXPORT,NETWORKDAYS($A16+1,FECHA_EXPORT,FESTIVOS),0) -> 6 | AS16: =IF(AR16>=5,1,INDEX(CDF_INC,1,AR16+1)) -> 1 | AT16: =TASA_USADA+(TASA_INC-TASA_USADA)*Q_INC*(1-AS16)/(1-Q_INC*AS16) -> 0.94117647
A17: 46311 | B17: 5 | C17: 7 | D17: 0 | E17: 3 | F17: 4 | K17: 5 | L17: 51.26 | M17: 39.63 | N17: 100.4 | P17: =B17+C17+D17 -> 12 | Q17: =AA17+AB17+AC17 -> 5 | R17: =B17*P1_PVP+C17*P2_PVP+D17*IF($A17<P3_DESDE,P3A_PVP,P3_PVP) -> 429.88 | S17: =IF(P17>0,R17/P17,"") -> 35.823333 | T17: =IF(P17>0,N17/P17,"") -> 8.3666667 | U17: =IF(N17>0,R17/N17,"") -> 4.2816733 | V17: =IF(E17+F17+G17+H17+I17+J17>0,(E17+F17+G17)/(E17+F17+G17+H17+I17+J17),"") -> 1 | W17: =E17*(P1_PVP-P1_CPROD)+F17*(P2_PVP-P2_CPROD)+G17*(IF($A17<P3_DESDE,P3A_PVP,P3_PVP)-IF($A17<P3_DESDE,P3A_CPROD,P3_CPROD))-IF(ISNUMBER(L17),L17,E17*P1_LOG+F17*P2_LOG+G17*P3_LOG) -> 172.1831 | X17: =W17-(E17*P1_IVAN+F17*P2_IVAN+G17*IF($A17<P3_DESDE,P3A_IVAN,P3_IVAN))-(H17+I17+J17)*(COSTE_DEV-IVA_DEV)-AM17-AO17 -> 60.3831 | Y17: =AH17-AI17-AJ17-AK17-AL17-AM17-AO17 -> 65.510936 | AA17: =MAX(0,B17-E17-H17) -> 2 | AB17: =MAX(0,C17-F17-I17) -> 3 | AC17: =MAX(0,D17-G17-J17) -> 0 | AD17: =E17+AA17*AQ17 -> 3.54 | AE17: =F17+AB17*AQ17 -> 4.81 | AF17: =G17+AC17*AQ17 -> 0 | AG17: =H17+I17+J17+(AA17+AB17+AC17)*(1-AQ17) -> 3.65 | AH17: =AD17*P1_PVP+AE17*P2_PVP+AF17*IF($A17<P3_DESDE,P3A_PVP,P3_PVP) -> 298.5165 | AI17: =AD17*P1_CPROD+AE17*P2_CPROD+AF17*IF($A17<P3_DESDE,P3A_CPROD,P3_CPROD) -> 31.687964 | AJ17: =IF(ISNUMBER(L17),L17,E17*P1_LOG+F17*P2_LOG+G17*P3_LOG)+IF(ISNUMBER(M17),M17,AA17*P1_LOG+AB17*P2_LOG+AC17*P3_LOG)*AQ17 -> 61.9601 | AK17: =AG17*COSTE_DEV -> 27.5575 | AL17: =AD17*P1_IVAN+AE17*P2_IVAN+AF17*IF($A17<P3_DESDE,P3A_IVAN,P3_IVAN)-AG17*IVA_DEV -> 0 | AM17: =N17*(1+RECARGO_ADS) -> 100.4 | AN17: =IF(ISNUMBER(L17),E17+F17+G17+AA17+AB17+AC17,0) -> 12 | AO17: =P17*COMISION -> 11.4 | AP17: =MIN(N(K17),Q17) -> 5 | AQ17: =IF(Q17>0,((Q17-AP17)*AT17+AP17*TASA_INC)/Q17,AT17) -> 0.27 | AR17: =IF($A17<FECHA_EXPORT,NETWORKDAYS($A17+1,FECHA_EXPORT,FESTIVOS),0) -> 5 | AS17: =IF(AR17>=5,1,INDEX(CDF_INC,1,AR17+1)) -> 1 | AT17: =TASA_USADA+(TASA_INC-TASA_USADA)*Q_INC*(1-AS17)/(1-Q_INC*AS17) -> 0.94117647
A18: 46312 | B18: 3 | C18: 5 | D18: 1 | E18: 3 | F18: 2 | K18: 3 | L18: 35.7 | M18: 28.76 | N18: 81.87 | P18: =B18+C18+D18 -> 9 | Q18: =AA18+AB18+AC18 -> 4 | R18: =B18*P1_PVP+C18*P2_PVP+D18*IF($A18<P3_DESDE,P3A_PVP,P3_PVP) -> 349.91 | S18: =IF(P18>0,R18/P18,"") -> 38.878889 | T18: =IF(P18>0,N18/P18,"") -> 9.0966667 | U18: =IF(N18>0,R18/N18,"") -> 4.2739709 | V18: =IF(E18+F18+G18+H18+I18+J18>0,(E18+F18+G18)/(E18+F18+G18+H18+I18+J18),"") -> 1 | W18: =E18*(P1_PVP-P1_CPROD)+F18*(P2_PVP-P2_CPROD)+G18*(IF($A18<P3_DESDE,P3A_PVP,P3_PVP)-IF($A18<P3_DESDE,P3A_CPROD,P3_CPROD))-IF(ISNUMBER(L18),L18,E18*P1_LOG+F18*P2_LOG+G18*P3_LOG) -> 117.3947 | X18: =W18-(E18*P1_IVAN+F18*P2_IVAN+G18*IF($A18<P3_DESDE,P3A_IVAN,P3_IVAN))-(H18+I18+J18)*(COSTE_DEV-IVA_DEV)-AM18-AO18 -> 26.9747 | Y18: =AH18-AI18-AJ18-AK18-AL18-AM18-AO18 -> 64.483447 | AA18: =MAX(0,B18-E18-H18) -> 0 | AB18: =MAX(0,C18-F18-I18) -> 3 | AC18: =MAX(0,D18-G18-J18) -> 1 | AD18: =E18+AA18*AQ18 -> 3 | AE18: =F18+AB18*AQ18 -> 3.3133824 | AF18: =G18+AC18*AQ18 -> 0.43779412 | AG18: =H18+I18+J18+(AA18+AB18+AC18)*(1-AQ18) -> 2.2488235 | AH18: =AD18*P1_PVP+AE18*P2_PVP+AF18*IF($A18<P3_DESDE,P3A_PVP,P3_PVP) -> 248.73543 | AI18: =AD18*P1_CPROD+AE18*P2_CPROD+AF18*IF($A18<P3_DESDE,P3A_CPROD,P3_CPROD) -> 28.562405 | AJ18: =IF(ISNUMBER(L18),L18,E18*P1_LOG+F18*P2_LOG+G18*P3_LOG)+IF(ISNUMBER(M18),M18,AA18*P1_LOG+AB18*P2_LOG+AC18*P3_LOG)*AQ18 -> 48.290959 | AK18: =AG18*COSTE_DEV -> 16.978618 | AL18: =AD18*P1_IVAN+AE18*P2_IVAN+AF18*IF($A18<P3_DESDE,P3A_IVAN,P3_IVAN)-AG18*IVA_DEV -> 0 | AM18: =N18*(1+RECARGO_ADS) -> 81.87 | AN18: =IF(ISNUMBER(L18),E18+F18+G18+AA18+AB18+AC18,0) -> 9 | AO18: =P18*COMISION -> 8.55 | AP18: =MIN(N(K18),Q18) -> 3 | AQ18: =IF(Q18>0,((Q18-AP18)*AT18+AP18*TASA_INC)/Q18,AT18) -> 0.43779412 | AR18: =IF($A18<FECHA_EXPORT,NETWORKDAYS($A18+1,FECHA_EXPORT,FESTIVOS),0) -> 5 | AS18: =IF(AR18>=5,1,INDEX(CDF_INC,1,AR18+1)) -> 1 | AT18: =TASA_USADA+(TASA_INC-TASA_USADA)*Q_INC*(1-AS18)/(1-Q_INC*AS18) -> 0.94117647
A19: 46313 | B19: 4 | C19: 6 | D19: 2 | E19: 1 | F19: 3 | K19: 2 | L19: 27 | M19: 54 | N19: 149.88 | P19: =B19+C19+D19 -> 12 | Q19: =AA19+AB19+AC19 -> 8 | R19: =B19*P1_PVP+C19*P2_PVP+D19*IF($A19<P3_DESDE,P3A_PVP,P3_PVP) -> 479.88 | S19: =IF(P19>0,R19/P19,"") -> 39.99 | T19: =IF(P19>0,N19/P19,"") -> 12.49 | U19: =IF(N19>0,R19/N19,"") -> 3.2017614 | V19: =IF(E19+F19+G19+H19+I19+J19>0,(E19+F19+G19)/(E19+F19+G19+H19+I19+J19),"") -> 1 | W19: =E19*(P1_PVP-P1_CPROD)+F19*(P2_PVP-P2_CPROD)+G19*(IF($A19<P3_DESDE,P3A_PVP,P3_PVP)-IF($A19<P3_DESDE,P3A_CPROD,P3_CPROD))-IF(ISNUMBER(L19),L19,E19*P1_LOG+F19*P2_LOG+G19*P3_LOG) -> 106.1047 | X19: =W19-(E19*P1_IVAN+F19*P2_IVAN+G19*IF($A19<P3_DESDE,P3A_IVAN,P3_IVAN))-(H19+I19+J19)*(COSTE_DEV-IVA_DEV)-AM19-AO19 -> -55.1753 | Y19: =AH19-AI19-AJ19-AK19-AL19-AM19-AO19 -> 108.75311 | AA19: =MAX(0,B19-E19-H19) -> 3 | AB19: =MAX(0,C19-F19-I19) -> 3 | AC19: =MAX(0,D19-G19-J19) -> 2 | AD19: =E19+AA19*AQ19 -> 3.3201471 | AE19: =F19+AB19*AQ19 -> 5.3201471 | AF19: =G19+AC19*AQ19 -> 1.5467647 | AG19: =H19+I19+J19+(AA19+AB19+AC19)*(1-AQ19) -> 1.8129412 | AH19: =AD19*P1_PVP+AE19*P2_PVP+AF19*IF($A19<P3_DESDE,P3A_PVP,P3_PVP) -> 405.11431 | AI19: =AD19*P1_CPROD+AE19*P2_CPROD+AF19*IF($A19<P3_DESDE,P3A_CPROD,P3_CPROD) -> 52.63084 | AJ19: =IF(ISNUMBER(L19),L19,E19*P1_LOG+F19*P2_LOG+G19*P3_LOG)+IF(ISNUMBER(M19),M19,AA19*P1_LOG+AB19*P2_LOG+AC19*P3_LOG)*AQ19 -> 68.762647 | AK19: =AG19*COSTE_DEV -> 13.687706 | AL19: =AD19*P1_IVAN+AE19*P2_IVAN+AF19*IF($A19<P3_DESDE,P3A_IVAN,P3_IVAN)-AG19*IVA_DEV -> 0 | AM19: =N19*(1+RECARGO_ADS) -> 149.88 | AN19: =IF(ISNUMBER(L19),E19+F19+G19+AA19+AB19+AC19,0) -> 12 | AO19: =P19*COMISION -> 11.4 | AP19: =MIN(N(K19),Q19) -> 2 | AQ19: =IF(Q19>0,((Q19-AP19)*AT19+AP19*TASA_INC)/Q19,AT19) -> 0.77338235 | AR19: =IF($A19<FECHA_EXPORT,NETWORKDAYS($A19+1,FECHA_EXPORT,FESTIVOS),0) -> 5 | AS19: =IF(AR19>=5,1,INDEX(CDF_INC,1,AR19+1)) -> 1 | AT19: =TASA_USADA+(TASA_INC-TASA_USADA)*Q_INC*(1-AS19)/(1-Q_INC*AS19) -> 0.94117647
A20: 46314 | B20: 5 | C20: 1 | D20: 2 | E20: 2 | G20: 2 | K20: 1 | L20: 27 | M20: 27 | N20: 85.31 | P20: =B20+C20+D20 -> 8 | Q20: =AA20+AB20+AC20 -> 4 | R20: =B20*P1_PVP+C20*P2_PVP+D20*IF($A20<P3_DESDE,P3A_PVP,P3_PVP) -> 309.92 | S20: =IF(P20>0,R20/P20,"") -> 38.74 | T20: =IF(P20>0,N20/P20,"") -> 10.66375 | U20: =IF(N20>0,R20/N20,"") -> 3.6328684 | V20: =IF(E20+F20+G20+H20+I20+J20>0,(E20+F20+G20)/(E20+F20+G20+H20+I20+J20),"") -> 1 | W20: =E20*(P1_PVP-P1_CPROD)+F20*(P2_PVP-P2_CPROD)+G20*(IF($A20<P3_DESDE,P3A_PVP,P3_PVP)-IF($A20<P3_DESDE,P3A_CPROD,P3_CPROD))-IF(ISNUMBER(L20),L20,E20*P1_LOG+F20*P2_LOG+G20*P3_LOG) -> 123.55676 | X20: =W20-(E20*P1_IVAN+F20*P2_IVAN+G20*IF($A20<P3_DESDE,P3A_IVAN,P3_IVAN))-(H20+I20+J20)*(COSTE_DEV-IVA_DEV)-AM20-AO20 -> 30.646758 | Y20: =AH20-AI20-AJ20-AK20-AL20-AM20-AO20 -> 93.113128 | AA20: =MAX(0,B20-E20-H20) -> 3 | AB20: =MAX(0,C20-F20-I20) -> 1 | AC20: =MAX(0,D20-G20-J20) -> 0 | AD20: =E20+AA20*AQ20 -> 4.2952276 | AE20: =F20+AB20*AQ20 -> 0.76507586 | AF20: =G20+AC20*AQ20 -> 2 | AG20: =H20+I20+J20+(AA20+AB20+AC20)*(1-AQ20) -> 0.93969657 | AH20: =AD20*P1_PVP+AE20*P2_PVP+AF20*IF($A20<P3_DESDE,P3A_PVP,P3_PVP) -> 279.38926 | AI20: =AD20*P1_CPROD+AE20*P2_CPROD+AF20*IF($A20<P3_DESDE,P3A_CPROD,P3_CPROD) -> 38.614373 | AJ20: =IF(ISNUMBER(L20),L20,E20*P1_LOG+F20*P2_LOG+G20*P3_LOG)+IF(ISNUMBER(M20),M20,AA20*P1_LOG+AB20*P2_LOG+AC20*P3_LOG)*AQ20 -> 47.657048 | AK20: =AG20*COSTE_DEV -> 7.0947091 | AL20: =AD20*P1_IVAN+AE20*P2_IVAN+AF20*IF($A20<P3_DESDE,P3A_IVAN,P3_IVAN)-AG20*IVA_DEV -> 0 | AM20: =N20*(1+RECARGO_ADS) -> 85.31 | AN20: =IF(ISNUMBER(L20),E20+F20+G20+AA20+AB20+AC20,0) -> 8 | AO20: =P20*COMISION -> 7.6 | AP20: =MIN(N(K20),Q20) -> 1 | AQ20: =IF(Q20>0,((Q20-AP20)*AT20+AP20*TASA_INC)/Q20,AT20) -> 0.76507586 | AR20: =IF($A20<FECHA_EXPORT,NETWORKDAYS($A20+1,FECHA_EXPORT,FESTIVOS),0) -> 4 | AS20: =IF(AR20>=5,1,INDEX(CDF_INC,1,AR20+1)) -> 0.98 | AT20: =TASA_USADA+(TASA_INC-TASA_USADA)*Q_INC*(1-AS20)/(1-Q_INC*AS20) -> 0.93010114
A21: 46315 | B21: 3 | C21: 2 | D21: 1 | E21: 1 | F21: 1 | K21: 1 | L21: 13.5 | M21: 27 | N21: 71.96 | P21: =B21+C21+D21 -> 6 | Q21: =AA21+AB21+AC21 -> 4 | R21: =B21*P1_PVP+C21*P2_PVP+D21*IF($A21<P3_DESDE,P3A_PVP,P3_PVP) -> 229.94 | S21: =IF(P21>0,R21/P21,"") -> 38.323333 | T21: =IF(P21>0,N21/P21,"") -> 11.993333 | U21: =IF(N21>0,R21/N21,"") -> 3.1953863 | V21: =IF(E21+F21+G21+H21+I21+J21>0,(E21+F21+G21)/(E21+F21+G21+H21+I21+J21),"") -> 1 | W21: =E21*(P1_PVP-P1_CPROD)+F21*(P2_PVP-P2_CPROD)+G21*(IF($A21<P3_DESDE,P3A_PVP,P3_PVP)-IF($A21<P3_DESDE,P3A_CPROD,P3_CPROD))-IF(ISNUMBER(L21),L21,E21*P1_LOG+F21*P2_LOG+G21*P3_LOG) -> 49.2563 | X21: =W21-(E21*P1_IVAN+F21*P2_IVAN+G21*IF($A21<P3_DESDE,P3A_IVAN,P3_IVAN))-(H21+I21+J21)*(COSTE_DEV-IVA_DEV)-AM21-AO21 -> -28.4037 | Y21: =AH21-AI21-AJ21-AK21-AL21-AM21-AO21 -> 46.153396 | AA21: =MAX(0,B21-E21-H21) -> 2 | AB21: =MAX(0,C21-F21-I21) -> 1 | AC21: =MAX(0,D21-G21-J21) -> 1 | AD21: =E21+AA21*AQ21 -> 2.4834472 | AE21: =F21+AB21*AQ21 -> 1.7417236 | AF21: =G21+AC21*AQ21 -> 0.74172361 | AG21: =H21+I21+J21+(AA21+AB21+AC21)*(1-AQ21) -> 1.0331056 | AH21: =AD21*P1_PVP+AE21*P2_PVP+AF21*IF($A21<P3_DESDE,P3A_PVP,P3_PVP) -> 188.62611 | AI21: =AD21*P1_CPROD+AE21*P2_CPROD+AF21*IF($A21<P3_DESDE,P3A_CPROD,P3_CPROD) -> 23.486228 | AJ21: =IF(ISNUMBER(L21),L21,E21*P1_LOG+F21*P2_LOG+G21*P3_LOG)+IF(ISNUMBER(M21),M21,AA21*P1_LOG+AB21*P2_LOG+AC21*P3_LOG)*AQ21 -> 33.526537 | AK21: =AG21*COSTE_DEV -> 7.799947 | AL21: =AD21*P1_IVAN+AE21*P2_IVAN+AF21*IF($A21<P3_DESDE,P3A_IVAN,P3_IVAN)-AG21*IVA_DEV -> 0 | AM21: =N21*(1+RECARGO_ADS) -> 71.96 | AN21: =IF(ISNUMBER(L21),E21+F21+G21+AA21+AB21+AC21,0) -> 6 | AO21: =P21*COMISION -> 5.7 | AP21: =MIN(N(K21),Q21) -> 1 | AQ21: =IF(Q21>0,((Q21-AP21)*AT21+AP21*TASA_INC)/Q21,AT21) -> 0.74172361 | AR21: =IF($A21<FECHA_EXPORT,NETWORKDAYS($A21+1,FECHA_EXPORT,FESTIVOS),0) -> 3 | AS21: =IF(AR21>=5,1,INDEX(CDF_INC,1,AR21+1)) -> 0.92 | AT21: =TASA_USADA+(TASA_INC-TASA_USADA)*Q_INC*(1-AS21)/(1-Q_INC*AS21) -> 0.89896481
A22: 46316 | B22: 1 | C22: 3 | D22: 1 | G22: 1 | K22: 1 | L22: 6.75 | M22: 27 | N22: 79.53 | P22: =B22+C22+D22 -> 5 | Q22: =AA22+AB22+AC22 -> 4 | R22: =B22*P1_PVP+C22*P2_PVP+D22*IF($A22<P3_DESDE,P3A_PVP,P3_PVP) -> 209.95 | S22: =IF(P22>0,R22/P22,"") -> 41.99 | T22: =IF(P22>0,N22/P22,"") -> 15.906 | U22: =IF(N22>0,R22/N22,"") -> 2.6398843 | V22: =IF(E22+F22+G22+H22+I22+J22>0,(E22+F22+G22)/(E22+F22+G22+H22+I22+J22),"") -> 1 | W22: =E22*(P1_PVP-P1_CPROD)+F22*(P2_PVP-P2_CPROD)+G22*(IF($A22<P3_DESDE,P3A_PVP,P3_PVP)-IF($A22<P3_DESDE,P3A_CPROD,P3_CPROD))-IF(ISNUMBER(L22),L22,E22*P1_LOG+F22*P2_LOG+G22*P3_LOG) -> 40.946279 | X22: =W22-(E22*P1_IVAN+F22*P2_IVAN+G22*IF($A22<P3_DESDE,P3A_IVAN,P3_IVAN))-(H22+I22+J22)*(COSTE_DEV-IVA_DEV)-AM22-AO22 -> -43.333721 | Y22: =AH22-AI22-AJ22-AK22-AL22-AM22-AO22 -> 18.085867 | AA22: =MAX(0,B22-E22-H22) -> 1 | AB22: =MAX(0,C22-F22-I22) -> 3 | AC22: =MAX(0,D22-G22-J22) -> 0 | AD22: =E22+AA22*AQ22 -> 0.67216749 | AE22: =F22+AB22*AQ22 -> 2.0165025 | AF22: =G22+AC22*AQ22 -> 1 | AG22: =H22+I22+J22+(AA22+AB22+AC22)*(1-AQ22) -> 1.31133 | AH22: =AD22*P1_PVP+AE22*P2_PVP+AF22*IF($A22<P3_DESDE,P3A_PVP,P3_PVP) -> 160.78824 | AI22: =AD22*P1_CPROD+AE22*P2_CPROD+AF22*IF($A22<P3_DESDE,P3A_CPROD,P3_CPROD) -> 23.623306 | AJ22: =IF(ISNUMBER(L22),L22,E22*P1_LOG+F22*P2_LOG+G22*P3_LOG)+IF(ISNUMBER(M22),M22,AA22*P1_LOG+AB22*P2_LOG+AC22*P3_LOG)*AQ22 -> 24.898522 | AK22: =AG22*COSTE_DEV -> 9.9005418 | AL22: =AD22*P1_IVAN+AE22*P2_IVAN+AF22*IF($A22<P3_DESDE,P3A_IVAN,P3_IVAN)-AG22*IVA_DEV -> 0 | AM22: =N22*(1+RECARGO_ADS) -> 79.53 | AN22: =IF(ISNUMBER(L22),E22+F22+G22+AA22+AB22+AC22,0) -> 5 | AO22: =P22*COMISION -> 4.75 | AP22: =MIN(N(K22),Q22) -> 1 | AQ22: =IF(Q22>0,((Q22-AP22)*AT22+AP22*TASA_INC)/Q22,AT22) -> 0.67216749 | AR22: =IF($A22<FECHA_EXPORT,NETWORKDAYS($A22+1,FECHA_EXPORT,FESTIVOS),0) -> 2 | AS22: =IF(AR22>=5,1,INDEX(CDF_INC,1,AR22+1)) -> 0.7 | AT22: =TASA_USADA+(TASA_INC-TASA_USADA)*Q_INC*(1-AS22)/(1-Q_INC*AS22) -> 0.80622332
A23: 46317 | B23: 2 | C23: 3 | D23: 1 | F23: 2 | K23: 2 | L23: 13.5 | M23: 27 | N23: 83.29 | P23: =B23+C23+D23 -> 6 | Q23: =AA23+AB23+AC23 -> 4 | R23: =B23*P1_PVP+C23*P2_PVP+D23*IF($A23<P3_DESDE,P3A_PVP,P3_PVP) -> 239.94 | S23: =IF(P23>0,R23/P23,"") -> 39.99 | T23: =IF(P23>0,N23/P23,"") -> 13.881667 | U23: =IF(N23>0,R23/N23,"") -> 2.880778 | V23: =IF(E23+F23+G23+H23+I23+J23>0,(E23+F23+G23)/(E23+F23+G23+H23+I23+J23),"") -> 1 | W23: =E23*(P1_PVP-P1_CPROD)+F23*(P2_PVP-P2_CPROD)+G23*(IF($A23<P3_DESDE,P3A_PVP,P3_PVP)-IF($A23<P3_DESDE,P3A_CPROD,P3_CPROD))-IF(ISNUMBER(L23),L23,E23*P1_LOG+F23*P2_LOG+G23*P3_LOG) -> 56.8484 | X23: =W23-(E23*P1_IVAN+F23*P2_IVAN+G23*IF($A23<P3_DESDE,P3A_IVAN,P3_IVAN))-(H23+I23+J23)*(COSTE_DEV-IVA_DEV)-AM23-AO23 -> -32.1416 | Y23: =AH23-AI23-AJ23-AK23-AL23-AM23-AO23 -> 5.6528793 | AA23: =MAX(0,B23-E23-H23) -> 2 | AB23: =MAX(0,C23-F23-I23) -> 1 | AC23: =MAX(0,D23-G23-J23) -> 1 | AD23: =E23+AA23*AQ23 -> 0.96285813 | AE23: =F23+AB23*AQ23 -> 2.4814291 | AF23: =G23+AC23*AQ23 -> 0.48142906 | AG23: =H23+I23+J23+(AA23+AB23+AC23)*(1-AQ23) -> 2.0742837 | AH23: =AD23*P1_PVP+AE23*P2_PVP+AF23*IF($A23<P3_DESDE,P3A_PVP,P3_PVP) -> 156.98939 | AI23: =AD23*P1_CPROD+AE23*P2_CPROD+AF23*IF($A23<P3_DESDE,P3A_CPROD,P3_CPROD) -> 20.187087 | AJ23: =IF(ISNUMBER(L23),L23,E23*P1_LOG+F23*P2_LOG+G23*P3_LOG)+IF(ISNUMBER(M23),M23,AA23*P1_LOG+AB23*P2_LOG+AC23*P3_LOG)*AQ23 -> 26.498585 | AK23: =AG23*COSTE_DEV -> 15.660842 | AL23: =AD23*P1_IVAN+AE23*P2_IVAN+AF23*IF($A23<P3_DESDE,P3A_IVAN,P3_IVAN)-AG23*IVA_DEV -> 0 | AM23: =N23*(1+RECARGO_ADS) -> 83.29 | AN23: =IF(ISNUMBER(L23),E23+F23+G23+AA23+AB23+AC23,0) -> 6 | AO23: =P23*COMISION -> 5.7 | AP23: =MIN(N(K23),Q23) -> 2 | AQ23: =IF(Q23>0,((Q23-AP23)*AT23+AP23*TASA_INC)/Q23,AT23) -> 0.48142906 | AR23: =IF($A23<FECHA_EXPORT,NETWORKDAYS($A23+1,FECHA_EXPORT,FESTIVOS),0) -> 1 | AS23: =IF(AR23>=5,1,INDEX(CDF_INC,1,AR23+1)) -> 0.3 | AT23: =TASA_USADA+(TASA_INC-TASA_USADA)*Q_INC*(1-AS23)/(1-Q_INC*AS23) -> 0.69285813
A24: 46318 | B24: 3 | C24: 1 | D24: 0 | L24: 0 | M24: 27 | N24: 29.29 | P24: =B24+C24+D24 -> 4 | Q24: =AA24+AB24+AC24 -> 4 | R24: =B24*P1_PVP+C24*P2_PVP+D24*IF($A24<P3_DESDE,P3A_PVP,P3_PVP) -> 129.96 | S24: =IF(P24>0,R24/P24,"") -> 32.49 | T24: =IF(P24>0,N24/P24,"") -> 7.3225 | U24: =IF(N24>0,R24/N24,"") -> 4.4370092 | V24: =IF(E24+F24+G24+H24+I24+J24>0,(E24+F24+G24)/(E24+F24+G24+H24+I24+J24),"") | W24: =E24*(P1_PVP-P1_CPROD)+F24*(P2_PVP-P2_CPROD)+G24*(IF($A24<P3_DESDE,P3A_PVP,P3_PVP)-IF($A24<P3_DESDE,P3A_CPROD,P3_CPROD))-IF(ISNUMBER(L24),L24,E24*P1_LOG+F24*P2_LOG+G24*P3_LOG) -> 0 | X24: =W24-(E24*P1_IVAN+F24*P2_IVAN+G24*IF($A24<P3_DESDE,P3A_IVAN,P3_IVAN))-(H24+I24+J24)*(COSTE_DEV-IVA_DEV)-AM24-AO24 -> -33.09 | Y24: =AH24-AI24-AJ24-AK24-AL24-AM24-AO24 -> 16.635852 | AA24: =MAX(0,B24-E24-H24) -> 3 | AB24: =MAX(0,C24-F24-I24) -> 1 | AC24: =MAX(0,D24-G24-J24) -> 0 | AD24: =E24+AA24*AQ24 -> 1.9796612 | AE24: =F24+AB24*AQ24 -> 0.65988707 | AF24: =G24+AC24*AQ24 -> 0 | AG24: =H24+I24+J24+(AA24+AB24+AC24)*(1-AQ24) -> 1.3604517 | AH24: =AD24*P1_PVP+AE24*P2_PVP+AF24*IF($A24<P3_DESDE,P3A_PVP,P3_PVP) -> 85.758924 | AI24: =AD24*P1_CPROD+AE24*P2_CPROD+AF24*IF($A24<P3_DESDE,P3A_CPROD,P3_CPROD) -> 7.9447104 | AJ24: =IF(ISNUMBER(L24),L24,E24*P1_LOG+F24*P2_LOG+G24*P3_LOG)+IF(ISNUMBER(M24),M24,AA24*P1_LOG+AB24*P2_LOG+AC24*P3_LOG)*AQ24 -> 17.816951 | AK24: =AG24*COSTE_DEV -> 10.27141 | AL24: =AD24*P1_IVAN+AE24*P2_IVAN+AF24*IF($A24<P3_DESDE,P3A_IVAN,P3_IVAN)-AG24*IVA_DEV -> 0 | AM24: =N24*(1+RECARGO_ADS) -> 29.29 | AN24: =IF(ISNUMBER(L24),E24+F24+G24+AA24+AB24+AC24,0) -> 4 | AO24: =P24*COMISION -> 3.8 | AP24: =MIN(N(K24),Q24) -> 0 | AQ24: =IF(Q24>0,((Q24-AP24)*AT24+AP24*TASA_INC)/Q24,AT24) -> 0.65988707 | AR24: =IF($A24<FECHA_EXPORT,NETWORKDAYS($A24+1,FECHA_EXPORT,FESTIVOS),0) -> 0 | AS24: =IF(AR24>=5,1,INDEX(CDF_INC,1,AR24+1)) -> 0.14 | AT24: =TASA_USADA+(TASA_INC-TASA_USADA)*Q_INC*(1-AS24)/(1-Q_INC*AS24) -> 0.65988707
A25: 46319 | P25: =B25+C25+D25 -> 0 | Q25: =AA25+AB25+AC25 -> 0 | R25: =B25*P1_PVP+C25*P2_PVP+D25*IF($A25<P3_DESDE,P3A_PVP,P3_PVP) -> 0 | S25: =IF(P25>0,R25/P25,"") | T25: =IF(P25>0,N25/P25,"") | U25: =IF(N25>0,R25/N25,"") | V25: =IF(E25+F25+G25+H25+I25+J25>0,(E25+F25+G25)/(E25+F25+G25+H25+I25+J25),"") | W25: =E25*(P1_PVP-P1_CPROD)+F25*(P2_PVP-P2_CPROD)+G25*(IF($A25<P3_DESDE,P3A_PVP,P3_PVP)-IF($A25<P3_DESDE,P3A_CPROD,P3_CPROD))-IF(ISNUMBER(L25),L25,E25*P1_LOG+F25*P2_LOG+G25*P3_LOG) -> 0 | X25: =W25-(E25*P1_IVAN+F25*P2_IVAN+G25*IF($A25<P3_DESDE,P3A_IVAN,P3_IVAN))-(H25+I25+J25)*(COSTE_DEV-IVA_DEV)-AM25-AO25 -> 0 | Y25: =AH25-AI25-AJ25-AK25-AL25-AM25-AO25 -> 0 | AA25: =MAX(0,B25-E25-H25) -> 0 | AB25: =MAX(0,C25-F25-I25) -> 0 | AC25: =MAX(0,D25-G25-J25) -> 0 | AD25: =E25+AA25*AQ25 -> 0 | AE25: =F25+AB25*AQ25 -> 0 | AF25: =G25+AC25*AQ25 -> 0 | AG25: =H25+I25+J25+(AA25+AB25+AC25)*(1-AQ25) -> 0 | AH25: =AD25*P1_PVP+AE25*P2_PVP+AF25*IF($A25<P3_DESDE,P3A_PVP,P3_PVP) -> 0 | AI25: =AD25*P1_CPROD+AE25*P2_CPROD+AF25*IF($A25<P3_DESDE,P3A_CPROD,P3_CPROD) -> 0 | AJ25: =IF(ISNUMBER(L25),L25,E25*P1_LOG+F25*P2_LOG+G25*P3_LOG)+IF(ISNUMBER(M25),M25,AA25*P1_LOG+AB25*P2_LOG+AC25*P3_LOG)*AQ25 -> 0 | AK25: =AG25*COSTE_DEV -> 0 | AL25: =AD25*P1_IVAN+AE25*P2_IVAN+AF25*IF($A25<P3_DESDE,P3A_IVAN,P3_IVAN)-AG25*IVA_DEV -> 0 | AM25: =N25*(1+RECARGO_ADS) -> 0 | AN25: =IF(ISNUMBER(L25),E25+F25+G25+AA25+AB25+AC25,0) -> 0 | AO25: =P25*COMISION -> 0 | AP25: =MIN(N(K25),Q25) -> 0 | AQ25: =IF(Q25>0,((Q25-AP25)*AT25+AP25*TASA_INC)/Q25,AT25) -> 0.65988707 | AR25: =IF($A25<FECHA_EXPORT,NETWORKDAYS($A25+1,FECHA_EXPORT,FESTIVOS),0) -> 0 | AS25: =IF(AR25>=5,1,INDEX(CDF_INC,1,AR25+1)) -> 0.14 | AT25: =TASA_USADA+(TASA_INC-TASA_USADA)*Q_INC*(1-AS25)/(1-Q_INC*AS25) -> 0.65988707
A26: 46320 | P26: =B26+C26+D26 -> 0 | Q26: =AA26+AB26+AC26 -> 0 | R26: =B26*P1_PVP+C26*P2_PVP+D26*IF($A26<P3_DESDE,P3A_PVP,P3_PVP) -> 0 | S26: =IF(P26>0,R26/P26,"") | T26: =IF(P26>0,N26/P26,"") | U26: =IF(N26>0,R26/N26,"") | V26: =IF(E26+F26+G26+H26+I26+J26>0,(E26+F26+G26)/(E26+F26+G26+H26+I26+J26),"") | W26: =E26*(P1_PVP-P1_CPROD)+F26*(P2_PVP-P2_CPROD)+G26*(IF($A26<P3_DESDE,P3A_PVP,P3_PVP)-IF($A26<P3_DESDE,P3A_CPROD,P3_CPROD))-IF(ISNUMBER(L26),L26,E26*P1_LOG+F26*P2_LOG+G26*P3_LOG) -> 0 | X26: =W26-(E26*P1_IVAN+F26*P2_IVAN+G26*IF($A26<P3_DESDE,P3A_IVAN,P3_IVAN))-(H26+I26+J26)*(COSTE_DEV-IVA_DEV)-AM26-AO26 -> 0 | Y26: =AH26-AI26-AJ26-AK26-AL26-AM26-AO26 -> 0 | AA26: =MAX(0,B26-E26-H26) -> 0 | AB26: =MAX(0,C26-F26-I26) -> 0 | AC26: =MAX(0,D26-G26-J26) -> 0 | AD26: =E26+AA26*AQ26 -> 0 | AE26: =F26+AB26*AQ26 -> 0 | AF26: =G26+AC26*AQ26 -> 0 | AG26: =H26+I26+J26+(AA26+AB26+AC26)*(1-AQ26) -> 0 | AH26: =AD26*P1_PVP+AE26*P2_PVP+AF26*IF($A26<P3_DESDE,P3A_PVP,P3_PVP) -> 0 | AI26: =AD26*P1_CPROD+AE26*P2_CPROD+AF26*IF($A26<P3_DESDE,P3A_CPROD,P3_CPROD) -> 0 | AJ26: =IF(ISNUMBER(L26),L26,E26*P1_LOG+F26*P2_LOG+G26*P3_LOG)+IF(ISNUMBER(M26),M26,AA26*P1_LOG+AB26*P2_LOG+AC26*P3_LOG)*AQ26 -> 0 | AK26: =AG26*COSTE_DEV -> 0 | AL26: =AD26*P1_IVAN+AE26*P2_IVAN+AF26*IF($A26<P3_DESDE,P3A_IVAN,P3_IVAN)-AG26*IVA_DEV -> 0 | AM26: =N26*(1+RECARGO_ADS) -> 0 | AN26: =IF(ISNUMBER(L26),E26+F26+G26+AA26+AB26+AC26,0) -> 0 | AO26: =P26*COMISION -> 0 | AP26: =MIN(N(K26),Q26) -> 0 | AQ26: =IF(Q26>0,((Q26-AP26)*AT26+AP26*TASA_INC)/Q26,AT26) -> 0.65988707 | AR26: =IF($A26<FECHA_EXPORT,NETWORKDAYS($A26+1,FECHA_EXPORT,FESTIVOS),0) -> 0 | AS26: =IF(AR26>=5,1,INDEX(CDF_INC,1,AR26+1)) -> 0.14 | AT26: =TASA_USADA+(TASA_INC-TASA_USADA)*Q_INC*(1-AS26)/(1-Q_INC*AS26) -> 0.65988707
A27: 46321 | P27: =B27+C27+D27 -> 0 | Q27: =AA27+AB27+AC27 -> 0 | R27: =B27*P1_PVP+C27*P2_PVP+D27*IF($A27<P3_DESDE,P3A_PVP,P3_PVP) -> 0 | S27: =IF(P27>0,R27/P27,"") | T27: =IF(P27>0,N27/P27,"") | U27: =IF(N27>0,R27/N27,"") | V27: =IF(E27+F27+G27+H27+I27+J27>0,(E27+F27+G27)/(E27+F27+G27+H27+I27+J27),"") | W27: =E27*(P1_PVP-P1_CPROD)+F27*(P2_PVP-P2_CPROD)+G27*(IF($A27<P3_DESDE,P3A_PVP,P3_PVP)-IF($A27<P3_DESDE,P3A_CPROD,P3_CPROD))-IF(ISNUMBER(L27),L27,E27*P1_LOG+F27*P2_LOG+G27*P3_LOG) -> 0 | X27: =W27-(E27*P1_IVAN+F27*P2_IVAN+G27*IF($A27<P3_DESDE,P3A_IVAN,P3_IVAN))-(H27+I27+J27)*(COSTE_DEV-IVA_DEV)-AM27-AO27 -> 0 | Y27: =AH27-AI27-AJ27-AK27-AL27-AM27-AO27 -> 0 | AA27: =MAX(0,B27-E27-H27) -> 0 | AB27: =MAX(0,C27-F27-I27) -> 0 | AC27: =MAX(0,D27-G27-J27) -> 0 | AD27: =E27+AA27*AQ27 -> 0 | AE27: =F27+AB27*AQ27 -> 0 | AF27: =G27+AC27*AQ27 -> 0 | AG27: =H27+I27+J27+(AA27+AB27+AC27)*(1-AQ27) -> 0 | AH27: =AD27*P1_PVP+AE27*P2_PVP+AF27*IF($A27<P3_DESDE,P3A_PVP,P3_PVP) -> 0 | AI27: =AD27*P1_CPROD+AE27*P2_CPROD+AF27*IF($A27<P3_DESDE,P3A_CPROD,P3_CPROD) -> 0 | AJ27: =IF(ISNUMBER(L27),L27,E27*P1_LOG+F27*P2_LOG+G27*P3_LOG)+IF(ISNUMBER(M27),M27,AA27*P1_LOG+AB27*P2_LOG+AC27*P3_LOG)*AQ27 -> 0 | AK27: =AG27*COSTE_DEV -> 0 | AL27: =AD27*P1_IVAN+AE27*P2_IVAN+AF27*IF($A27<P3_DESDE,P3A_IVAN,P3_IVAN)-AG27*IVA_DEV -> 0 | AM27: =N27*(1+RECARGO_ADS) -> 0 | AN27: =IF(ISNUMBER(L27),E27+F27+G27+AA27+AB27+AC27,0) -> 0 | AO27: =P27*COMISION -> 0 | AP27: =MIN(N(K27),Q27) -> 0 | AQ27: =IF(Q27>0,((Q27-AP27)*AT27+AP27*TASA_INC)/Q27,AT27) -> 0.65988707 | AR27: =IF($A27<FECHA_EXPORT,NETWORKDAYS($A27+1,FECHA_EXPORT,FESTIVOS),0) -> 0 | AS27: =IF(AR27>=5,1,INDEX(CDF_INC,1,AR27+1)) -> 0.14 | AT27: =TASA_USADA+(TASA_INC-TASA_USADA)*Q_INC*(1-AS27)/(1-Q_INC*AS27) -> 0.65988707
A28: 46322 | P28: =B28+C28+D28 -> 0 | Q28: =AA28+AB28+AC28 -> 0 | R28: =B28*P1_PVP+C28*P2_PVP+D28*IF($A28<P3_DESDE,P3A_PVP,P3_PVP) -> 0 | S28: =IF(P28>0,R28/P28,"") | T28: =IF(P28>0,N28/P28,"") | U28: =IF(N28>0,R28/N28,"") | V28: =IF(E28+F28+G28+H28+I28+J28>0,(E28+F28+G28)/(E28+F28+G28+H28+I28+J28),"") | W28: =E28*(P1_PVP-P1_CPROD)+F28*(P2_PVP-P2_CPROD)+G28*(IF($A28<P3_DESDE,P3A_PVP,P3_PVP)-IF($A28<P3_DESDE,P3A_CPROD,P3_CPROD))-IF(ISNUMBER(L28),L28,E28*P1_LOG+F28*P2_LOG+G28*P3_LOG) -> 0 | X28: =W28-(E28*P1_IVAN+F28*P2_IVAN+G28*IF($A28<P3_DESDE,P3A_IVAN,P3_IVAN))-(H28+I28+J28)*(COSTE_DEV-IVA_DEV)-AM28-AO28 -> 0 | Y28: =AH28-AI28-AJ28-AK28-AL28-AM28-AO28 -> 0 | AA28: =MAX(0,B28-E28-H28) -> 0 | AB28: =MAX(0,C28-F28-I28) -> 0 | AC28: =MAX(0,D28-G28-J28) -> 0 | AD28: =E28+AA28*AQ28 -> 0 | AE28: =F28+AB28*AQ28 -> 0 | AF28: =G28+AC28*AQ28 -> 0 | AG28: =H28+I28+J28+(AA28+AB28+AC28)*(1-AQ28) -> 0 | AH28: =AD28*P1_PVP+AE28*P2_PVP+AF28*IF($A28<P3_DESDE,P3A_PVP,P3_PVP) -> 0 | AI28: =AD28*P1_CPROD+AE28*P2_CPROD+AF28*IF($A28<P3_DESDE,P3A_CPROD,P3_CPROD) -> 0 | AJ28: =IF(ISNUMBER(L28),L28,E28*P1_LOG+F28*P2_LOG+G28*P3_LOG)+IF(ISNUMBER(M28),M28,AA28*P1_LOG+AB28*P2_LOG+AC28*P3_LOG)*AQ28 -> 0 | AK28: =AG28*COSTE_DEV -> 0 | AL28: =AD28*P1_IVAN+AE28*P2_IVAN+AF28*IF($A28<P3_DESDE,P3A_IVAN,P3_IVAN)-AG28*IVA_DEV -> 0 | AM28: =N28*(1+RECARGO_ADS) -> 0 | AN28: =IF(ISNUMBER(L28),E28+F28+G28+AA28+AB28+AC28,0) -> 0 | AO28: =P28*COMISION -> 0 | AP28: =MIN(N(K28),Q28) -> 0 | AQ28: =IF(Q28>0,((Q28-AP28)*AT28+AP28*TASA_INC)/Q28,AT28) -> 0.65988707 | AR28: =IF($A28<FECHA_EXPORT,NETWORKDAYS($A28+1,FECHA_EXPORT,FESTIVOS),0) -> 0 | AS28: =IF(AR28>=5,1,INDEX(CDF_INC,1,AR28+1)) -> 0.14 | AT28: =TASA_USADA+(TASA_INC-TASA_USADA)*Q_INC*(1-AS28)/(1-Q_INC*AS28) -> 0.65988707
A29: 46323 | P29: =B29+C29+D29 -> 0 | Q29: =AA29+AB29+AC29 -> 0 | R29: =B29*P1_PVP+C29*P2_PVP+D29*IF($A29<P3_DESDE,P3A_PVP,P3_PVP) -> 0 | S29: =IF(P29>0,R29/P29,"") | T29: =IF(P29>0,N29/P29,"") | U29: =IF(N29>0,R29/N29,"") | V29: =IF(E29+F29+G29+H29+I29+J29>0,(E29+F29+G29)/(E29+F29+G29+H29+I29+J29),"") | W29: =E29*(P1_PVP-P1_CPROD)+F29*(P2_PVP-P2_CPROD)+G29*(IF($A29<P3_DESDE,P3A_PVP,P3_PVP)-IF($A29<P3_DESDE,P3A_CPROD,P3_CPROD))-IF(ISNUMBER(L29),L29,E29*P1_LOG+F29*P2_LOG+G29*P3_LOG) -> 0 | X29: =W29-(E29*P1_IVAN+F29*P2_IVAN+G29*IF($A29<P3_DESDE,P3A_IVAN,P3_IVAN))-(H29+I29+J29)*(COSTE_DEV-IVA_DEV)-AM29-AO29 -> 0 | Y29: =AH29-AI29-AJ29-AK29-AL29-AM29-AO29 -> 0 | AA29: =MAX(0,B29-E29-H29) -> 0 | AB29: =MAX(0,C29-F29-I29) -> 0 | AC29: =MAX(0,D29-G29-J29) -> 0 | AD29: =E29+AA29*AQ29 -> 0 | AE29: =F29+AB29*AQ29 -> 0 | AF29: =G29+AC29*AQ29 -> 0 | AG29: =H29+I29+J29+(AA29+AB29+AC29)*(1-AQ29) -> 0 | AH29: =AD29*P1_PVP+AE29*P2_PVP+AF29*IF($A29<P3_DESDE,P3A_PVP,P3_PVP) -> 0 | AI29: =AD29*P1_CPROD+AE29*P2_CPROD+AF29*IF($A29<P3_DESDE,P3A_CPROD,P3_CPROD) -> 0 | AJ29: =IF(ISNUMBER(L29),L29,E29*P1_LOG+F29*P2_LOG+G29*P3_LOG)+IF(ISNUMBER(M29),M29,AA29*P1_LOG+AB29*P2_LOG+AC29*P3_LOG)*AQ29 -> 0 | AK29: =AG29*COSTE_DEV -> 0 | AL29: =AD29*P1_IVAN+AE29*P2_IVAN+AF29*IF($A29<P3_DESDE,P3A_IVAN,P3_IVAN)-AG29*IVA_DEV -> 0 | AM29: =N29*(1+RECARGO_ADS) -> 0 | AN29: =IF(ISNUMBER(L29),E29+F29+G29+AA29+AB29+AC29,0) -> 0 | AO29: =P29*COMISION -> 0 | AP29: =MIN(N(K29),Q29) -> 0 | AQ29: =IF(Q29>0,((Q29-AP29)*AT29+AP29*TASA_INC)/Q29,AT29) -> 0.65988707 | AR29: =IF($A29<FECHA_EXPORT,NETWORKDAYS($A29+1,FECHA_EXPORT,FESTIVOS),0) -> 0 | AS29: =IF(AR29>=5,1,INDEX(CDF_INC,1,AR29+1)) -> 0.14 | AT29: =TASA_USADA+(TASA_INC-TASA_USADA)*Q_INC*(1-AS29)/(1-Q_INC*AS29) -> 0.65988707
A30: 46324 | P30: =B30+C30+D30 -> 0 | Q30: =AA30+AB30+AC30 -> 0 | R30: =B30*P1_PVP+C30*P2_PVP+D30*IF($A30<P3_DESDE,P3A_PVP,P3_PVP) -> 0 | S30: =IF(P30>0,R30/P30,"") | T30: =IF(P30>0,N30/P30,"") | U30: =IF(N30>0,R30/N30,"") | V30: =IF(E30+F30+G30+H30+I30+J30>0,(E30+F30+G30)/(E30+F30+G30+H30+I30+J30),"") | W30: =E30*(P1_PVP-P1_CPROD)+F30*(P2_PVP-P2_CPROD)+G30*(IF($A30<P3_DESDE,P3A_PVP,P3_PVP)-IF($A30<P3_DESDE,P3A_CPROD,P3_CPROD))-IF(ISNUMBER(L30),L30,E30*P1_LOG+F30*P2_LOG+G30*P3_LOG) -> 0 | X30: =W30-(E30*P1_IVAN+F30*P2_IVAN+G30*IF($A30<P3_DESDE,P3A_IVAN,P3_IVAN))-(H30+I30+J30)*(COSTE_DEV-IVA_DEV)-AM30-AO30 -> 0 | Y30: =AH30-AI30-AJ30-AK30-AL30-AM30-AO30 -> 0 | AA30: =MAX(0,B30-E30-H30) -> 0 | AB30: =MAX(0,C30-F30-I30) -> 0 | AC30: =MAX(0,D30-G30-J30) -> 0 | AD30: =E30+AA30*AQ30 -> 0 | AE30: =F30+AB30*AQ30 -> 0 | AF30: =G30+AC30*AQ30 -> 0 | AG30: =H30+I30+J30+(AA30+AB30+AC30)*(1-AQ30) -> 0 | AH30: =AD30*P1_PVP+AE30*P2_PVP+AF30*IF($A30<P3_DESDE,P3A_PVP,P3_PVP) -> 0 | AI30: =AD30*P1_CPROD+AE30*P2_CPROD+AF30*IF($A30<P3_DESDE,P3A_CPROD,P3_CPROD) -> 0 | AJ30: =IF(ISNUMBER(L30),L30,E30*P1_LOG+F30*P2_LOG+G30*P3_LOG)+IF(ISNUMBER(M30),M30,AA30*P1_LOG+AB30*P2_LOG+AC30*P3_LOG)*AQ30 -> 0 | AK30: =AG30*COSTE_DEV -> 0 | AL30: =AD30*P1_IVAN+AE30*P2_IVAN+AF30*IF($A30<P3_DESDE,P3A_IVAN,P3_IVAN)-AG30*IVA_DEV -> 0 | AM30: =N30*(1+RECARGO_ADS) -> 0 | AN30: =IF(ISNUMBER(L30),E30+F30+G30+AA30+AB30+AC30,0) -> 0 | AO30: =P30*COMISION -> 0 | AP30: =MIN(N(K30),Q30) -> 0 | AQ30: =IF(Q30>0,((Q30-AP30)*AT30+AP30*TASA_INC)/Q30,AT30) -> 0.65988707 | AR30: =IF($A30<FECHA_EXPORT,NETWORKDAYS($A30+1,FECHA_EXPORT,FESTIVOS),0) -> 0 | AS30: =IF(AR30>=5,1,INDEX(CDF_INC,1,AR30+1)) -> 0.14 | AT30: =TASA_USADA+(TASA_INC-TASA_USADA)*Q_INC*(1-AS30)/(1-Q_INC*AS30) -> 0.65988707
A31: 46325 | P31: =B31+C31+D31 -> 0 | Q31: =AA31+AB31+AC31 -> 0 | R31: =B31*P1_PVP+C31*P2_PVP+D31*IF($A31<P3_DESDE,P3A_PVP,P3_PVP) -> 0 | S31: =IF(P31>0,R31/P31,"") | T31: =IF(P31>0,N31/P31,"") | U31: =IF(N31>0,R31/N31,"") | V31: =IF(E31+F31+G31+H31+I31+J31>0,(E31+F31+G31)/(E31+F31+G31+H31+I31+J31),"") | W31: =E31*(P1_PVP-P1_CPROD)+F31*(P2_PVP-P2_CPROD)+G31*(IF($A31<P3_DESDE,P3A_PVP,P3_PVP)-IF($A31<P3_DESDE,P3A_CPROD,P3_CPROD))-IF(ISNUMBER(L31),L31,E31*P1_LOG+F31*P2_LOG+G31*P3_LOG) -> 0 | X31: =W31-(E31*P1_IVAN+F31*P2_IVAN+G31*IF($A31<P3_DESDE,P3A_IVAN,P3_IVAN))-(H31+I31+J31)*(COSTE_DEV-IVA_DEV)-AM31-AO31 -> 0 | Y31: =AH31-AI31-AJ31-AK31-AL31-AM31-AO31 -> 0 | AA31: =MAX(0,B31-E31-H31) -> 0 | AB31: =MAX(0,C31-F31-I31) -> 0 | AC31: =MAX(0,D31-G31-J31) -> 0 | AD31: =E31+AA31*AQ31 -> 0 | AE31: =F31+AB31*AQ31 -> 0 | AF31: =G31+AC31*AQ31 -> 0 | AG31: =H31+I31+J31+(AA31+AB31+AC31)*(1-AQ31) -> 0 | AH31: =AD31*P1_PVP+AE31*P2_PVP+AF31*IF($A31<P3_DESDE,P3A_PVP,P3_PVP) -> 0 | AI31: =AD31*P1_CPROD+AE31*P2_CPROD+AF31*IF($A31<P3_DESDE,P3A_CPROD,P3_CPROD) -> 0 | AJ31: =IF(ISNUMBER(L31),L31,E31*P1_LOG+F31*P2_LOG+G31*P3_LOG)+IF(ISNUMBER(M31),M31,AA31*P1_LOG+AB31*P2_LOG+AC31*P3_LOG)*AQ31 -> 0 | AK31: =AG31*COSTE_DEV -> 0 | AL31: =AD31*P1_IVAN+AE31*P2_IVAN+AF31*IF($A31<P3_DESDE,P3A_IVAN,P3_IVAN)-AG31*IVA_DEV -> 0 | AM31: =N31*(1+RECARGO_ADS) -> 0 | AN31: =IF(ISNUMBER(L31),E31+F31+G31+AA31+AB31+AC31,0) -> 0 | AO31: =P31*COMISION -> 0 | AP31: =MIN(N(K31),Q31) -> 0 | AQ31: =IF(Q31>0,((Q31-AP31)*AT31+AP31*TASA_INC)/Q31,AT31) -> 0.65988707 | AR31: =IF($A31<FECHA_EXPORT,NETWORKDAYS($A31+1,FECHA_EXPORT,FESTIVOS),0) -> 0 | AS31: =IF(AR31>=5,1,INDEX(CDF_INC,1,AR31+1)) -> 0.14 | AT31: =TASA_USADA+(TASA_INC-TASA_USADA)*Q_INC*(1-AS31)/(1-Q_INC*AS31) -> 0.65988707
A32: 46326 | P32: =B32+C32+D32 -> 0 | Q32: =AA32+AB32+AC32 -> 0 | R32: =B32*P1_PVP+C32*P2_PVP+D32*IF($A32<P3_DESDE,P3A_PVP,P3_PVP) -> 0 | S32: =IF(P32>0,R32/P32,"") | T32: =IF(P32>0,N32/P32,"") | U32: =IF(N32>0,R32/N32,"") | V32: =IF(E32+F32+G32+H32+I32+J32>0,(E32+F32+G32)/(E32+F32+G32+H32+I32+J32),"") | W32: =E32*(P1_PVP-P1_CPROD)+F32*(P2_PVP-P2_CPROD)+G32*(IF($A32<P3_DESDE,P3A_PVP,P3_PVP)-IF($A32<P3_DESDE,P3A_CPROD,P3_CPROD))-IF(ISNUMBER(L32),L32,E32*P1_LOG+F32*P2_LOG+G32*P3_LOG) -> 0 | X32: =W32-(E32*P1_IVAN+F32*P2_IVAN+G32*IF($A32<P3_DESDE,P3A_IVAN,P3_IVAN))-(H32+I32+J32)*(COSTE_DEV-IVA_DEV)-AM32-AO32 -> 0 | Y32: =AH32-AI32-AJ32-AK32-AL32-AM32-AO32 -> 0 | AA32: =MAX(0,B32-E32-H32) -> 0 | AB32: =MAX(0,C32-F32-I32) -> 0 | AC32: =MAX(0,D32-G32-J32) -> 0 | AD32: =E32+AA32*AQ32 -> 0 | AE32: =F32+AB32*AQ32 -> 0 | AF32: =G32+AC32*AQ32 -> 0 | AG32: =H32+I32+J32+(AA32+AB32+AC32)*(1-AQ32) -> 0 | AH32: =AD32*P1_PVP+AE32*P2_PVP+AF32*IF($A32<P3_DESDE,P3A_PVP,P3_PVP) -> 0 | AI32: =AD32*P1_CPROD+AE32*P2_CPROD+AF32*IF($A32<P3_DESDE,P3A_CPROD,P3_CPROD) -> 0 | AJ32: =IF(ISNUMBER(L32),L32,E32*P1_LOG+F32*P2_LOG+G32*P3_LOG)+IF(ISNUMBER(M32),M32,AA32*P1_LOG+AB32*P2_LOG+AC32*P3_LOG)*AQ32 -> 0 | AK32: =AG32*COSTE_DEV -> 0 | AL32: =AD32*P1_IVAN+AE32*P2_IVAN+AF32*IF($A32<P3_DESDE,P3A_IVAN,P3_IVAN)-AG32*IVA_DEV -> 0 | AM32: =N32*(1+RECARGO_ADS) -> 0 | AN32: =IF(ISNUMBER(L32),E32+F32+G32+AA32+AB32+AC32,0) -> 0 | AO32: =P32*COMISION -> 0 | AP32: =MIN(N(K32),Q32) -> 0 | AQ32: =IF(Q32>0,((Q32-AP32)*AT32+AP32*TASA_INC)/Q32,AT32) -> 0.65988707 | AR32: =IF($A32<FECHA_EXPORT,NETWORKDAYS($A32+1,FECHA_EXPORT,FESTIVOS),0) -> 0 | AS32: =IF(AR32>=5,1,INDEX(CDF_INC,1,AR32+1)) -> 0.14 | AT32: =TASA_USADA+(TASA_INC-TASA_USADA)*Q_INC*(1-AS32)/(1-Q_INC*AS32) -> 0.65988707
A33: 46327 | P33: =B33+C33+D33 -> 0 | Q33: =AA33+AB33+AC33 -> 0 | R33: =B33*P1_PVP+C33*P2_PVP+D33*IF($A33<P3_DESDE,P3A_PVP,P3_PVP) -> 0 | S33: =IF(P33>0,R33/P33,"") | T33: =IF(P33>0,N33/P33,"") | U33: =IF(N33>0,R33/N33,"") | V33: =IF(E33+F33+G33+H33+I33+J33>0,(E33+F33+G33)/(E33+F33+G33+H33+I33+J33),"") | W33: =E33*(P1_PVP-P1_CPROD)+F33*(P2_PVP-P2_CPROD)+G33*(IF($A33<P3_DESDE,P3A_PVP,P3_PVP)-IF($A33<P3_DESDE,P3A_CPROD,P3_CPROD))-IF(ISNUMBER(L33),L33,E33*P1_LOG+F33*P2_LOG+G33*P3_LOG) -> 0 | X33: =W33-(E33*P1_IVAN+F33*P2_IVAN+G33*IF($A33<P3_DESDE,P3A_IVAN,P3_IVAN))-(H33+I33+J33)*(COSTE_DEV-IVA_DEV)-AM33-AO33 -> 0 | Y33: =AH33-AI33-AJ33-AK33-AL33-AM33-AO33 -> 0 | AA33: =MAX(0,B33-E33-H33) -> 0 | AB33: =MAX(0,C33-F33-I33) -> 0 | AC33: =MAX(0,D33-G33-J33) -> 0 | AD33: =E33+AA33*AQ33 -> 0 | AE33: =F33+AB33*AQ33 -> 0 | AF33: =G33+AC33*AQ33 -> 0 | AG33: =H33+I33+J33+(AA33+AB33+AC33)*(1-AQ33) -> 0 | AH33: =AD33*P1_PVP+AE33*P2_PVP+AF33*IF($A33<P3_DESDE,P3A_PVP,P3_PVP) -> 0 | AI33: =AD33*P1_CPROD+AE33*P2_CPROD+AF33*IF($A33<P3_DESDE,P3A_CPROD,P3_CPROD) -> 0 | AJ33: =IF(ISNUMBER(L33),L33,E33*P1_LOG+F33*P2_LOG+G33*P3_LOG)+IF(ISNUMBER(M33),M33,AA33*P1_LOG+AB33*P2_LOG+AC33*P3_LOG)*AQ33 -> 0 | AK33: =AG33*COSTE_DEV -> 0 | AL33: =AD33*P1_IVAN+AE33*P2_IVAN+AF33*IF($A33<P3_DESDE,P3A_IVAN,P3_IVAN)-AG33*IVA_DEV -> 0 | AM33: =N33*(1+RECARGO_ADS) -> 0 | AN33: =IF(ISNUMBER(L33),E33+F33+G33+AA33+AB33+AC33,0) -> 0 | AO33: =P33*COMISION -> 0 | AP33: =MIN(N(K33),Q33) -> 0 | AQ33: =IF(Q33>0,((Q33-AP33)*AT33+AP33*TASA_INC)/Q33,AT33) -> 0.65988707 | AR33: =IF($A33<FECHA_EXPORT,NETWORKDAYS($A33+1,FECHA_EXPORT,FESTIVOS),0) -> 0 | AS33: =IF(AR33>=5,1,INDEX(CDF_INC,1,AR33+1)) -> 0.14 | AT33: =TASA_USADA+(TASA_INC-TASA_USADA)*Q_INC*(1-AS33)/(1-Q_INC*AS33) -> 0.65988707
A34: 46328 | P34: =B34+C34+D34 -> 0 | Q34: =AA34+AB34+AC34 -> 0 | R34: =B34*P1_PVP+C34*P2_PVP+D34*IF($A34<P3_DESDE,P3A_PVP,P3_PVP) -> 0 | S34: =IF(P34>0,R34/P34,"") | T34: =IF(P34>0,N34/P34,"") | U34: =IF(N34>0,R34/N34,"") | V34: =IF(E34+F34+G34+H34+I34+J34>0,(E34+F34+G34)/(E34+F34+G34+H34+I34+J34),"") | W34: =E34*(P1_PVP-P1_CPROD)+F34*(P2_PVP-P2_CPROD)+G34*(IF($A34<P3_DESDE,P3A_PVP,P3_PVP)-IF($A34<P3_DESDE,P3A_CPROD,P3_CPROD))-IF(ISNUMBER(L34),L34,E34*P1_LOG+F34*P2_LOG+G34*P3_LOG) -> 0 | X34: =W34-(E34*P1_IVAN+F34*P2_IVAN+G34*IF($A34<P3_DESDE,P3A_IVAN,P3_IVAN))-(H34+I34+J34)*(COSTE_DEV-IVA_DEV)-AM34-AO34 -> 0 | Y34: =AH34-AI34-AJ34-AK34-AL34-AM34-AO34 -> 0 | AA34: =MAX(0,B34-E34-H34) -> 0 | AB34: =MAX(0,C34-F34-I34) -> 0 | AC34: =MAX(0,D34-G34-J34) -> 0 | AD34: =E34+AA34*AQ34 -> 0 | AE34: =F34+AB34*AQ34 -> 0 | AF34: =G34+AC34*AQ34 -> 0 | AG34: =H34+I34+J34+(AA34+AB34+AC34)*(1-AQ34) -> 0 | AH34: =AD34*P1_PVP+AE34*P2_PVP+AF34*IF($A34<P3_DESDE,P3A_PVP,P3_PVP) -> 0 | AI34: =AD34*P1_CPROD+AE34*P2_CPROD+AF34*IF($A34<P3_DESDE,P3A_CPROD,P3_CPROD) -> 0 | AJ34: =IF(ISNUMBER(L34),L34,E34*P1_LOG+F34*P2_LOG+G34*P3_LOG)+IF(ISNUMBER(M34),M34,AA34*P1_LOG+AB34*P2_LOG+AC34*P3_LOG)*AQ34 -> 0 | AK34: =AG34*COSTE_DEV -> 0 | AL34: =AD34*P1_IVAN+AE34*P2_IVAN+AF34*IF($A34<P3_DESDE,P3A_IVAN,P3_IVAN)-AG34*IVA_DEV -> 0 | AM34: =N34*(1+RECARGO_ADS) -> 0 | AN34: =IF(ISNUMBER(L34),E34+F34+G34+AA34+AB34+AC34,0) -> 0 | AO34: =P34*COMISION -> 0 | AP34: =MIN(N(K34),Q34) -> 0 | AQ34: =IF(Q34>0,((Q34-AP34)*AT34+AP34*TASA_INC)/Q34,AT34) -> 0.65988707 | AR34: =IF($A34<FECHA_EXPORT,NETWORKDAYS($A34+1,FECHA_EXPORT,FESTIVOS),0) -> 0 | AS34: =IF(AR34>=5,1,INDEX(CDF_INC,1,AR34+1)) -> 0.14 | AT34: =TASA_USADA+(TASA_INC-TASA_USADA)*Q_INC*(1-AS34)/(1-Q_INC*AS34) -> 0.65988707
A35: 46329 | P35: =B35+C35+D35 -> 0 | Q35: =AA35+AB35+AC35 -> 0 | R35: =B35*P1_PVP+C35*P2_PVP+D35*IF($A35<P3_DESDE,P3A_PVP,P3_PVP) -> 0 | S35: =IF(P35>0,R35/P35,"") | T35: =IF(P35>0,N35/P35,"") | U35: =IF(N35>0,R35/N35,"") | V35: =IF(E35+F35+G35+H35+I35+J35>0,(E35+F35+G35)/(E35+F35+G35+H35+I35+J35),"") | W35: =E35*(P1_PVP-P1_CPROD)+F35*(P2_PVP-P2_CPROD)+G35*(IF($A35<P3_DESDE,P3A_PVP,P3_PVP)-IF($A35<P3_DESDE,P3A_CPROD,P3_CPROD))-IF(ISNUMBER(L35),L35,E35*P1_LOG+F35*P2_LOG+G35*P3_LOG) -> 0 | X35: =W35-(E35*P1_IVAN+F35*P2_IVAN+G35*IF($A35<P3_DESDE,P3A_IVAN,P3_IVAN))-(H35+I35+J35)*(COSTE_DEV-IVA_DEV)-AM35-AO35 -> 0 | Y35: =AH35-AI35-AJ35-AK35-AL35-AM35-AO35 -> 0 | AA35: =MAX(0,B35-E35-H35) -> 0 | AB35: =MAX(0,C35-F35-I35) -> 0 | AC35: =MAX(0,D35-G35-J35) -> 0 | AD35: =E35+AA35*AQ35 -> 0 | AE35: =F35+AB35*AQ35 -> 0 | AF35: =G35+AC35*AQ35 -> 0 | AG35: =H35+I35+J35+(AA35+AB35+AC35)*(1-AQ35) -> 0 | AH35: =AD35*P1_PVP+AE35*P2_PVP+AF35*IF($A35<P3_DESDE,P3A_PVP,P3_PVP) -> 0 | AI35: =AD35*P1_CPROD+AE35*P2_CPROD+AF35*IF($A35<P3_DESDE,P3A_CPROD,P3_CPROD) -> 0 | AJ35: =IF(ISNUMBER(L35),L35,E35*P1_LOG+F35*P2_LOG+G35*P3_LOG)+IF(ISNUMBER(M35),M35,AA35*P1_LOG+AB35*P2_LOG+AC35*P3_LOG)*AQ35 -> 0 | AK35: =AG35*COSTE_DEV -> 0 | AL35: =AD35*P1_IVAN+AE35*P2_IVAN+AF35*IF($A35<P3_DESDE,P3A_IVAN,P3_IVAN)-AG35*IVA_DEV -> 0 | AM35: =N35*(1+RECARGO_ADS) -> 0 | AN35: =IF(ISNUMBER(L35),E35+F35+G35+AA35+AB35+AC35,0) -> 0 | AO35: =P35*COMISION -> 0 | AP35: =MIN(N(K35),Q35) -> 0 | AQ35: =IF(Q35>0,((Q35-AP35)*AT35+AP35*TASA_INC)/Q35,AT35) -> 0.65988707 | AR35: =IF($A35<FECHA_EXPORT,NETWORKDAYS($A35+1,FECHA_EXPORT,FESTIVOS),0) -> 0 | AS35: =IF(AR35>=5,1,INDEX(CDF_INC,1,AR35+1)) -> 0.14 | AT35: =TASA_USADA+(TASA_INC-TASA_USADA)*Q_INC*(1-AS35)/(1-Q_INC*AS35) -> 0.65988707
A36: 46330 | P36: =B36+C36+D36 -> 0 | Q36: =AA36+AB36+AC36 -> 0 | R36: =B36*P1_PVP+C36*P2_PVP+D36*IF($A36<P3_DESDE,P3A_PVP,P3_PVP) -> 0 | S36: =IF(P36>0,R36/P36,"") | T36: =IF(P36>0,N36/P36,"") | U36: =IF(N36>0,R36/N36,"") | V36: =IF(E36+F36+G36+H36+I36+J36>0,(E36+F36+G36)/(E36+F36+G36+H36+I36+J36),"") | W36: =E36*(P1_PVP-P1_CPROD)+F36*(P2_PVP-P2_CPROD)+G36*(IF($A36<P3_DESDE,P3A_PVP,P3_PVP)-IF($A36<P3_DESDE,P3A_CPROD,P3_CPROD))-IF(ISNUMBER(L36),L36,E36*P1_LOG+F36*P2_LOG+G36*P3_LOG) -> 0 | X36: =W36-(E36*P1_IVAN+F36*P2_IVAN+G36*IF($A36<P3_DESDE,P3A_IVAN,P3_IVAN))-(H36+I36+J36)*(COSTE_DEV-IVA_DEV)-AM36-AO36 -> 0 | Y36: =AH36-AI36-AJ36-AK36-AL36-AM36-AO36 -> 0 | AA36: =MAX(0,B36-E36-H36) -> 0 | AB36: =MAX(0,C36-F36-I36) -> 0 | AC36: =MAX(0,D36-G36-J36) -> 0 | AD36: =E36+AA36*AQ36 -> 0 | AE36: =F36+AB36*AQ36 -> 0 | AF36: =G36+AC36*AQ36 -> 0 | AG36: =H36+I36+J36+(AA36+AB36+AC36)*(1-AQ36) -> 0 | AH36: =AD36*P1_PVP+AE36*P2_PVP+AF36*IF($A36<P3_DESDE,P3A_PVP,P3_PVP) -> 0 | AI36: =AD36*P1_CPROD+AE36*P2_CPROD+AF36*IF($A36<P3_DESDE,P3A_CPROD,P3_CPROD) -> 0 | AJ36: =IF(ISNUMBER(L36),L36,E36*P1_LOG+F36*P2_LOG+G36*P3_LOG)+IF(ISNUMBER(M36),M36,AA36*P1_LOG+AB36*P2_LOG+AC36*P3_LOG)*AQ36 -> 0 | AK36: =AG36*COSTE_DEV -> 0 | AL36: =AD36*P1_IVAN+AE36*P2_IVAN+AF36*IF($A36<P3_DESDE,P3A_IVAN,P3_IVAN)-AG36*IVA_DEV -> 0 | AM36: =N36*(1+RECARGO_ADS) -> 0 | AN36: =IF(ISNUMBER(L36),E36+F36+G36+AA36+AB36+AC36,0) -> 0 | AO36: =P36*COMISION -> 0 | AP36: =MIN(N(K36),Q36) -> 0 | AQ36: =IF(Q36>0,((Q36-AP36)*AT36+AP36*TASA_INC)/Q36,AT36) -> 0.65988707 | AR36: =IF($A36<FECHA_EXPORT,NETWORKDAYS($A36+1,FECHA_EXPORT,FESTIVOS),0) -> 0 | AS36: =IF(AR36>=5,1,INDEX(CDF_INC,1,AR36+1)) -> 0.14 | AT36: =TASA_USADA+(TASA_INC-TASA_USADA)*Q_INC*(1-AS36)/(1-Q_INC*AS36) -> 0.65988707
... A370: 46664 | P370: =B370+C370+D370 -> 0 | Q370: =AA370+AB370+AC370 -> 0 | R370: =B370*P1_PVP+C370*P2_PVP+D370*IF($A370<P3_DESDE,P3A_PVP,P3_PVP) -> 0 | S370: =IF(P370>0,R370/P370,"") | T370: =IF(P370>0,N370/P370,"") | U370: =IF(N370>0,R370/N370,"") | V370: =IF(E370+F370+G370+H370+I370+J370>0,(E370+F370+G370)/(E370+F370+G370+H370+I370+J370),"") | W370: =E370*(P1_PVP-P1_CPROD)+F370*(P2_PVP-P2_CPROD)+G370*(IF($A370<P3_DESDE,P3A_PVP,P3_PVP)-IF($A370<P3_DESDE,P3A_CPROD,P3_CPROD))-IF(ISNUMBER(L370),L370,E370*P1_LOG+F370*P2_LOG+G370*P3_LOG) -> 0 | X370: =W370-(E370*P1_IVAN+F370*P2_IVAN+G370*IF($A370<P3_DESDE,P3A_IVAN,P3_IVAN))-(H370+I370+J370)*(COSTE_DEV-IVA_DEV)-AM370-AO370 -> 0 | Y370: =AH370-AI370-AJ370-AK370-AL370-AM370-AO370 -> 0 | AA370: =MAX(0,B370-E370-H370) -> 0 | AB370: =MAX(0,C370-F370-I370) -> 0 | AC370: =MAX(0,D370-G370-J370) -> 0 | AD370: =E370+AA370*AQ370 -> 0 | AE370: =F370+AB370*AQ370 -> 0 | AF370: =G370+AC370*AQ370 -> 0 | AG370: =H370+I370+J370+(AA370+AB370+AC370)*(1-AQ370) -> 0 | AH370: =AD370*P1_PVP+AE370*P2_PVP+AF370*IF($A370<P3_DESDE,P3A_PVP,P3_PVP) -> 0 | AI370: =AD370*P1_CPROD+AE370*P2_CPROD+AF370*IF($A370<P3_DESDE,P3A_CPROD,P3_CPROD) -> 0 | AJ370: =IF(ISNUMBER(L370),L370,E370*P1_LOG+F370*P2_LOG+G370*P3_LOG)+IF(ISNUMBER(M370),M370,AA370*P1_LOG+AB370*P2_LOG+AC370*P3_LOG)*AQ370 -> 0 | AK370: =AG370*COSTE_DEV -> 0 | AL370: =AD370*P1_IVAN+AE370*P2_IVAN+AF370*IF($A370<P3_DESDE,P3A_IVAN,P3_IVAN)-AG370*IVA_DEV -> 0 | AM370: =N370*(1+RECARGO_ADS) -> 0 | AN370: =IF(ISNUMBER(L370),E370+F370+G370+AA370+AB370+AC370,0) -> 0 | AO370: =P370*COMISION -> 0 | AP370: =MIN(N(K370),Q370) -> 0 | AQ370: =IF(Q370>0,((Q370-AP370)*AT370+AP370*TASA_INC)/Q370,AT370) -> 0.65988707 | AR370: =IF($A370<FECHA_EXPORT,NETWORKDAYS($A370+1,FECHA_EXPORT,FESTIVOS),0) -> 0 | AS370: =IF(AR370>=5,1,INDEX(CDF_INC,1,AR370+1)) -> 0.14 | AT370: =TASA_USADA+(TASA_INC-TASA_USADA)*Q_INC*(1-AS370)/(1-Q_INC*AS370) -> 0.65988707

Sheet Gastos
A1: Otros gastos
A2: Todo lo que no es producto, envío ni Ads: Shopify, apps, dominio, muestras, gestoría...
A3: Ejemplo de fila: 01/10/2026 | Shopify Basic | Suscripciones | 36,00 € | mensual
A4: Fecha | B4: Concepto | C4: Categoría | D4: Importe (€) | E4: Notas

Sheet Config
B1: Configuración · CeraLux
B2: Celdas azules con fondo amarillo = editables. Todo lo demás se calcula solo.
B4: Unit economics por pack | C4: Pack 1 ud | D4: Pack 2 uds | E4: Pack 3 + aspirador | F4: De dónde sale | G4: Pack 3 antes
B5: PVP contra reembolso (IVA incl.) | C5: 29.99 | D5: 39.99 | E5: 59.99 | F5: Importe que cobra el repartidor. Dato de Alec. | G5: 49.99
B6: Unidades en el pack | C6: 1 | D6: 2 | E6: 3 | F6: Dato de Alec. | G6: 3
B7: Coste producto por unidad (sin IVA) | C7: 1.99 | D7: 1.99 | E7: 3.3867 | F7: Export del almacén: 1,99 € por spray (sin IVA). Pack 3 desde el 15/10: (3 × 1,99 + aspirador 4,19) / 3. | G7: 1.99
B8: Coste de envío estándar (sin IVA) | C8: 7.55 | D8: 7.55 | E8: 7.55 | F8: Envío medio que te cobra Dropi al confirmar (7,55 € según la cartera). Si el día tiene envío real del export, se usa el real (6,75-8,06 €). | G8: 7.55
B9: Coste producto (IVA incl.) | C9: =C6*C7*(1+IVA_PROD) -> 2.4079 | D9: =D6*D7*(1+IVA_PROD) -> 4.8158 | E9: =E6*E7*(1+IVA_PROD) -> 12.293721 | F9: Uds × coste × (1 + IVA producto). | G9: =G6*G7*(1+IVA_PROD) -> 7.2237
B10: Coste total del pedido | C10: =C9+C8 -> 9.9579 | D10: =D9+D8 -> 12.3658 | E10: =E9+E8 -> 19.843721 | F10: Cuadra con 'Coste total pedido' del almacén: 10,47 €, 12,88 € y 20,35 € (Pack 3 + aspirador; 15,28 € el de antes). | G10: =G9+G8 -> 14.7737
B11: Beneficio dropshipper por pedido ENTREGADO | C11: =C5-C10 -> 20.0321 | D11: =D5-D10 -> 27.6242 | E11: =E5-E10 -> 40.146279 | F11: Lo que te liquida el almacén: 19,52 €, 27,11 € y 39,64 € (34,71 € el Pack 3 de antes). | G11: =G5-G10 -> 35.2163
B12: IVA repercutido (dentro del PVP) | C12: =C5*IVA_VENTAS/(1+IVA_VENTAS) -> 5.204876 | D12: =D5*IVA_VENTAS/(1+IVA_VENTAS) -> 6.9404132 | E12: =E5*IVA_VENTAS/(1+IVA_VENTAS) -> 10.411488 | F12: PVP × 21/121. | G12: =G5*IVA_VENTAS/(1+IVA_VENTAS) -> 8.6759504
B13: IVA soportado deducible | C13: =C6*C7*IVA_PROD+IF(LOG_IVA=1,C8*IVA_VENTAS/(1+IVA_VENTAS),0) -> 0.4179 | D13: =D6*D7*IVA_PROD+IF(LOG_IVA=1,D8*IVA_VENTAS/(1+IVA_VENTAS),0) -> 0.8358 | E13: =E6*E7*IVA_PROD+IF(LOG_IVA=1,E8*IVA_VENTAS/(1+IVA_VENTAS),0) -> 2.133621 | F13: IVA del producto (+ IVA del envío solo si en Parámetros dices que lo lleva). | G13: =G6*G7*IVA_PROD+IF(LOG_IVA=1,G8*IVA_VENTAS/(1+IVA_VENTAS),0) -> 1.2537
B14: IVA neto a pagar por pedido entregado | C14: =IF(APLICA_IVA=1,C12-C13,0) -> 0 | D14: =IF(APLICA_IVA=1,D12-D13,0) -> 0 | E14: =IF(APLICA_IVA=1,E12-E13,0) -> 0 | F14: 0 si en Parámetros pones NO al IVA. | G14: =IF(APLICA_IVA=1,G12-G13,0) -> 0
B15: Beneficio neto por pedido entregado (antes de Ads) | C15: =C11-C14 -> 20.0321 | D15: =D11-D14 -> 27.6242 | E15: =E11-E14 -> 40.146279 | F15: Lo que te queda de verdad por cada entrega. | G15: =G11-G14 -> 35.2163
B16: Pack 3 actual vigente desde (antes: columna G) | C16: 46310
B17: Parámetros | C17: Valor | F17: Qué significa
B18: IVA de las ventas | C18: 0.21 | F18: IVA general en España.
B19: IVA del producto (lo aplica el almacén) | C19: 0.21 | F19: Coste producto × 1,21 en el export.
B20: ¿Descontar el IVA del beneficio? | C20: NO | F20: SÍ si facturas como autónomo o SL (Hacienda se queda ~4,8 € por Pack 1 entregado). NO solo para ver el bruto.
B21: ¿El envío lleva IVA deducible? | C21: NO | F21: NO: el export dice 'Coste de envío (SIN IVA)' y el coste total no le suma IVA, así que no hay IVA que deducir.
B22: Coste por pedido devuelto | C22: 7.55 | F22: El envío que ya pagaste al confirmar (7,55 € de media): la vuelta no se cobra aparte y el producto vuelve.
B23: Recargo sobre el gasto en Ads | C23: 0 | F23: 0% si Meta factura sin IVA (alta en ROI) o lo deduces. 21% si te cobran IVA y no lo recuperas.
B24: Tasa de entrega estimada (pedidos sin incidencia) | C24: 0.8 | F24: Para proyectar los pendientes normales mientras no tengas datos propios.
B25: Pedidos resueltos para usar tu tasa real | C25: 30 | F25: Con estos entregados + devueltos SIN incidencia, el libro pasa a usar tu tasa real.
B26: % de Pack 2 (C) y de Pack 3 (D) estimado, sin datos | C26: 0.3 | D26: 0.05 | F26: Solo se usa hasta que haya pedidos.
B27: Objetivo de beneficio neto mensual | C27: 10000 | F27: La meta: 10.000 €/mes.
B28: Fecha de inicio | C28: 46300 | F28: Primer día del Diario y del resumen mensual.
B29: Cuenta publicitaria Meta | C29: HeatioShop (26290722800581380) | F29: De aquí sale el gasto en Ads (conector de Meta).
B30: Filtro de campañas | C30: CeraLux | F30: Solo cuenta campañas cuyo nombre contiene este texto.
B31: Comisión del almacén por pedido confirmado | C31: 0.95 | F31: Dropi cobra 0,95 € por cada pedido confirmado, se entregue o se devuelva.
B32: Calculado con tus datos | C32: Valor | F32: Cómo se calcula
B33: IVA aplicado (1 = sí) | C33: =IF(C20="SÍ",1,0) -> 0
B34: Envío con IVA deducible (1 = sí) | C34: =IF(C21="SÍ",1,0) -> 0
B35: IVA recuperable por devolución | C35: =IF(AND(APLICA_IVA=1,LOG_IVA=1),C22*IVA_VENTAS/(1+IVA_VENTAS),0) -> 0
B36: Coste neto por devolución | C36: =C22-C35 -> 7.55
B37: Pedidos resueltos (entregados + devueltos) | C37: =(SUM(Diario!$E$6:$E$370)+SUM(Diario!$F$6:$F$370)+SUM(Diario!$G$6:$G$370))+(SUM(Diario!$H$6:$H$370)+SUM(Diario!$I$6:$I$370)+SUM(Diario!$J$6:$J$370)) -> 108 | F37: Histórico.
B38: Tasa de entrega real | C38: =IF(C37>0,(SUM(Diario!$E$6:$E$370)+SUM(Diario!$F$6:$F$370)+SUM(Diario!$G$6:$G$370))/C37,"") -> 0.68518519 | F38: Entregados ÷ (entregados + devueltos).
B39: Tasa de entrega USADA (pendientes sin incidencia) | C39: =IF(AND(C37-C52>=C25,C55<>""),C55,C24) -> 0.94117647 | F39: La real sin incidencias si hay suficientes resueltos; si no, la estimada. Las incidencias van con la suya (C54).
B40: % de Pack 2 (C) y de Pack 3 (D) real | C40: =IF(SUM(Diario!$P$6:$P$370)>0,SUM(Diario!$C$6:$C$370)/SUM(Diario!$P$6:$P$370),"") -> 0.35849057 | D40: =IF(SUM(Diario!$P$6:$P$370)>0,SUM(Diario!$D$6:$D$370)/SUM(Diario!$P$6:$P$370),"") -> 0.081761006 | F40: Upsell real.
B41: % de Pack 2 (C) y de Pack 3 (D) usado | C41: =IF(C40="",C26,C40) -> 0.35849057 | D41: =IF(D40="",D26,D40) -> 0.081761006
B42: Envío medio real por pedido (sin IVA) | C42: =IF(SUM(Diario!$AN$6:$AN$370)>0,(SUM(Diario!$L$6:$L$370)+SUM(Diario!$M$6:$M$370))/SUM(Diario!$AN$6:$AN$370),"") -> 7.25144 | F42: Media de los envíos reales del export del almacén.
B43: Ticket medio esperado | C43: =(1-C41-D41)*C5+C41*D5+D41*E5 -> 36.027736
B44: Beneficio neto medio por pedido entregado | C44: =(1-C41-D41)*(C5-C9-IF(C42="",C8,C42)-C14)+C41*(D5-D9-IF(C42="",D8,C42)-D14)+D41*(E5-E9-IF(C42="",E8,C42)-E14) -> 24.696912 | F44: Mezcla de packs, con tu envío medio real.
B45: Beneficio esperado por pedido confirmado (antes de Ads) | C45: =TASA_BE*C44-(1-TASA_BE)*C36-COMISION -> 11.851932 | F45: Tasa final esperada (C58) × beneficio por entrega − (1 − tasa) × coste de devolución − comisión del almacén.
B46: CPA break-even (máximo que puedes pagar por pedido) | C46: =C45/(1+RECARGO_ADS) -> 11.851932 | F46: Por encima de este CPA pierdes dinero.
B47: ROAS break-even | C47: =IF(C46>0,C43/C46,"") -> 3.0398196 | F47: Facturación bruta ÷ Ads mínima para no perder.
B49: Incidencias (tablero del equipo) | C49: Valor | F49: Qué significa
B50: Tasa de entrega estimada de las incidencias | C50: 0.35 | F50: Punto de partida (35%). Se va corrigiendo con las incidencias que el equipo cierra.
B51: Peso de la estimación (en incidencias) | C51: 10 | F51: La estimación cuenta como 10 incidencias: con pocas cerradas manda ella, con muchas manda lo real.
B52: Incidencias cerradas (entregadas + devueltas) | C52: 40 | F52: Del tablero de Incidencias del dashboard (lo rellena Claude al regenerar).
B53: … de ellas entregadas | C53: 10
B54: Tasa de entrega USADA para incidencias | C54: =(C53+C50*C51)/(C52+C51) -> 0.27 | F54: (entregadas + estimada × peso) ÷ (cerradas + peso).
B55: Tasa de entrega real sin incidencias | C55: =IF(C37-C52>0,((SUM(Diario!$E$6:$E$370)+SUM(Diario!$F$6:$F$370)+SUM(Diario!$G$6:$G$370))-C53)/(C37-C52),"") -> 0.94117647 | F55: (Entregados − incidencias entregadas) ÷ (resueltos − incidencias cerradas).
B56: Pendientes ahora | C56: =SUM(Diario!$Q$6:$Q$370) -> 51
B57: … de ellos en incidencia | C57: =SUM(Diario!$AP$6:$AP$370) -> 29
B58: Tasa final esperada (la del break-even) | C58: =IF(C37+C56>0,((SUM(Diario!$E$6:$E$370)+SUM(Diario!$F$6:$F$370)+SUM(Diario!$G$6:$G$370))+SUMPRODUCT(Diario!$Q$6:$Q$370,Diario!$AQ$6:$AQ$370))/(C37+C56),C39) -> 0.6311281 | F58: (Entregados + pendientes × su tasa) ÷ todo lo enviado. Es la que manda en el CPA break-even.
B60: Pedidos recientes | C60: Valor | F60: Qué significa
B61: % de pedidos que acaban en incidencia | C61: 0.4562 | F61: Incidencias del tablero ÷ pedidos (corrigiendo los días recientes). Lo rellena Claude al regenerar.
B62: Fecha del último Excel del almacén | C62: 46318 | F62: La edad de cada pedido se cuenta hasta aquí.
B63: Incidencias ya visibles a 0 / 1 / 2 / 3 / 4 días laborables | C63: 0.14 | D63: 0.3 | E63: 0.7 | F63: 0.92 | G63: 0.98
B64: Festivos nacionales (sin entregas ni abonos) | C64: 46307 | D64: 46364 | E64: 46381 | F64: 46388 | G64: 46393 | H64: 46472 | I64: 46672 | J64: 46692 | K64: 46727 | L64: 46729
B65: Tasa de entrega de un pedido nuevo | C65: =(1-C61)*C39+C61*C54 -> 0.63498576 | F65: (1 − % incidencia) × tasa sin incidencia + % incidencia × tasa de incidencias.

Sheet Guía
B1: Cómo usar este libro
B4: Hojas
B5: Dashboard: tus números del periodo que elijas (celdas Desde / Hasta). Todo se calcula solo.
B6: Diario: una fila por día de pedido, con pedidos y estados de cada pack.
B7: Gastos: Shopify, apps, muestras, gestoría... todo lo que no es producto, envío ni Ads.
B8: Config: precios, costes de tus 3 packs y supuestos. Si el almacén cambia tarifas, se cambia aquí.
B10: Rutina diaria (2 minutos)
B11: 1. Descarga el Excel de pedidos del almacén y pásaselo a Claude. Lo importa entero: pedidos por pack, estados, incidencias y coste de envío real. Sin datos personales: solo totales por día.
B12: 2. Si no tienes el export a mano, basta con decir "hoy 9 Pack 1, 4 Pack 2 y 1 Pack 3" o apuntarlo en el dashboard web.
B13: 3. El gasto de Meta Ads lo trae Claude del conector (y el dashboard web lo lee en directo).
B15: Estados del almacén
B16: Preparado, En ruta e Incidencia = pendientes. Una incidencia NO es venta perdida hasta que pasa a Devuelto.
... B37: Azul sobre amarillo = dato que escribes tú. Negro = fórmula. Verde = viene de otra hoja.
